Workbook

Sheet Seguimiento OIT
A1: Requerimientos OIT
A2: Datos del Requerimiento | Q2: Seguimiento de atención de requerimiento y estado del servicio | AH2: Gestión de Renovación
A3: Código | B3: Estado_Tablero | C3: Requerimiento asociado | D3: Indicador PAC | E3: Tipo de Procedimiento | F3: Tipo requerimiento | G3: Tipo de adquisición | H3: Denominación | I3: Hoja de Ruta asociadas | J3: Servicios - Bienes incluidos | K3: Área OIT | L3: Coordinador | M3: Responsable | N3: Área Usuaria MEF | O3: Monto | P3: Fecha de solicitud | Q3: Estado_Requerimiento/Contrato | R3: Area_asignada | S3: Fecha de ultimo estado | T3: Cantidad_dias_ en área asignada | U3: Documento de contratación | V3: Nro de documento | W3: Fecha de suscripción o notificación | X3: Empresa(s) contratada | Y3: Reponsable de ejecución | Z3: Estado_servicio | AA3: Fecha de inicio_vigencia | AB3: Fecha de fin_vigencia | AC3: Vigencia | AD3: Dias sin servicio | AE3: Comentarios_atencion_requerimiento | AF3: Comentarios_Servicio (Ejecución) | AG3: Enlace de Repositorio | AH3: ¿Requiere Renovar? | AI3: Estado renovación | AJ3: HR renovación | AK3: Fecha_Inicio_Renov | AL3: Fecha_Fin_Renov
A4: REQ-2026-0001 | B4: =IF(OR(Q4="Desistido",Q4="No corresponde Atención OGTI",Q4="Para reformulación",Q4="Paralizado",Q4="-",Z4="Renovado",AND(AH4="NO",Z4="Culminado")),"NO","SI") -> NO | C4: - | D4: NO | E4: Contratación Directa | F4: Renovación | G4: Bienes | H4: Adquisición de licencias de software para Central Telefónica destinadas al uso de softphone para la Defensoría del Contribuyente y Usuario Aduanero del MEF. | I4: 074877-2026 | J4: Licencias Softphone para central telefonica | K4: Telefonía | L4: Isaias Bolivar Reaño | M4: Isaias Bolivar Reaño | N4: Defensoría del Contribuyente y Usuario Aduanero | O4: 6808.64 | P4: 46113 | Q4: Ejecutado | R4: - | S4: - | T4: =IFERROR(IF(OR(Q4="Ejecutado",Q4="No corresponde atención OGTI",Q4="Desistido",Q4="-",Q4="Para reformulación"),"-",IF(OR(S4="-",S4=""),"Falta fecha_estado",NETWORKDAYS(S4,TODAY(),{"02/04/2026";"03/04/2026";"30/06/2026"}))),"-") -> - | U4: Orden de Compra | V4: 0000149-2026 | W4: 46154 | X4: E-BUSINESS DISTRIBUTION PERU S.A | Y4: Isaias Bolivar Reaño | Z4: =IFERROR(IF(Q4="-","-",IF(Q4="Proceso de implementación/Activación/Entrega","Proceso de implementación/Activación/Entrega",IF(OR(Q4="Desistido",Q4="No corresponde atención OGTI",Q4="Para reformulación"),Q4,IF(AND(Q4="Ejecutado",AA4="No aplica",AB4="No Aplica"),"Culminado",IF(Q4="Ejecutado",IF(AND(AC4="-",G4="Bienes"),"Culminado",IF(AC4="-","Falta informacion",IF(AND(AB4-TODAY()>=0,AB4-TODAY()<=90),"Vigente_por vencer",IF(AND(AH4<>"SI",AB4<TODAY()),"Culminado",IF(AND(AH4="SI",AB4<TODAY(),OR(AK4="Sin Registro",AL4="Sin Registro")),"Vencido",IF(AND(AH4="SI",AB4<TODAY(),AK4>AA4,AL4>AB4),"Renovado","Vigente")))))),"En tramite"))))),"-") -> Culminado | AA4: - | AB4: - | AC4: =IFERROR(IF(OR(AA4="-",AA4="",AB4="-",AB4=""),"-",CONCATENATE('Seguimiento OIT'!AB4-'Seguimiento OIT'!AA4+1," dias")),"-") -> - | AD4: =IFERROR(IF(Z4="Vencido",(TODAY()-AB4)+1,"-"),"-") -> - | AE4: - | AF4: Licencias no tienen vigencia. Garantia del 12-05-26 al 11-05-27) | AG4: https://mefgobpe1.sharepoint.com/:f:/t/DireccindelaOficinadeInfraestructuraTecnolgica/IgAMjzQ2CwrsSrZrpbNNuH6TAexSvIZkaygR0PcCrH9EkUg?e=bpppHT | AH4: NO | AI4: =IFERROR(IF(AH4="SI",VLOOKUP(A4,$C$4:$AL$151,15,FALSE),"-"),"Sin tramite") -> - | AJ4: =IFERROR(IF(AH4="SI",VLOOKUP(A4,$C$4:$AL$151,7,FALSE),"-"),"Sin HR") -> - | AK4: =IF(AH4="SI",IFERROR(IF(VLOOKUP(A4,$C$4:$AL$151,25,FALSE)="","Sin registro",VLOOKUP(A4,$C$4:$AL$151,25,FALSE)),"Sin registro"),"-") -> - | AL4: =IF(AH4="SI",IFERROR(IF(VLOOKUP(A4,$C$4:$AL$151,26,FALSE)="","Sin registro",VLOOKUP(A4,$C$4:$AL$151,26,FALSE)),"Sin registro"),"-") -> -
A5: REQ-2026-0002 | B5: =IF(OR(Q5="Desistido",Q5="No corresponde Atención OGTI",Q5="Para reformulación",Q5="Paralizado",Q5="-",Z5="Renovado",AND(AH5="NO",Z5="Culminado")),"NO","SI") -> NO | C5: - | D5: NO | E5: Contratación Directa | F5: Nuevo requerimiento | G5: Bienes | H5: Adquisición de audífonos para la Defensoría del Contribuyente y Usuario Aduanero del MEF | I5: 074848-2026 | J5: Audifonos (12 unidades) | K5: Telefonía | L5: Isaias Bolivar Reaño | M5: Isaias Bolivar Reaño | N5: Defensoría del Contribuyente y Usuario Aduanero | O5: 1192.2 | P5: 46113 | Q5: Ejecutado | R5: - | S5: - | T5: =IFERROR(IF(OR(Q5="Ejecutado",Q5="No corresponde atención OGTI",Q5="Desistido",Q5="-",Q5="Para reformulación"),"-",IF(OR(S5="-",S5=""),"Falta fecha_estado",NETWORKDAYS(S5,TODAY(),{"02/04/2026";"03/04/2026";"30/06/2026"}))),"-") -> - | U5: Orden de Compra | V5: 0000115-2026 | W5: 46129 | X5: VML COMPUTER S.A.C. | Y5: Isaias Bolivar Reaño | Z5: =IFERROR(IF(Q5="-","-",IF(Q5="Proceso de implementación/Activación/Entrega","Proceso de implementación/Activación/Entrega",IF(OR(Q5="Desistido",Q5="No corresponde atención OGTI",Q5="Para reformulación"),Q5,IF(AND(Q5="Ejecutado",AA5="No aplica",AB5="No Aplica"),"Culminado",IF(Q5="Ejecutado",IF(AND(AC5="-",G5="Bienes"),"Culminado",IF(AC5="-","Falta informacion",IF(AND(AB5-TODAY()>=0,AB5-TODAY()<=90),"Vigente_por vencer",IF(AND(AH5<>"SI",AB5<TODAY()),"Culminado",IF(AND(AH5="SI",AB5<TODAY(),OR(AK5="Sin Registro",AL5="Sin Registro")),"Vencido",IF(AND(AH5="SI",AB5<TODAY(),AK5>AA5,AL5>AB5),"Renovado","Vigente")))))),"En tramite"))))),"-") -> Culminado | AA5: - | AB5: - | AC5: =IFERROR(IF(OR(AA5="-",AA5="",AB5="-",AB5=""),"-",CONCATENATE('Seguimiento OIT'!AB5-'Seguimiento OIT'!AA5+1," dias")),"-") -> - | AD5: =IFERROR(IF(Z5="Vencido",(TODAY()-AB5)+1,"-"),"-") -> - | AE5: - | AF5: Conforrmidad HR 090493-2026 | AG5: https://mefgobpe1.sharepoint.com/:f:/t/DireccindelaOficinadeInfraestructuraTecnolgica/IgAMjzQ2CwrsSrZrpbNNuH6TAexSvIZkaygR0PcCrH9EkUg?e=bpppHT | AH5: NO | AI5: =IFERROR(IF(AH5="SI",VLOOKUP(A5,$C$4:$AL$151,15,FALSE),"-"),"Sin tramite") -> - | AJ5: =IFERROR(IF(AH5="SI",VLOOKUP(A5,$C$4:$AL$151,7,FALSE),"-"),"Sin HR") -> - | AK5: =IF(AH5="SI",IFERROR(IF(VLOOKUP(A5,$C$4:$AL$151,25,FALSE)="","Sin registro",VLOOKUP(A5,$C$4:$AL$151,25,FALSE)),"Sin registro"),"-") -> - | AL5: =IF(AH5="SI",IFERROR(IF(VLOOKUP(A5,$C$4:$AL$151,26,FALSE)="","Sin registro",VLOOKUP(A5,$C$4:$AL$151,26,FALSE)),"Sin registro"),"-") -> -
A6: REQ-2026-0003 | B6: =IF(OR(Q6="Desistido",Q6="No corresponde Atención OGTI",Q6="Para reformulación",Q6="Paralizado",Q6="-",Z6="Renovado",AND(AH6="NO",Z6="Culminado")),"NO","SI") -> SI | C6: - | D6: NO | E6: Contratación Directa | F6: Nuevo requerimiento | G6: Servicios | H6: Contratación de una Cuenta Teams Room para la Sala de Reuniones de la Dirección General de Abastecimiento | I6: *082319-2026 (Requerimiento) *033456-2026 (Antecedente 01) *178871-2025 (Antecedente 02) | J6: Teams Room | K6: Soporte Tecnico | L6: Napoleon Alva Vasquez | M6: Ronald Yrupailla Diaz | N6: Dirección General de Abastecimiento | O6: 2315 | P6: 46125 | Q6: Ejecutado | R6: - | S6: - | T6: =IFERROR(IF(OR(Q6="Ejecutado",Q6="No corresponde atención OGTI",Q6="Desistido",Q6="-",Q6="Para reformulación"),"-",IF(OR(S6="-",S6=""),"Falta fecha_estado",NETWORKDAYS(S6,TODAY(),{"02/04/2026";"03/04/2026";"30/06/2026"}))),"-") -> - | U6: Orden de Servicio | V6: 0002117-2026 | W6: 46139 | X6: DAILY TECHNOLOGY S.A.C | Y6: Ronald Yrupailla Diaz | Z6: =IFERROR(IF(Q6="-","-",IF(Q6="Proceso de implementación/Activación/Entrega","Proceso de implementación/Activación/Entrega",IF(OR(Q6="Desistido",Q6="No corresponde atención OGTI",Q6="Para reformulación"),Q6,IF(AND(Q6="Ejecutado",AA6="No aplica",AB6="No Aplica"),"Culminado",IF(Q6="Ejecutado",IF(AND(AC6="-",G6="Bienes"),"Culminado",IF(AC6="-","Falta informacion",IF(AND(AB6-TODAY()>=0,AB6-TODAY()<=90),"Vigente_por vencer",IF(AND(AH6<>"SI",AB6<TODAY()),"Culminado",IF(AND(AH6="SI",AB6<TODAY(),OR(AK6="Sin Registro",AL6="Sin Registro")),"Vencido",IF(AND(AH6="SI",AB6<TODAY(),AK6>AA6,AL6>AB6),"Renovado","Vigente")))))),"En tramite"))))),"-") -> Vigente | AA6: 46141 | AB6: 46505 | AC6: =IFERROR(IF(OR(AA6="-",AA6="",AB6="-",AB6=""),"-",CONCATENATE('Seguimiento OIT'!AB6-'Seguimiento OIT'!AA6+1," dias")),"-") -> 365 dias | AD6: =IFERROR(IF(Z6="Vencido",(TODAY()-AB6)+1,"-"),"-") -> - | AE6: - | AF6: Conforrmidad HR 096621-2026 | AG6: https://mefgobpe1.sharepoint.com/:f:/t/DireccindelaOficinadeInfraestructuraTecnolgica/IgAZXGbnCkU6TontNlj_5zofAbPXwRd4mqf2ka9BS6cc7LU?e=Ejjkds | AH6: NO | AI6: =IFERROR(IF(AH6="SI",VLOOKUP(A6,$C$4:$AL$151,15,FALSE),"-"),"Sin tramite") -> - | AJ6: =IFERROR(IF(AH6="SI",VLOOKUP(A6,$C$4:$AL$151,7,FALSE),"-"),"Sin HR") -> - | AK6: =IF(AH6="SI",IFERROR(IF(VLOOKUP(A6,$C$4:$AL$151,25,FALSE)="","Sin registro",VLOOKUP(A6,$C$4:$AL$151,25,FALSE)),"Sin registro"),"-") -> - | AL6: =IF(AH6="SI",IFERROR(IF(VLOOKUP(A6,$C$4:$AL$151,26,FALSE)="","Sin registro",VLOOKUP(A6,$C$4:$AL$151,26,FALSE)),"Sin registro"),"-") -> -
A7: REQ-2026-0004 | B7: =IF(OR(Q7="Desistido",Q7="No corresponde Atención OGTI",Q7="Para reformulación",Q7="Paralizado",Q7="-",Z7="Renovado",AND(AH7="NO",Z7="Culminado")),"NO","SI") -> NO | C7: - | D7: NO | E7: Contratación Directa | F7: Nuevo requerimiento | G7: Bienes | H7: Adquisición de puntero laser inalámbrico para presentación de diapositivas y extensor inalámbrico de señal HDMI/VGA | I7: *082266-2026 (Requerimiento) *060008-2026 (Apoyo presupuestal) | J7: *Puntero Laser USB *Extensor inalámbrico de señal HDMI/VGA | K7: Soporte Tecnico | L7: Napoleon Alva Vasquez | M7: Ronald Yrupailla Diaz | N7: Dirección General de Abastecimiento | O7: 1490 | P7: 46125 | Q7: Ejecutado | R7: - | S7: - | T7: =IFERROR(IF(OR(Q7="Ejecutado",Q7="No corresponde atención OGTI",Q7="Desistido",Q7="-",Q7="Para reformulación"),"-",IF(OR(S7="-",S7=""),"Falta fecha_estado",NETWORKDAYS(S7,TODAY(),{"02/04/2026";"03/04/2026";"30/06/2026"}))),"-") -> - | U7: Orden de Compra | V7: 0000114-2026 | W7: 46128 | X7: ELECTRONICA MUSICAL SOCIEDAD ANONIMA CERRADA | Y7: Ronald Yrupailla Diaz | Z7: =IFERROR(IF(Q7="-","-",IF(Q7="Proceso de implementación/Activación/Entrega","Proceso de implementación/Activación/Entrega",IF(OR(Q7="Desistido",Q7="No corresponde atención OGTI",Q7="Para reformulación"),Q7,IF(AND(Q7="Ejecutado",AA7="No aplica",AB7="No Aplica"),"Culminado",IF(Q7="Ejecutado",IF(AND(AC7="-",G7="Bienes"),"Culminado",IF(AC7="-","Falta informacion",IF(AND(AB7-TODAY()>=0,AB7-TODAY()<=90),"Vigente_por vencer",IF(AND(AH7<>"SI",AB7<TODAY()),"Culminado",IF(AND(AH7="SI",AB7<TODAY(),OR(AK7="Sin Registro",AL7="Sin Registro")),"Vencido",IF(AND(AH7="SI",AB7<TODAY(),AK7>AA7,AL7>AB7),"Renovado","Vigente")))))),"En tramite"))))),"-") -> Culminado | AA7: - | AB7: - | AC7: =IFERROR(IF(OR(AA7="-",AA7="",AB7="-",AB7=""),"-",CONCATENATE('Seguimiento OIT'!AB7-'Seguimiento OIT'!AA7+1," dias")),"-") -> - | AD7: =IFERROR(IF(Z7="Vencido",(TODAY()-AB7)+1,"-"),"-") -> - | AE7: - | AF7: Conforrmidad HR 090442-2026 | AG7: https://mefgobpe1.sharepoint.com/:f:/t/DireccindelaOficinadeInfraestructuraTecnolgica/IgDhJgwKBPIITJaNuzbU7fwMAWJyPbtURdvydZOXH0YHWGA?e=5X4nby | AH7: NO | AI7: =IFERROR(IF(AH7="SI",VLOOKUP(A7,$C$4:$AL$151,15,FALSE),"-"),"Sin tramite") -> - | AJ7: =IFERROR(IF(AH7="SI",VLOOKUP(A7,$C$4:$AL$151,7,FALSE),"-"),"Sin HR") -> - | AK7: =IF(AH7="SI",IFERROR(IF(VLOOKUP(A7,$C$4:$AL$151,25,FALSE)="","Sin registro",VLOOKUP(A7,$C$4:$AL$151,25,FALSE)),"Sin registro"),"-") -> - | AL7: =IF(AH7="SI",IFERROR(IF(VLOOKUP(A7,$C$4:$AL$151,26,FALSE)="","Sin registro",VLOOKUP(A7,$C$4:$AL$151,26,FALSE)),"Sin registro"),"-") -> -
A8: REQ-2026-0005 | B8: =IF(OR(Q8="Desistido",Q8="No corresponde Atención OGTI",Q8="Para reformulación",Q8="Paralizado",Q8="-",Z8="Renovado",AND(AH8="NO",Z8="Culminado")),"NO","SI") -> NO | C8: - | D8: NO | E8: Contratación Directa | F8: Nuevo requerimiento | G8: Bienes | H8: Adquisición de Pantalla Interactiva para la Dirección General de Presupuesto Público (DGPP). | I8: 048517-2026 | J8: Pantalla interactiva | K8: Soporte Tecnico | L8: Napoleon Alva Vasquez | M8: Ronald Yrupailla Diaz | N8: Dirección General de Presupuesto Público | O8: 23529.29 | P8: 46086 | Q8: Ejecutado | R8: - | S8: - | T8: =IFERROR(IF(OR(Q8="Ejecutado",Q8="No corresponde atención OGTI",Q8="Desistido",Q8="-",Q8="Para reformulación"),"-",IF(OR(S8="-",S8=""),"Falta fecha_estado",NETWORKDAYS(S8,TODAY(),{"02/04/2026";"03/04/2026";"30/06/2026"}))),"-") -> - | U8: Orden de Compra | V8: 0000077-2026 | W8: 46107 | X8: COMPU CENTER BUSSINES S.A.C. | Y8: Napoleon Alva Vasquez | Z8: =IFERROR(IF(Q8="-","-",IF(Q8="Proceso de implementación/Activación/Entrega","Proceso de implementación/Activación/Entrega",IF(OR(Q8="Desistido",Q8="No corresponde atención OGTI",Q8="Para reformulación"),Q8,IF(AND(Q8="Ejecutado",AA8="No aplica",AB8="No Aplica"),"Culminado",IF(Q8="Ejecutado",IF(AND(AC8="-",G8="Bienes"),"Culminado",IF(AC8="-","Falta informacion",IF(AND(AB8-TODAY()>=0,AB8-TODAY()<=90),"Vigente_por vencer",IF(AND(AH8<>"SI",AB8<TODAY()),"Culminado",IF(AND(AH8="SI",AB8<TODAY(),OR(AK8="Sin Registro",AL8="Sin Registro")),"Vencido",IF(AND(AH8="SI",AB8<TODAY(),AK8>AA8,AL8>AB8),"Renovado","Vigente")))))),"En tramite"))))),"-") -> Culminado | AA8: - | AB8: - | AC8: =IFERROR(IF(OR(AA8="-",AA8="",AB8="-",AB8=""),"-",CONCATENATE('Seguimiento OIT'!AB8-'Seguimiento OIT'!AA8+1," dias")),"-") -> - | AD8: =IFERROR(IF(Z8="Vencido",(TODAY()-AB8)+1,"-"),"-") -> - | AE8: - | AF8: Conforrmidad HR 081407-2026 | AG8: https://mefgobpe1.sharepoint.com/:f:/t/DireccindelaOficinadeInfraestructuraTecnolgica/IgAuQUOZDJlsS52DtyJNBD8aAQ9zOl_Ud_ejgD_u3ufWXIQ?e=YafDUj | AH8: NO | AI8: =IFERROR(IF(AH8="SI",VLOOKUP(A8,$C$4:$AL$151,15,FALSE),"-"),"Sin tramite") -> - | AJ8: =IFERROR(IF(AH8="SI",VLOOKUP(A8,$C$4:$AL$151,7,FALSE),"-"),"Sin HR") -> - | AK8: =IF(AH8="SI",IFERROR(IF(VLOOKUP(A8,$C$4:$AL$151,25,FALSE)="","Sin registro",VLOOKUP(A8,$C$4:$AL$151,25,FALSE)),"Sin registro"),"-") -> - | AL8: =IF(AH8="SI",IFERROR(IF(VLOOKUP(A8,$C$4:$AL$151,26,FALSE)="","Sin registro",VLOOKUP(A8,$C$4:$AL$151,26,FALSE)),"Sin registro"),"-") -> -
A9: REQ-2026-0006 | B9: =IF(OR(Q9="Desistido",Q9="No corresponde Atención OGTI",Q9="Para reformulación",Q9="Paralizado",Q9="-",Z9="Renovado",AND(AH9="NO",Z9="Culminado")),"NO","SI") -> NO | C9: - | D9: NO | E9: Contratación Directa | F9: Nuevo requerimiento | G9: Bienes | H9: Adquisición de Pantalla Interactiva para el Tribunal Fiscal del Ministerio de Economía y Finanzas | I9: 033089-2026 | J9: Pantalla interactiva | K9: Soporte Tecnico | L9: Napoleon Alva Vasquez | M9: Ronald Yrupailla Diaz | N9: Tribunal Fiscal | O9: 22956.19 | P9: 46064 | Q9: Ejecutado | R9: - | S9: - | T9: =IFERROR(IF(OR(Q9="Ejecutado",Q9="No corresponde atención OGTI",Q9="Desistido",Q9="-",Q9="Para reformulación"),"-",IF(OR(S9="-",S9=""),"Falta fecha_estado",NETWORKDAYS(S9,TODAY(),{"02/04/2026";"03/04/2026";"30/06/2026"}))),"-") -> - | U9: Orden de Compra | V9: 0000048-2026 | W9: 46083 | X9: COMPU CENTER BUSSINES S.A.C. | Y9: Napoleon Alva Vasquez | Z9: =IFERROR(IF(Q9="-","-",IF(Q9="Proceso de implementación/Activación/Entrega","Proceso de implementación/Activación/Entrega",IF(OR(Q9="Desistido",Q9="No corresponde atención OGTI",Q9="Para reformulación"),Q9,IF(AND(Q9="Ejecutado",AA9="No aplica",AB9="No Aplica"),"Culminado",IF(Q9="Ejecutado",IF(AND(AC9="-",G9="Bienes"),"Culminado",IF(AC9="-","Falta informacion",IF(AND(AB9-TODAY()>=0,AB9-TODAY()<=90),"Vigente_por vencer",IF(AND(AH9<>"SI",AB9<TODAY()),"Culminado",IF(AND(AH9="SI",AB9<TODAY(),OR(AK9="Sin Registro",AL9="Sin Registro")),"Vencido",IF(AND(AH9="SI",AB9<TODAY(),AK9>AA9,AL9>AB9),"Renovado","Vigente")))))),"En tramite"))))),"-") -> Culminado | AA9: - | AB9: - | AC9: =IFERROR(IF(OR(AA9="-",AA9="",AB9="-",AB9=""),"-",CONCATENATE('Seguimiento OIT'!AB9-'Seguimiento OIT'!AA9+1," dias")),"-") -> - | AD9: =IFERROR(IF(Z9="Vencido",(TODAY()-AB9)+1,"-"),"-") -> - | AE9: - | AF9: Conforrmidad HR 056765-2026 | AG9: https://mefgobpe1.sharepoint.com/:f:/t/DireccindelaOficinadeInfraestructuraTecnolgica/IgA4J9G8lX8jTL50cb-xPfgVAYuuw3a9sQa6941P4nOdfms?e=DE2hgt | AH9: NO | AI9: =IFERROR(IF(AH9="SI",VLOOKUP(A9,$C$4:$AL$151,15,FALSE),"-"),"Sin tramite") -> - | AJ9: =IFERROR(IF(AH9="SI",VLOOKUP(A9,$C$4:$AL$151,7,FALSE),"-"),"Sin HR") -> - | AK9: =IF(AH9="SI",IFERROR(IF(VLOOKUP(A9,$C$4:$AL$151,25,FALSE)="","Sin registro",VLOOKUP(A9,$C$4:$AL$151,25,FALSE)),"Sin registro"),"-") -> - | AL9: =IF(AH9="SI",IFERROR(IF(VLOOKUP(A9,$C$4:$AL$151,26,FALSE)="","Sin registro",VLOOKUP(A9,$C$4:$AL$151,26,FALSE)),"Sin registro"),"-") -> -
A10: REQ-2026-0007 | B10: =IF(OR(Q10="Desistido",Q10="No corresponde Atención OGTI",Q10="Para reformulación",Q10="Paralizado",Q10="-",Z10="Renovado",AND(AH10="NO",Z10="Culminado")),"NO","SI") -> SI | C10: - | D10: NO | E10: Contratación Directa | F10: Nuevo requerimiento | G10: Servicios | H10: Servicio de mantenimiento preventivo y correctivo de equipos escáner de gran formato de la Oficina General de Servicios al Usuario (OGSU) | I10: 042907-2026 | J10: Mantenimiento preventivo y correctivo (Escaner IQ X4400) | K10: Soporte Tecnico | L10: Napoleon Alva Vasquez | M10: Ronald Yrupailla Diaz | N10: Oficina General de Servicios al Usuario | O10: 5445.7 | P10: 46103 | Q10: Ejecutado | R10: - | S10: - | T10: =IFERROR(IF(OR(Q10="Ejecutado",Q10="No corresponde atención OGTI",Q10="Desistido",Q10="-",Q10="Para reformulación"),"-",IF(OR(S10="-",S10=""),"Falta fecha_estado",NETWORKDAYS(S10,TODAY(),{"02/04/2026";"03/04/2026";"30/06/2026"}))),"-") -> - | U10: Orden de Servicio | V10: 0001928-2026 | W10: 46125 | X10: GRUPO VENTURA PERU S.A.C. | Y10: Napoleon Alva Vasquez | Z10: =IFERROR(IF(Q10="-","-",IF(Q10="Proceso de implementación/Activación/Entrega","Proceso de implementación/Activación/Entrega",IF(OR(Q10="Desistido",Q10="No corresponde atención OGTI",Q10="Para reformulación"),Q10,IF(AND(Q10="Ejecutado",AA10="No aplica",AB10="No Aplica"),"Culminado",IF(Q10="Ejecutado",IF(AND(AC10="-",G10="Bienes"),"Culminado",IF(AC10="-","Falta informacion",IF(AND(AB10-TODAY()>=0,AB10-TODAY()<=90),"Vigente_por vencer",IF(AND(AH10<>"SI",AB10<TODAY()),"Culminado",IF(AND(AH10="SI",AB10<TODAY(),OR(AK10="Sin Registro",AL10="Sin Registro")),"Vencido",IF(AND(AH10="SI",AB10<TODAY(),AK10>AA10,AL10>AB10),"Renovado","Vigente")))))),"En tramite"))))),"-") -> Vigente | AA10: 46147 | AB10: 46330 | AC10: =IFERROR(IF(OR(AA10="-",AA10="",AB10="-",AB10=""),"-",CONCATENATE('Seguimiento OIT'!AB10-'Seguimiento OIT'!AA10+1," dias")),"-") -> 184 dias | AD10: =IFERROR(IF(Z10="Vencido",(TODAY()-AB10)+1,"-"),"-") -> - | AE10: - | AF10: *Conformidad HR 092550-2026 *Seguimiento a garantia | AG10: https://mefgobpe1.sharepoint.com/:f:/t/DireccindelaOficinadeInfraestructuraTecnolgica/IgAdCBapqOqqRJpyEFJ7XwgXAX0rGkLM2DRJnlRRxk9fGTo?e=7jpXkp | AH10: NO | AI10: =IFERROR(IF(AH10="SI",VLOOKUP(A10,$C$4:$AL$151,15,FALSE),"-"),"Sin tramite") -> - | AJ10: =IFERROR(IF(AH10="SI",VLOOKUP(A10,$C$4:$AL$151,7,FALSE),"-"),"Sin HR") -> - | AK10: =IF(AH10="SI",IFERROR(IF(VLOOKUP(A10,$C$4:$AL$151,25,FALSE)="","Sin registro",VLOOKUP(A10,$C$4:$AL$151,25,FALSE)),"Sin registro"),"-") -> - | AL10: =IF(AH10="SI",IFERROR(IF(VLOOKUP(A10,$C$4:$AL$151,26,FALSE)="","Sin registro",VLOOKUP(A10,$C$4:$AL$151,26,FALSE)),"Sin registro"),"-") -> -
A11: REQ-2026-0008 | B11: =IF(OR(Q11="Desistido",Q11="No corresponde Atención OGTI",Q11="Para reformulación",Q11="Paralizado",Q11="-",Z11="Renovado",AND(AH11="NO",Z11="Culminado")),"NO","SI") -> SI | C11: - | D11: NO | E11: Contratación Directa | F11: Renovación | G11: Servicios | H11: Servicio de suscripción de licencias de software de asistencia inteligente y de automatización de flujos de trabajo de la marca Microsoft | I11: 040448-2026 | J11: *COPILOT 365 (21) *Power Automate Process (02) | K11: Jefatura OIT | L11: José Romucho Sotelo | M11: Ronald Yrupailla Diaz | N11: Oficina General de Tecnologías de la Información | O11: 43764.05 | P11: 46073 | Q11: Ejecutado | R11: - | S11: - | T11: =IFERROR(IF(OR(Q11="Ejecutado",Q11="No corresponde atención OGTI",Q11="Desistido",Q11="-",Q11="Para reformulación"),"-",IF(OR(S11="-",S11=""),"Falta fecha_estado",NETWORKDAYS(S11,TODAY(),{"02/04/2026";"03/04/2026";"30/06/2026"}))),"-") -> - | U11: Orden de Servicio | V11: 0001422-2026 | W11: 46099 | X11: SEIDOR TECHNOLOGIES PERU S.A.C. | Y11: José Romucho Sotelo | Z11: =IFERROR(IF(Q11="-","-",IF(Q11="Proceso de implementación/Activación/Entrega","Proceso de implementación/Activación/Entrega",IF(OR(Q11="Desistido",Q11="No corresponde atención OGTI",Q11="Para reformulación"),Q11,IF(AND(Q11="Ejecutado",AA11="No aplica",AB11="No Aplica"),"Culminado",IF(Q11="Ejecutado",IF(AND(AC11="-",G11="Bienes"),"Culminado",IF(AC11="-","Falta informacion",IF(AND(AB11-TODAY()>=0,AB11-TODAY()<=90),"Vigente_por vencer",IF(AND(AH11<>"SI",AB11<TODAY()),"Culminado",IF(AND(AH11="SI",AB11<TODAY(),OR(AK11="Sin Registro",AL11="Sin Registro")),"Vencido",IF(AND(AH11="SI",AB11<TODAY(),AK11>AA11,AL11>AB11),"Renovado","Vigente")))))),"En tramite"))))),"-") -> Vigente | AA11: 46104 | AB11: 46468 | AC11: =IFERROR(IF(OR(AA11="-",AA11="",AB11="-",AB11=""),"-",CONCATENATE('Seguimiento OIT'!AB11-'Seguimiento OIT'!AA11+1," dias")),"-") -> 365 dias | AD11: =IFERROR(IF(Z11="Vencido",(TODAY()-AB11)+1,"-"),"-") -> - | AE11: - | AF11: *Conformidad HR 072061-2026 | AG11: https://mefgobpe1.sharepoint.com/:f:/t/DireccindelaOficinadeInfraestructuraTecnolgica/IgDtI1itSj1MRIe9w_PuV_8qAWxI3nhcWFemRLD2qjgXkco?e=DCylEI | AH11: NO | AI11: =IFERROR(IF(AH11="SI",VLOOKUP(A11,$C$4:$AL$151,15,FALSE),"-"),"Sin tramite") -> - | AJ11: =IFERROR(IF(AH11="SI",VLOOKUP(A11,$C$4:$AL$151,7,FALSE),"-"),"Sin HR") -> - | AK11: =IF(AH11="SI",IFERROR(IF(VLOOKUP(A11,$C$4:$AL$151,25,FALSE)="","Sin registro",VLOOKUP(A11,$C$4:$AL$151,25,FALSE)),"Sin registro"),"-") -> - | AL11: =IF(AH11="SI",IFERROR(IF(VLOOKUP(A11,$C$4:$AL$151,26,FALSE)="","Sin registro",VLOOKUP(A11,$C$4:$AL$151,26,FALSE)),"Sin registro"),"-") -> -
A12: REQ-2026-0009 | B12: =IF(OR(Q12="Desistido",Q12="No corresponde Atención OGTI",Q12="Para reformulación",Q12="Paralizado",Q12="-",Z12="Renovado",AND(AH12="NO",Z12="Culminado")),"NO","SI") -> SI | C12: - | D12: NO | E12: Contratación Directa | F12: Nuevo requerimiento | G12: Servicios | H12: Servicio de suscripción de licencias de software para el desarrollo de aplicaciones empresariales de bajo código (low-code) | I12: 040460-2026 | J12: Power Apps Premium | K12: Jefatura OIT | L12: José Romucho Sotelo | M12: Ronald Yrupailla Diaz | N12: Oficina de Sistemas de Información | O12: 1899.16 | P12: 46073 | Q12: Ejecutado | R12: - | S12: - | T12: =IFERROR(IF(OR(Q12="Ejecutado",Q12="No corresponde atención OGTI",Q12="Desistido",Q12="-",Q12="Para reformulación"),"-",IF(OR(S12="-",S12=""),"Falta fecha_estado",NETWORKDAYS(S12,TODAY(),{"02/04/2026";"03/04/2026";"30/06/2026"}))),"-") -> - | U12: Orden de Servicio | V12: 0001453-2026 | W12: 46101 | X12: SEIDOR TECHNOLOGIES PERU S.A.C. | Y12: José Romucho Sotelo | Z12: =IFERROR(IF(Q12="-","-",IF(Q12="Proceso de implementación/Activación/Entrega","Proceso de implementación/Activación/Entrega",IF(OR(Q12="Desistido",Q12="No corresponde atención OGTI",Q12="Para reformulación"),Q12,IF(AND(Q12="Ejecutado",AA12="No aplica",AB12="No Aplica"),"Culminado",IF(Q12="Ejecutado",IF(AND(AC12="-",G12="Bienes"),"Culminado",IF(AC12="-","Falta informacion",IF(AND(AB12-TODAY()>=0,AB12-TODAY()<=90),"Vigente_por vencer",IF(AND(AH12<>"SI",AB12<TODAY()),"Culminado",IF(AND(AH12="SI",AB12<TODAY(),OR(AK12="Sin Registro",AL12="Sin Registro")),"Vencido",IF(AND(AH12="SI",AB12<TODAY(),AK12>AA12,AL12>AB12),"Renovado","Vigente")))))),"En tramite"))))),"-") -> Vigente | AA12: 46106 | AB12: 46470 | AC12: =IFERROR(IF(OR(AA12="-",AA12="",AB12="-",AB12=""),"-",CONCATENATE('Seguimiento OIT'!AB12-'Seguimiento OIT'!AA12+1," dias")),"-") -> 365 dias | AD12: =IFERROR(IF(Z12="Vencido",(TODAY()-AB12)+1,"-"),"-") -> - | AE12: - | AF12: Conformidad HR 072066-2026 | AG12: https://mefgobpe1.sharepoint.com/:f:/t/DireccindelaOficinadeInfraestructuraTecnolgica/IgDtI1itSj1MRIe9w_PuV_8qAWxI3nhcWFemRLD2qjgXkco?e=DCylEI | AH12: NO | AI12: =IFERROR(IF(AH12="SI",VLOOKUP(A12,$C$4:$AL$151,15,FALSE),"-"),"Sin tramite") -> - | AJ12: =IFERROR(IF(AH12="SI",VLOOKUP(A12,$C$4:$AL$151,7,FALSE),"-"),"Sin HR") -> - | AK12: =IF(AH12="SI",IFERROR(IF(VLOOKUP(A12,$C$4:$AL$151,25,FALSE)="","Sin registro",VLOOKUP(A12,$C$4:$AL$151,25,FALSE)),"Sin registro"),"-") -> - | AL12: =IF(AH12="SI",IFERROR(IF(VLOOKUP(A12,$C$4:$AL$151,26,FALSE)="","Sin registro",VLOOKUP(A12,$C$4:$AL$151,26,FALSE)),"Sin registro"),"-") -> -
A13: REQ-2026-0010 | B13: =IF(OR(Q13="Desistido",Q13="No corresponde Atención OGTI",Q13="Para reformulación",Q13="Paralizado",Q13="-",Z13="Renovado",AND(AH13="NO",Z13="Culminado")),"NO","SI") -> NO | C13: - | D13: NO | E13: Contratación Directa | F13: Nuevo requerimiento | G13: Bienes | H13: Adquisición de equipamiento tecnológico para la producción y difusión de contenidos de la Oficina de Comunicaciones | I13: *089135-2026 (Requerimiento) *085712-2026- 005955-2026 (Apoyo presupuestal) | J13: *Discos solidos externos (1 TB y 2TB) *Telepromter *Tablet *Bateria Recargable *Equipo de transmision en vivo *Transmisor de video inalambrico *Tripode con sujetador de movil | K13: Soporte Tecnico | L13: Napoleon Alva Vasquez | M13: Ronald Yrupailla Diaz | N13: Oficina de Comunicaciones | O13: 33330.5 | P13: 46133 | Q13: Ejecutado | R13: - | S13: - | T13: =IFERROR(IF(OR(Q13="Ejecutado",Q13="No corresponde atención OGTI",Q13="Desistido",Q13="-",Q13="Para reformulación"),"-",IF(OR(S13="-",S13=""),"Falta fecha_estado",NETWORKDAYS(S13,TODAY(),{"02/04/2026";"03/04/2026";"30/06/2026"}))),"-") -> - | U13: Orden de Compra | V13: 0000164-2026 | W13: 46167 | X13: CUY TECHNOLOGIES E.I.R.L. | Y13: Napoleon Alva Vasquez | Z13: =IFERROR(IF(Q13="-","-",IF(Q13="Proceso de implementación/Activación/Entrega","Proceso de implementación/Activación/Entrega",IF(OR(Q13="Desistido",Q13="No corresponde atención OGTI",Q13="Para reformulación"),Q13,IF(AND(Q13="Ejecutado",AA13="No aplica",AB13="No Aplica"),"Culminado",IF(Q13="Ejecutado",IF(AND(AC13="-",G13="Bienes"),"Culminado",IF(AC13="-","Falta informacion",IF(AND(AB13-TODAY()>=0,AB13-TODAY()<=90),"Vigente_por vencer",IF(AND(AH13<>"SI",AB13<TODAY()),"Culminado",IF(AND(AH13="SI",AB13<TODAY(),OR(AK13="Sin Registro",AL13="Sin Registro")),"Vencido",IF(AND(AH13="SI",AB13<TODAY(),AK13>AA13,AL13>AB13),"Renovado","Vigente")))))),"En tramite"))))),"-") -> Culminado | AA13: - | AB13: - | AC13: =IFERROR(IF(OR(AA13="-",AA13="",AB13="-",AB13=""),"-",CONCATENATE('Seguimiento OIT'!AB13-'Seguimiento OIT'!AA13+1," dias")),"-") -> - | AD13: =IFERROR(IF(Z13="Vencido",(TODAY()-AB13)+1,"-"),"-") -> - | AE13: - | AF13: Conformidad 120798-2026 / 120456-2026 | AG13: https://mefgobpe1.sharepoint.com/:f:/t/DireccindelaOficinadeInfraestructuraTecnolgica/IgC1sKmCnD2OR6nwjjoR-5QzAWuoyeFD46P5CnRUqQofQSM?e=fKqH5P | AH13: NO | AI13: =IFERROR(IF(AH13="SI",VLOOKUP(A13,$C$4:$AL$151,15,FALSE),"-"),"Sin tramite") -> - | AJ13: =IFERROR(IF(AH13="SI",VLOOKUP(A13,$C$4:$AL$151,7,FALSE),"-"),"Sin HR") -> - | AK13: =IF(AH13="SI",IFERROR(IF(VLOOKUP(A13,$C$4:$AL$151,25,FALSE)="","Sin registro",VLOOKUP(A13,$C$4:$AL$151,25,FALSE)),"Sin registro"),"-") -> - | AL13: =IF(AH13="SI",IFERROR(IF(VLOOKUP(A13,$C$4:$AL$151,26,FALSE)="","Sin registro",VLOOKUP(A13,$C$4:$AL$151,26,FALSE)),"Sin registro"),"-") -> -
A14: REQ-2026-0011 | B14: =IF(OR(Q14="Desistido",Q14="No corresponde Atención OGTI",Q14="Para reformulación",Q14="Paralizado",Q14="-",Z14="Renovado",AND(AH14="NO",Z14="Culminado")),"NO","SI") -> NO | C14: - | D14: NO | E14: Contratación Directa | F14: Nuevo requerimiento | G14: Bienes | H14: Adquisición de equipos de cómputo (CPU y Monitor) para la Oficina de Comunicaciones del Ministerio de Economía y Finanzas | I14: 052742-2026 | J14: *02 Workstation *02 Monitores | K14: Soporte Tecnico | L14: Napoleon Alva Vasquez | M14: Ronald Yrupailla Diaz | N14: Oficina de Comunicaciones | O14: 33211.05 | P14: 46090 | Q14: Ejecutado | R14: - | S14: - | T14: =IFERROR(IF(OR(Q14="Ejecutado",Q14="No corresponde atención OGTI",Q14="Desistido",Q14="-",Q14="Para reformulación"),"-",IF(OR(S14="-",S14=""),"Falta fecha_estado",NETWORKDAYS(S14,TODAY(),{"02/04/2026";"03/04/2026";"30/06/2026"}))),"-") -> - | U14: Orden de Compra | V14: 0000143-2026 | W14: 46148 | X14: COMPU-SISTEMAS DEL PERU SAC | Y14: Napoleon Alva Vasquez | Z14: =IFERROR(IF(Q14="-","-",IF(Q14="Proceso de implementación/Activación/Entrega","Proceso de implementación/Activación/Entrega",IF(OR(Q14="Desistido",Q14="No corresponde atención OGTI",Q14="Para reformulación"),Q14,IF(AND(Q14="Ejecutado",AA14="No aplica",AB14="No Aplica"),"Culminado",IF(Q14="Ejecutado",IF(AND(AC14="-",G14="Bienes"),"Culminado",IF(AC14="-","Falta informacion",IF(AND(AB14-TODAY()>=0,AB14-TODAY()<=90),"Vigente_por vencer",IF(AND(AH14<>"SI",AB14<TODAY()),"Culminado",IF(AND(AH14="SI",AB14<TODAY(),OR(AK14="Sin Registro",AL14="Sin Registro")),"Vencido",IF(AND(AH14="SI",AB14<TODAY(),AK14>AA14,AL14>AB14),"Renovado","Vigente")))))),"En tramite"))))),"-") -> Culminado | AA14: - | AB14: - | AC14: =IFERROR(IF(OR(AA14="-",AA14="",AB14="-",AB14=""),"-",CONCATENATE('Seguimiento OIT'!AB14-'Seguimiento OIT'!AA14+1," dias")),"-") -> - | AD14: =IFERROR(IF(Z14="Vencido",(TODAY()-AB14)+1,"-"),"-") -> - | AE14: - | AF14: Conformidad 113245-2026 | AG14: https://mefgobpe1.sharepoint.com/:f:/t/DireccindelaOficinadeInfraestructuraTecnolgica/IgA5G0WmVxohTqP5MQbMskHSAWM6M_Nigc_QT61A2izummk?e=2mwTcX | AH14: NO | AI14: =IFERROR(IF(AH14="SI",VLOOKUP(A14,$C$4:$AL$151,15,FALSE),"-"),"Sin tramite") -> - | AJ14: =IFERROR(IF(AH14="SI",VLOOKUP(A14,$C$4:$AL$151,7,FALSE),"-"),"Sin HR") -> - | AK14: =IF(AH14="SI",IFERROR(IF(VLOOKUP(A14,$C$4:$AL$151,25,FALSE)="","Sin registro",VLOOKUP(A14,$C$4:$AL$151,25,FALSE)),"Sin registro"),"-") -> - | AL14: =IF(AH14="SI",IFERROR(IF(VLOOKUP(A14,$C$4:$AL$151,26,FALSE)="","Sin registro",VLOOKUP(A14,$C$4:$AL$151,26,FALSE)),"Sin registro"),"-") -> -
A15: REQ-2026-0012 | B15: =IF(OR(Q15="Desistido",Q15="No corresponde Atención OGTI",Q15="Para reformulación",Q15="Paralizado",Q15="-",Z15="Renovado",AND(AH15="NO",Z15="Culminado")),"NO","SI") -> SI | C15: - | D15: NO | E15: Contratación Directa | F15: Renovación | G15: Servicios | H15: Servicio de suscripción de licencias de software para la gestión de videoconferencias (Modo Cloud) de la Oficina General de Recursos Humanos del Ministerio de Economía y Finanzas | I15: *101707-2026 (Requerimiento) *088416-202 (Req 01) *097140-2026 (Apoyo presupuestal) | J15: Zoom Business (15 licencias) | K15: Jefatura OIT | L15: José Romucho Sotelo | M15: Ronald Yrupailla Diaz | N15: Oficina General de Recursos Humanos | O15: 13650 | P15: 46153 | Q15: Ejecutado | R15: - | S15: - | T15: =IFERROR(IF(OR(Q15="Ejecutado",Q15="No corresponde atención OGTI",Q15="Desistido",Q15="-",Q15="Para reformulación"),"-",IF(OR(S15="-",S15=""),"Falta fecha_estado",NETWORKDAYS(S15,TODAY(),{"02/04/2026";"03/04/2026";"30/06/2026"}))),"-") -> - | U15: Orden de Servicio | V15: 0002637-2026 | W15: 46163 | X15: ARGACORP S.A.C. | Y15: José Romucho Sotelo | Z15: =IFERROR(IF(Q15="-","-",IF(Q15="Proceso de implementación/Activación/Entrega","Proceso de implementación/Activación/Entrega",IF(OR(Q15="Desistido",Q15="No corresponde atención OGTI",Q15="Para reformulación"),Q15,IF(AND(Q15="Ejecutado",AA15="No aplica",AB15="No Aplica"),"Culminado",IF(Q15="Ejecutado",IF(AND(AC15="-",G15="Bienes"),"Culminado",IF(AC15="-","Falta informacion",IF(AND(AB15-TODAY()>=0,AB15-TODAY()<=90),"Vigente_por vencer",IF(AND(AH15<>"SI",AB15<TODAY()),"Culminado",IF(AND(AH15="SI",AB15<TODAY(),OR(AK15="Sin Registro",AL15="Sin Registro")),"Vencido",IF(AND(AH15="SI",AB15<TODAY(),AK15>AA15,AL15>AB15),"Renovado","Vigente")))))),"En tramite"))))),"-") -> Vigente | AA15: 46167 | AB15: 46531 | AC15: =IFERROR(IF(OR(AA15="-",AA15="",AB15="-",AB15=""),"-",CONCATENATE('Seguimiento OIT'!AB15-'Seguimiento OIT'!AA15+1," dias")),"-") -> 365 dias | AD15: =IFERROR(IF(Z15="Vencido",(TODAY()-AB15)+1,"-"),"-") -> - | AE15: - | AF15: Conformidad 118804-2026 | AG15: https://mefgobpe1.sharepoint.com/:f:/t/DireccindelaOficinadeInfraestructuraTecnolgica/IgBFT23nqG9zQ7rbTFVcZ7QxAYluJ9F4NfR0qxfKpTAXlgY?e=nMW8TE | AH15: NO | AI15: =IFERROR(IF(AH15="SI",VLOOKUP(A15,$C$4:$AL$151,15,FALSE),"-"),"Sin tramite") -> - | AJ15: =IFERROR(IF(AH15="SI",VLOOKUP(A15,$C$4:$AL$151,7,FALSE),"-"),"Sin HR") -> - | AK15: =IF(AH15="SI",IFERROR(IF(VLOOKUP(A15,$C$4:$AL$151,25,FALSE)="","Sin registro",VLOOKUP(A15,$C$4:$AL$151,25,FALSE)),"Sin registro"),"-") -> - | AL15: =IF(AH15="SI",IFERROR(IF(VLOOKUP(A15,$C$4:$AL$151,26,FALSE)="","Sin registro",VLOOKUP(A15,$C$4:$AL$151,26,FALSE)),"Sin registro"),"-") -> -
A16: REQ-2026-0013 | B16: =IF(OR(Q16="Desistido",Q16="No corresponde Atención OGTI",Q16="Para reformulación",Q16="Paralizado",Q16="-",Z16="Renovado",AND(AH16="NO",Z16="Culminado")),"NO","SI") -> NO | C16: - | D16: NO | E16: Contratación Directa | F16: Nuevo requerimiento | G16: Bienes | H16: Adquisición de accesorios informáticos para equipos de cómputo (Lectoras CD/DVD)-OGSU | I16: *114171-2026 (Requerimiento consolidado) *073576-2026 (Requerimiento inicial) *109395-2026 (Apoyo presupuesta) | J16: Lectoras externas de CD/DVD (06 unidades) | K16: Soporte Tecnico | L16: Napoleon Alva Vasquez | M16: Ronald Yrupailla Diaz | N16: Oficina General de Servicios al Usuario | O16: 660 | P16: 46164 | Q16: Ejecutado | R16: - | S16: - | T16: =IFERROR(IF(OR(Q16="Ejecutado",Q16="No corresponde atención OGTI",Q16="Desistido",Q16="-",Q16="Para reformulación"),"-",IF(OR(S16="-",S16=""),"Falta fecha_estado",NETWORKDAYS(S16,TODAY(),{"02/04/2026";"03/04/2026";"30/06/2026"}))),"-") -> - | U16: Orden de Compra | V16: 0000182-2026 | W16: 46176 | X16: CUY TECHNOLOGIES E.I.R.L. | Y16: Napoleon Alva Vasquez | Z16: =IFERROR(IF(Q16="-","-",IF(Q16="Proceso de implementación/Activación/Entrega","Proceso de implementación/Activación/Entrega",IF(OR(Q16="Desistido",Q16="No corresponde atención OGTI",Q16="Para reformulación"),Q16,IF(AND(Q16="Ejecutado",AA16="No aplica",AB16="No Aplica"),"Culminado",IF(Q16="Ejecutado",IF(AND(AC16="-",G16="Bienes"),"Culminado",IF(AC16="-","Falta informacion",IF(AND(AB16-TODAY()>=0,AB16-TODAY()<=90),"Vigente_por vencer",IF(AND(AH16<>"SI",AB16<TODAY()),"Culminado",IF(AND(AH16="SI",AB16<TODAY(),OR(AK16="Sin Registro",AL16="Sin Registro")),"Vencido",IF(AND(AH16="SI",AB16<TODAY(),AK16>AA16,AL16>AB16),"Renovado","Vigente")))))),"En tramite"))))),"-") -> Culminado | AA16: - | AB16: - | AC16: =IFERROR(IF(OR(AA16="-",AA16="",AB16="-",AB16=""),"-",CONCATENATE('Seguimiento OIT'!AB16-'Seguimiento OIT'!AA16+1," dias")),"-") -> - | AD16: =IFERROR(IF(Z16="Vencido",(TODAY()-AB16)+1,"-"),"-") -> - | AE16: - | AF16: Conformidad 125911-2026 | AG16: https://mefgobpe1.sharepoint.com/:f:/t/DireccindelaOficinadeInfraestructuraTecnolgica/IgBggS-oH5JqTr_6GWypG4b4ATKxqfyCVeq7C0aBSIKTF4c?e=LBGJEY | AH16: NO | AI16: =IFERROR(IF(AH16="SI",VLOOKUP(A16,$C$4:$AL$151,15,FALSE),"-"),"Sin tramite") -> - | AJ16: =IFERROR(IF(AH16="SI",VLOOKUP(A16,$C$4:$AL$151,7,FALSE),"-"),"Sin HR") -> - | AK16: =IF(AH16="SI",IFERROR(IF(VLOOKUP(A16,$C$4:$AL$151,25,FALSE)="","Sin registro",VLOOKUP(A16,$C$4:$AL$151,25,FALSE)),"Sin registro"),"-") -> - | AL16: =IF(AH16="SI",IFERROR(IF(VLOOKUP(A16,$C$4:$AL$151,26,FALSE)="","Sin registro",VLOOKUP(A16,$C$4:$AL$151,26,FALSE)),"Sin registro"),"-") -> -
A17: REQ-2026-0014 | B17: =IF(OR(Q17="Desistido",Q17="No corresponde Atención OGTI",Q17="Para reformulación",Q17="Paralizado",Q17="-",Z17="Renovado",AND(AH17="NO",Z17="Culminado")),"NO","SI") -> NO | C17: - | D17: NO | E17: Contratación Directa | F17: Nuevo requerimiento | G17: Bienes | H17: Adquisición de accesorios informáticos para equipos de cómputo (Lectoras CD/DVD)-Procuradoria | I17: *114171-2026 (Requerimiento consolidado) *Correo (Requerimiento inicial) | J17: Lectoras externas de CD/DVD (03 unidades) | K17: Soporte Tecnico | L17: Napoleon Alva Vasquez | M17: Ronald Yrupailla Diaz | N17: Procuraduría Pública Especializada en Materia Hacendaria | O17: 330 | P17: 46164 | Q17: Ejecutado | R17: - | S17: - | T17: =IFERROR(IF(OR(Q17="Ejecutado",Q17="No corresponde atención OGTI",Q17="Desistido",Q17="-",Q17="Para reformulación"),"-",IF(OR(S17="-",S17=""),"Falta fecha_estado",NETWORKDAYS(S17,TODAY(),{"02/04/2026";"03/04/2026";"30/06/2026"}))),"-") -> - | U17: Orden de Compra | V17: 0000182-2026 | W17: 46176 | X17: CUY TECHNOLOGIES E.I.R.L. | Y17: Napoleon Alva Vasquez | Z17: =IFERROR(IF(Q17="-","-",IF(Q17="Proceso de implementación/Activación/Entrega","Proceso de implementación/Activación/Entrega",IF(OR(Q17="Desistido",Q17="No corresponde atención OGTI",Q17="Para reformulación"),Q17,IF(AND(Q17="Ejecutado",AA17="No aplica",AB17="No Aplica"),"Culminado",IF(Q17="Ejecutado",IF(AND(AC17="-",G17="Bienes"),"Culminado",IF(AC17="-","Falta informacion",IF(AND(AB17-TODAY()>=0,AB17-TODAY()<=90),"Vigente_por vencer",IF(AND(AH17<>"SI",AB17<TODAY()),"Culminado",IF(AND(AH17="SI",AB17<TODAY(),OR(AK17="Sin Registro",AL17="Sin Registro")),"Vencido",IF(AND(AH17="SI",AB17<TODAY(),AK17>AA17,AL17>AB17),"Renovado","Vigente")))))),"En tramite"))))),"-") -> Culminado | AA17: - | AB17: - | AC17: =IFERROR(IF(OR(AA17="-",AA17="",AB17="-",AB17=""),"-",CONCATENATE('Seguimiento OIT'!AB17-'Seguimiento OIT'!AA17+1," dias")),"-") -> - | AD17: =IFERROR(IF(Z17="Vencido",(TODAY()-AB17)+1,"-"),"-") -> - | AE17: - | AF17: Conformidad 125911-2026 | AG17: https://mefgobpe1.sharepoint.com/:f:/t/DireccindelaOficinadeInfraestructuraTecnolgica/IgAhsups6_SGQojMLYgdHk-0AXwoAEv3n-GpPgZzS4F96cQ?e=SUEvKN | AH17: NO | AI17: =IFERROR(IF(AH17="SI",VLOOKUP(A17,$C$4:$AL$151,15,FALSE),"-"),"Sin tramite") -> - | AJ17: =IFERROR(IF(AH17="SI",VLOOKUP(A17,$C$4:$AL$151,7,FALSE),"-"),"Sin HR") -> - | AK17: =IF(AH17="SI",IFERROR(IF(VLOOKUP(A17,$C$4:$AL$151,25,FALSE)="","Sin registro",VLOOKUP(A17,$C$4:$AL$151,25,FALSE)),"Sin registro"),"-") -> - | AL17: =IF(AH17="SI",IFERROR(IF(VLOOKUP(A17,$C$4:$AL$151,26,FALSE)="","Sin registro",VLOOKUP(A17,$C$4:$AL$151,26,FALSE)),"Sin registro"),"-") -> -
A18: REQ-2026-0015 | B18: =IF(OR(Q18="Desistido",Q18="No corresponde Atención OGTI",Q18="Para reformulación",Q18="Paralizado",Q18="-",Z18="Renovado",AND(AH18="NO",Z18="Culminado")),"NO","SI") -> NO | C18: - | D18: NO | E18: Contratación Directa | F18: Nuevo requerimiento | G18: Bienes | H18: Adquisición de accesorios informáticos para equipos de cómputo (Adaptador HDMI-VGA y Cable de seguridad Laptop)-DEFCON | I18: *114171-2026 (Requerimiento consolidado) *092014-2026 / 082489-2026 (Requerimiento inicial) | J18: *Adaptador HDMI a VGA *Cable de seguridad para laptop | K18: Soporte Tecnico | L18: Napoleon Alva Vasquez | M18: Ronald Yrupailla Diaz | N18: Procuraduría Pública Especializada en Materia Hacendaria | O18: 1610 | P18: 46164 | Q18: Ejecutado | R18: - | S18: - | T18: =IFERROR(IF(OR(Q18="Ejecutado",Q18="No corresponde atención OGTI",Q18="Desistido",Q18="-",Q18="Para reformulación"),"-",IF(OR(S18="-",S18=""),"Falta fecha_estado",NETWORKDAYS(S18,TODAY(),{"02/04/2026";"03/04/2026";"30/06/2026"}))),"-") -> - | U18: Orden de Compra | V18: 0000182-2026 | W18: 46176 | X18: CUY TECHNOLOGIES E.I.R.L. | Y18: Napoleon Alva Vasquez | Z18: =IFERROR(IF(Q18="-","-",IF(Q18="Proceso de implementación/Activación/Entrega","Proceso de implementación/Activación/Entrega",IF(OR(Q18="Desistido",Q18="No corresponde atención OGTI",Q18="Para reformulación"),Q18,IF(AND(Q18="Ejecutado",AA18="No aplica",AB18="No Aplica"),"Culminado",IF(Q18="Ejecutado",IF(AND(AC18="-",G18="Bienes"),"Culminado",IF(AC18="-","Falta informacion",IF(AND(AB18-TODAY()>=0,AB18-TODAY()<=90),"Vigente_por vencer",IF(AND(AH18<>"SI",AB18<TODAY()),"Culminado",IF(AND(AH18="SI",AB18<TODAY(),OR(AK18="Sin Registro",AL18="Sin Registro")),"Vencido",IF(AND(AH18="SI",AB18<TODAY(),AK18>AA18,AL18>AB18),"Renovado","Vigente")))))),"En tramite"))))),"-") -> Culminado | AA18: - | AB18: - | AC18: =IFERROR(IF(OR(AA18="-",AA18="",AB18="-",AB18=""),"-",CONCATENATE('Seguimiento OIT'!AB18-'Seguimiento OIT'!AA18+1," dias")),"-") -> - | AD18: =IFERROR(IF(Z18="Vencido",(TODAY()-AB18)+1,"-"),"-") -> - | AE18: - | AF18: Conformidad 125911-2026 | AG18: https://mefgobpe1.sharepoint.com/:f:/t/DireccindelaOficinadeInfraestructuraTecnolgica/IgCll127HQEpSImNYotDU9X-AVijdG8ZVg50_SyeasEmpiA?e=acIxyJ | AH18: NO | AI18: =IFERROR(IF(AH18="SI",VLOOKUP(A18,$C$4:$AL$151,15,FALSE),"-"),"Sin tramite") -> - | AJ18: =IFERROR(IF(AH18="SI",VLOOKUP(A18,$C$4:$AL$151,7,FALSE),"-"),"Sin HR") -> - | AK18: =IF(AH18="SI",IFERROR(IF(VLOOKUP(A18,$C$4:$AL$151,25,FALSE)="","Sin registro",VLOOKUP(A18,$C$4:$AL$151,25,FALSE)),"Sin registro"),"-") -> - | AL18: =IF(AH18="SI",IFERROR(IF(VLOOKUP(A18,$C$4:$AL$151,26,FALSE)="","Sin registro",VLOOKUP(A18,$C$4:$AL$151,26,FALSE)),"Sin registro"),"-") -> -
A19: REQ-2026-0016 | B19: =IF(OR(Q19="Desistido",Q19="No corresponde Atención OGTI",Q19="Para reformulación",Q19="Paralizado",Q19="-",Z19="Renovado",AND(AH19="NO",Z19="Culminado")),"NO","SI") -> SI | C19: - | D19: NO | E19: Contratación Directa | F19: Renovación | G19: Servicios | H19: Servicio de Suscripción de Software de Gestión de Proyectos de la marca Microsoft | I19: 080309-2026 | J19: Planner y Project Plan 3 (23 unidades) | K19: Jefatura OIT | L19: José Romucho Sotelo | M19: Ronald Yrupailla Diaz | N19: Oficina General de Tecnologías de la Información | O19: 43165 | P19: 46122 | Q19: Ejecutado | R19: - | S19: - | T19: =IFERROR(IF(OR(Q19="Ejecutado",Q19="No corresponde atención OGTI",Q19="Desistido",Q19="-",Q19="Para reformulación"),"-",IF(OR(S19="-",S19=""),"Falta fecha_estado",NETWORKDAYS(S19,TODAY(),{"02/04/2026";"03/04/2026";"30/06/2026"}))),"-") -> - | U19: Orden de Servicio | V19: 0002327-2026 | W19: 46147 | X19: DAILY TECHNOLOGY S.A.C | Y19: José Romucho Sotelo | Z19: =IFERROR(IF(Q19="-","-",IF(Q19="Proceso de implementación/Activación/Entrega","Proceso de implementación/Activación/Entrega",IF(OR(Q19="Desistido",Q19="No corresponde atención OGTI",Q19="Para reformulación"),Q19,IF(AND(Q19="Ejecutado",AA19="No aplica",AB19="No Aplica"),"Culminado",IF(Q19="Ejecutado",IF(AND(AC19="-",G19="Bienes"),"Culminado",IF(AC19="-","Falta informacion",IF(AND(AB19-TODAY()>=0,AB19-TODAY()<=90),"Vigente_por vencer",IF(AND(AH19<>"SI",AB19<TODAY()),"Culminado",IF(AND(AH19="SI",AB19<TODAY(),OR(AK19="Sin Registro",AL19="Sin Registro")),"Vencido",IF(AND(AH19="SI",AB19<TODAY(),AK19>AA19,AL19>AB19),"Renovado","Vigente")))))),"En tramite"))))),"-") -> Vigente | AA19: 46163 | AB19: 46527 | AC19: =IFERROR(IF(OR(AA19="-",AA19="",AB19="-",AB19=""),"-",CONCATENATE('Seguimiento OIT'!AB19-'Seguimiento OIT'!AA19+1," dias")),"-") -> 365 dias | AD19: =IFERROR(IF(Z19="Vencido",(TODAY()-AB19)+1,"-"),"-") -> - | AE19: - | AF19: *Conformidad 114042-2026 *Reduccion de o.s 114497-2026 | AG19: https://mefgobpe1.sharepoint.com/:f:/t/DireccindelaOficinadeInfraestructuraTecnolgica/IgA_ThXieabKQYWhIq9N88JYAUdCaTsOhspNLFXZ1xVx_XQ?e=6VmMxh | AH19: NO | AI19: =IFERROR(IF(AH19="SI",VLOOKUP(A19,$C$4:$AL$151,15,FALSE),"-"),"Sin tramite") -> - | AJ19: =IFERROR(IF(AH19="SI",VLOOKUP(A19,$C$4:$AL$151,7,FALSE),"-"),"Sin HR") -> - | AK19: =IF(AH19="SI",IFERROR(IF(VLOOKUP(A19,$C$4:$AL$151,25,FALSE)="","Sin registro",VLOOKUP(A19,$C$4:$AL$151,25,FALSE)),"Sin registro"),"-") -> - | AL19: =IF(AH19="SI",IFERROR(IF(VLOOKUP(A19,$C$4:$AL$151,26,FALSE)="","Sin registro",VLOOKUP(A19,$C$4:$AL$151,26,FALSE)),"Sin registro"),"-") -> -
A20: REQ-2026-0017 | B20: =IF(OR(Q20="Desistido",Q20="No corresponde Atención OGTI",Q20="Para reformulación",Q20="Paralizado",Q20="-",Z20="Renovado",AND(AH20="NO",Z20="Culminado")),"NO","SI") -> SI | C20: - | D20: NO | E20: Contratación Directa | F20: Nuevo requerimiento | G20: Servicios | H20: Servicio de notificaciones masivas para mensajería empresarial (WhatsApp) a través de la plataforma INFOBIP | I20: 015282-2026 | J20: *34,000 creditos *03 Agentes *5000 sesiones x mes | K20: Jefatura OIT | L20: José Romucho Sotelo | M20: Ronald Yrupailla Diaz | N20: Oficina de Sistemas de Información | O20: 43890 | P20: 46049 | Q20: Ejecutado | R20: - | S20: - | T20: =IFERROR(IF(OR(Q20="Ejecutado",Q20="No corresponde atención OGTI",Q20="Desistido",Q20="-",Q20="Para reformulación"),"-",IF(OR(S20="-",S20=""),"Falta fecha_estado",NETWORKDAYS(S20,TODAY(),{"02/04/2026";"03/04/2026";"30/06/2026"}))),"-") -> - | U20: Orden de Servicio | V20: 0001386-2026 | W20: 46097 | X20: ENTEL PERU S.A. | Y20: José Romucho Sotelo | Z20: =IFERROR(IF(Q20="-","-",IF(Q20="Proceso de implementación/Activación/Entrega","Proceso de implementación/Activación/Entrega",IF(OR(Q20="Desistido",Q20="No corresponde atención OGTI",Q20="Para reformulación"),Q20,IF(AND(Q20="Ejecutado",AA20="No aplica",AB20="No Aplica"),"Culminado",IF(Q20="Ejecutado",IF(AND(AC20="-",G20="Bienes"),"Culminado",IF(AC20="-","Falta informacion",IF(AND(AB20-TODAY()>=0,AB20-TODAY()<=90),"Vigente_por vencer",IF(AND(AH20<>"SI",AB20<TODAY()),"Culminado",IF(AND(AH20="SI",AB20<TODAY(),OR(AK20="Sin Registro",AL20="Sin Registro")),"Vencido",IF(AND(AH20="SI",AB20<TODAY(),AK20>AA20,AL20>AB20),"Renovado","Vigente")))))),"En tramite"))))),"-") -> Vigente | AA20: 46150 | AB20: 46334 | AC20: =IFERROR(IF(OR(AA20="-",AA20="",AB20="-",AB20=""),"-",CONCATENATE('Seguimiento OIT'!AB20-'Seguimiento OIT'!AA20+1," dias")),"-") -> 185 dias | AD20: =IFERROR(IF(Z20="Vencido",(TODAY()-AB20)+1,"-"),"-") -> - | AE20: - | AF20: *Ampliacion de plazo 101774-2026 / 101763-2026 *Conformidad 110185-2026 | AG20: https://mefgobpe1.sharepoint.com/:f:/t/DireccindelaOficinadeInfraestructuraTecnolgica/IgAJ7qpoO04-RKLsaYI_TPCaAVnLB3BfeTI4TPceZmZC55c?e=sVYOpK | AH20: NO | AI20: =IFERROR(IF(AH20="SI",VLOOKUP(A20,$C$4:$AL$151,15,FALSE),"-"),"Sin tramite") -> - | AJ20: =IFERROR(IF(AH20="SI",VLOOKUP(A20,$C$4:$AL$151,7,FALSE),"-"),"Sin HR") -> - | AK20: =IF(AH20="SI",IFERROR(IF(VLOOKUP(A20,$C$4:$AL$151,25,FALSE)="","Sin registro",VLOOKUP(A20,$C$4:$AL$151,25,FALSE)),"Sin registro"),"-") -> - | AL20: =IF(AH20="SI",IFERROR(IF(VLOOKUP(A20,$C$4:$AL$151,26,FALSE)="","Sin registro",VLOOKUP(A20,$C$4:$AL$151,26,FALSE)),"Sin registro"),"-") -> -
A21: REQ-2026-0018 | B21: =IF(OR(Q21="Desistido",Q21="No corresponde Atención OGTI",Q21="Para reformulación",Q21="Paralizado",Q21="-",Z21="Renovado",AND(AH21="NO",Z21="Culminado")),"NO","SI") -> SI | C21: - | D21: NO | E21: Contratación Directa | F21: Nuevo requerimiento | G21: Servicios | H21: Certificados digitales de persona jurídica - RENIEC | I21: 081249-2026 | J21: 1500 Certificados digitales | K21: Soporte Tecnico | L21: José Romucho Sotelo | M21: Ronald Yrupailla Diaz | N21: Oficina de Infraestructura Tecnológica | O21: 12150 | P21: 46122 | Q21: Ejecutado | R21: - | S21: - | T21: =IFERROR(IF(OR(Q21="Ejecutado",Q21="No corresponde atención OGTI",Q21="Desistido",Q21="-",Q21="Para reformulación"),"-",IF(OR(S21="-",S21=""),"Falta fecha_estado",NETWORKDAYS(S21,TODAY(),{"02/04/2026";"03/04/2026";"30/06/2026"}))),"-") -> - | U21: Nota de Compromiso | V21: 0345-2026-EF | W21: 46128 | X21: RENIEC | Y21: José Romucho Sotelo | Z21: =IFERROR(IF(Q21="-","-",IF(Q21="Proceso de implementación/Activación/Entrega","Proceso de implementación/Activación/Entrega",IF(OR(Q21="Desistido",Q21="No corresponde atención OGTI",Q21="Para reformulación"),Q21,IF(AND(Q21="Ejecutado",AA21="No aplica",AB21="No Aplica"),"Culminado",IF(Q21="Ejecutado",IF(AND(AC21="-",G21="Bienes"),"Culminado",IF(AC21="-","Falta informacion",IF(AND(AB21-TODAY()>=0,AB21-TODAY()<=90),"Vigente_por vencer",IF(AND(AH21<>"SI",AB21<TODAY()),"Culminado",IF(AND(AH21="SI",AB21<TODAY(),OR(AK21="Sin Registro",AL21="Sin Registro")),"Vencido",IF(AND(AH21="SI",AB21<TODAY(),AK21>AA21,AL21>AB21),"Renovado","Vigente")))))),"En tramite"))))),"-") -> Vigente_por vencer | AA21: 46113 | AB21: 46265 | AC21: =IFERROR(IF(OR(AA21="-",AA21="",AB21="-",AB21=""),"-",CONCATENATE('Seguimiento OIT'!AB21-'Seguimiento OIT'!AA21+1," dias")),"-") -> 153 dias | AD21: =IFERROR(IF(Z21="Vencido",(TODAY()-AB21)+1,"-"),"-") -> - | AE21: - | AF21: - | AG21: https://mefgobpe1.sharepoint.com/:f:/t/DireccindelaOficinadeInfraestructuraTecnolgica/IgA9cJfXxPsWSrNqD9HaRbozAaXWixz8fwTopb-CgIW66Dg?e=QYD4wl | AH21: NO | AI21: =IFERROR(IF(AH21="SI",VLOOKUP(A21,$C$4:$AL$151,15,FALSE),"-"),"Sin tramite") -> - | AJ21: =IFERROR(IF(AH21="SI",VLOOKUP(A21,$C$4:$AL$151,7,FALSE),"-"),"Sin HR") -> - | AK21: =IF(AH21="SI",IFERROR(IF(VLOOKUP(A21,$C$4:$AL$151,25,FALSE)="","Sin registro",VLOOKUP(A21,$C$4:$AL$151,25,FALSE)),"Sin registro"),"-") -> - | AL21: =IF(AH21="SI",IFERROR(IF(VLOOKUP(A21,$C$4:$AL$151,26,FALSE)="","Sin registro",VLOOKUP(A21,$C$4:$AL$151,26,FALSE)),"Sin registro"),"-") -> -
A22: REQ-2026-0019 | B22: =IF(OR(Q22="Desistido",Q22="No corresponde Atención OGTI",Q22="Para reformulación",Q22="Paralizado",Q22="-",Z22="Renovado",AND(AH22="NO",Z22="Culminado")),"NO","SI") -> NO | C22: - | D22: NO | E22: Contratación Directa | F22: Nuevo requerimiento | G22: Bienes | H22: Adquisición de impresora multifuncional laser a color | I22: 085801-2026 | J22: Impresora a color | K22: Soporte Tecnico | L22: Napoleon Alva Vasquez | M22: Ronald Yrupailla Diaz | N22: Secretaría General | O22: 26724.01 | P22: 46129 | Q22: Ejecutado | R22: - | S22: - | T22: =IFERROR(IF(OR(Q22="Ejecutado",Q22="No corresponde atención OGTI",Q22="Desistido",Q22="-",Q22="Para reformulación"),"-",IF(OR(S22="-",S22=""),"Falta fecha_estado",NETWORKDAYS(S22,TODAY(),{"02/04/2026";"03/04/2026";"30/06/2026"}))),"-") -> - | U22: Orden de Compra | V22: 0000137-2026 | W22: 46140 | X22: TEAMWORK CONSULTING & GENERAL SERVICES S.A.C. | Y22: Napoleon Alva Vasquez | Z22: =IFERROR(IF(Q22="-","-",IF(Q22="Proceso de implementación/Activación/Entrega","Proceso de implementación/Activación/Entrega",IF(OR(Q22="Desistido",Q22="No corresponde atención OGTI",Q22="Para reformulación"),Q22,IF(AND(Q22="Ejecutado",AA22="No aplica",AB22="No Aplica"),"Culminado",IF(Q22="Ejecutado",IF(AND(AC22="-",G22="Bienes"),"Culminado",IF(AC22="-","Falta informacion",IF(AND(AB22-TODAY()>=0,AB22-TODAY()<=90),"Vigente_por vencer",IF(AND(AH22<>"SI",AB22<TODAY()),"Culminado",IF(AND(AH22="SI",AB22<TODAY(),OR(AK22="Sin Registro",AL22="Sin Registro")),"Vencido",IF(AND(AH22="SI",AB22<TODAY(),AK22>AA22,AL22>AB22),"Renovado","Vigente")))))),"En tramite"))))),"-") -> Culminado | AA22: - | AB22: - | AC22: =IFERROR(IF(OR(AA22="-",AA22="",AB22="-",AB22=""),"-",CONCATENATE('Seguimiento OIT'!AB22-'Seguimiento OIT'!AA22+1," dias")),"-") -> - | AD22: =IFERROR(IF(Z22="Vencido",(TODAY()-AB22)+1,"-"),"-") -> - | AE22: - | AF22: *Conformidad 099839-2026 *Antecedente 192039-2025 | AG22: https://mefgobpe1.sharepoint.com/:f:/t/DireccindelaOficinadeInfraestructuraTecnolgica/IgC5keBoO6yUTY2pp9YKreusASg9cM4_iBsOqn5zrKc9kHA?e=wC8brs | AH22: NO | AI22: =IFERROR(IF(AH22="SI",VLOOKUP(A22,$C$4:$AL$151,15,FALSE),"-"),"Sin tramite") -> - | AJ22: =IFERROR(IF(AH22="SI",VLOOKUP(A22,$C$4:$AL$151,7,FALSE),"-"),"Sin HR") -> - | AK22: =IF(AH22="SI",IFERROR(IF(VLOOKUP(A22,$C$4:$AL$151,25,FALSE)="","Sin registro",VLOOKUP(A22,$C$4:$AL$151,25,FALSE)),"Sin registro"),"-") -> - | AL22: =IF(AH22="SI",IFERROR(IF(VLOOKUP(A22,$C$4:$AL$151,26,FALSE)="","Sin registro",VLOOKUP(A22,$C$4:$AL$151,26,FALSE)),"Sin registro"),"-") -> -
A23: REQ-2026-0020 | B23: =IF(OR(Q23="Desistido",Q23="No corresponde Atención OGTI",Q23="Para reformulación",Q23="Paralizado",Q23="-",Z23="Renovado",AND(AH23="NO",Z23="Culminado")),"NO","SI") -> NO | C23: - | D23: NO | E23: Contratación Directa | F23: Nuevo requerimiento | G23: Bienes | H23: Adquisición de tótem multimedia para la Oficina de Gestión Documental y Atención al Usuario (OGDAU) | I23: *084299-2026 (Requerimiento) **109395-2026 (Apoyo presupuestal) | J23: Totem Multimedia | K23: Soporte Tecnico | L23: Napoleon Alva Vasquez | M23: Ronald Yrupailla Diaz | N23: Oficina General de Servicios al Usuario | O23: 13865 | P23: 46167 | Q23: Ejecutado | R23: - | S23: - | T23: =IFERROR(IF(OR(Q23="Ejecutado",Q23="No corresponde atención OGTI",Q23="Desistido",Q23="-",Q23="Para reformulación"),"-",IF(OR(S23="-",S23=""),"Falta fecha_estado",NETWORKDAYS(S23,TODAY(),{"02/04/2026";"03/04/2026";"30/06/2026"}))),"-") -> - | U23: Orden de Compra | V23: 0000224-2026 | W23: 46197 | X23: HOLIGRAM E.I.R.L | Y23: Napoleon Alva Vasquez | Z23: =IFERROR(IF(Q23="-","-",IF(Q23="Proceso de implementación/Activación/Entrega","Proceso de implementación/Activación/Entrega",IF(OR(Q23="Desistido",Q23="No corresponde atención OGTI",Q23="Para reformulación"),Q23,IF(AND(Q23="Ejecutado",AA23="No aplica",AB23="No Aplica"),"Culminado",IF(Q23="Ejecutado",IF(AND(AC23="-",G23="Bienes"),"Culminado",IF(AC23="-","Falta informacion",IF(AND(AB23-TODAY()>=0,AB23-TODAY()<=90),"Vigente_por vencer",IF(AND(AH23<>"SI",AB23<TODAY()),"Culminado",IF(AND(AH23="SI",AB23<TODAY(),OR(AK23="Sin Registro",AL23="Sin Registro")),"Vencido",IF(AND(AH23="SI",AB23<TODAY(),AK23>AA23,AL23>AB23),"Renovado","Vigente")))))),"En tramite"))))),"-") -> Culminado | AA23: - | AB23: - | AC23: =IFERROR(IF(OR(AA23="-",AA23="",AB23="-",AB23=""),"-",CONCATENATE('Seguimiento OIT'!AB23-'Seguimiento OIT'!AA23+1," dias")),"-") -> - | AD23: =IFERROR(IF(Z23="Vencido",(TODAY()-AB23)+1,"-"),"-") -> - | AE23: - | AF23: *Conformidad (HR 159104-2026) | AG23: https://mefgobpe1.sharepoint.com/:f:/t/DireccindelaOficinadeInfraestructuraTecnolgica/IgBkEDxQVsnrSZNPX9ZDIeapAZSZtEMhDBEtCdy2R1qrdLs?e=RR4APt | AH23: NO | AI23: =IFERROR(IF(AH23="SI",VLOOKUP(A23,$C$4:$AL$151,15,FALSE),"-"),"Sin tramite") -> - | AJ23: =IFERROR(IF(AH23="SI",VLOOKUP(A23,$C$4:$AL$151,7,FALSE),"-"),"Sin HR") -> - | AK23: =IF(AH23="SI",IFERROR(IF(VLOOKUP(A23,$C$4:$AL$151,25,FALSE)="","Sin registro",VLOOKUP(A23,$C$4:$AL$151,25,FALSE)),"Sin registro"),"-") -> - | AL23: =IF(AH23="SI",IFERROR(IF(VLOOKUP(A23,$C$4:$AL$151,26,FALSE)="","Sin registro",VLOOKUP(A23,$C$4:$AL$151,26,FALSE)),"Sin registro"),"-") -> -
A24: REQ-2026-0021 | B24: =IF(OR(Q24="Desistido",Q24="No corresponde Atención OGTI",Q24="Para reformulación",Q24="Paralizado",Q24="-",Z24="Renovado",AND(AH24="NO",Z24="Culminado")),"NO","SI") -> SI | C24: - | D24: NO | E24: Contratación Directa | F24: Renovación | G24: Servicios | H24: Servicio de alquiler de escáneres de alta Producción para la línea de producción de microformas | I24: 031853-2026 | J24: Alquiler de escáneres de alta Producción | K24: Redes y Comunicaciones | L24: Elliot Hans Lindo Claudet | M24: Elliot Hans Lindo Claudet | N24: Oficina de Infraestructura Tecnológica | O24: 43992 | Q24: Ejecutado | R24: - | S24: - | T24: =IFERROR(IF(OR(Q24="Ejecutado",Q24="No corresponde atención OGTI",Q24="Desistido",Q24="-",Q24="Para reformulación"),"-",IF(OR(S24="-",S24=""),"Falta fecha_estado",NETWORKDAYS(S24,TODAY(),{"02/04/2026";"03/04/2026";"30/06/2026"}))),"-") -> - | U24: Contrato | V24: 003-2026-EF/43.03/CM | W24: 46086 | X24: GRUPO VENTURA PERU S.A.C. | Y24: Elliot Hans Lindo Claudet | Z24: =IFERROR(IF(Q24="-","-",IF(Q24="Proceso de implementación/Activación/Entrega","Proceso de implementación/Activación/Entrega",IF(OR(Q24="Desistido",Q24="No corresponde atención OGTI",Q24="Para reformulación"),Q24,IF(AND(Q24="Ejecutado",AA24="No aplica",AB24="No Aplica"),"Culminado",IF(Q24="Ejecutado",IF(AND(AC24="-",G24="Bienes"),"Culminado",IF(AC24="-","Falta informacion",IF(AND(AB24-TODAY()>=0,AB24-TODAY()<=90),"Vigente_por vencer",IF(AND(AH24<>"SI",AB24<TODAY()),"Culminado",IF(AND(AH24="SI",AB24<TODAY(),OR(AK24="Sin Registro",AL24="Sin Registro")),"Vencido",IF(AND(AH24="SI",AB24<TODAY(),AK24>AA24,AL24>AB24),"Renovado","Vigente")))))),"En tramite"))))),"-") -> Vigente | AA24: 46090 | AB24: 46449 | AC24: =IFERROR(IF(OR(AA24="-",AA24="",AB24="-",AB24=""),"-",CONCATENATE('Seguimiento OIT'!AB24-'Seguimiento OIT'!AA24+1," dias")),"-") -> 360 dias | AD24: =IFERROR(IF(Z24="Vencido",(TODAY()-AB24)+1,"-"),"-") -> - | AE24: - | AG24: https://mefgobpe1.sharepoint.com/:f:/t/DireccindelaOficinadeInfraestructuraTecnolgica/IgByz6DfXvV6SaiSj3QDxmGgAbuEEZLO-att1RGPIFhijJY?e=fhYV1S | AH24: NO | AI24: =IFERROR(IF(AH24="SI",VLOOKUP(A24,$C$4:$AL$151,15,FALSE),"-"),"Sin tramite") -> - | AJ24: =IFERROR(IF(AH24="SI",VLOOKUP(A24,$C$4:$AL$151,7,FALSE),"-"),"Sin HR") -> - | AK24: =IF(AH24="SI",IFERROR(IF(VLOOKUP(A24,$C$4:$AL$151,25,FALSE)="","Sin registro",VLOOKUP(A24,$C$4:$AL$151,25,FALSE)),"Sin registro"),"-") -> - | AL24: =IF(AH24="SI",IFERROR(IF(VLOOKUP(A24,$C$4:$AL$151,26,FALSE)="","Sin registro",VLOOKUP(A24,$C$4:$AL$151,26,FALSE)),"Sin registro"),"-") -> -
A25: REQ-2026-0022 | B25: =IF(OR(Q25="Desistido",Q25="No corresponde Atención OGTI",Q25="Para reformulación",Q25="Paralizado",Q25="-",Z25="Renovado",AND(AH25="NO",Z25="Culminado")),"NO","SI") -> NO | C25: - | D25: NO | E25: Contratación Directa | F25: Nuevo requerimiento (Apoyo técnico AUS) | G25: Bienes | H25: Adquisición de trípodes para uso de captura fotográfica de documentos históricos del Ministerio de Economía y Finanzas | I25: 109789-2026 | J25: *Tripode con aro de luz *Tripode Cenital | K25: Soporte Tecnico | L25: Napoleon Alva Vasquez | M25: Ronald Yrupailla Diaz | N25: Oficina General de Servicios al Usuario | O25: 1698 | P25: 46192 | Q25: Ejecutado | R25: - | S25: - | T25: =IFERROR(IF(OR(Q25="Ejecutado",Q25="No corresponde atención OGTI",Q25="Desistido",Q25="-",Q25="Para reformulación"),"-",IF(OR(S25="-",S25=""),"Falta fecha_estado",NETWORKDAYS(S25,TODAY(),{"02/04/2026";"03/04/2026";"30/06/2026"}))),"-") -> - | U25: Orden de Compra | V25: *0000204-2026 *0000205-2026 | W25: 46192 | X25: *INVERSIONES FOTOGRAFICAS DEL PERU S.A.C *ELECTRONICA MUSICAL SOCIEDAD ANONIMA CERRADA | Y25: Kevin Alexis Escobar Vega (OGSU) kescobar@mef.gob.pe | Z25: =IFERROR(IF(Q25="-","-",IF(Q25="Proceso de implementación/Activación/Entrega","Proceso de implementación/Activación/Entrega",IF(OR(Q25="Desistido",Q25="No corresponde atención OGTI",Q25="Para reformulación"),Q25,IF(AND(Q25="Ejecutado",AA25="No aplica",AB25="No Aplica"),"Culminado",IF(Q25="Ejecutado",IF(AND(AC25="-",G25="Bienes"),"Culminado",IF(AC25="-","Falta informacion",IF(AND(AB25-TODAY()>=0,AB25-TODAY()<=90),"Vigente_por vencer",IF(AND(AH25<>"SI",AB25<TODAY()),"Culminado",IF(AND(AH25="SI",AB25<TODAY(),OR(AK25="Sin Registro",AL25="Sin Registro")),"Vencido",IF(AND(AH25="SI",AB25<TODAY(),AK25>AA25,AL25>AB25),"Renovado","Vigente")))))),"En tramite"))))),"-") -> Culminado | AA25: - | AB25: - | AC25: =IFERROR(IF(OR(AA25="-",AA25="",AB25="-",AB25=""),"-",CONCATENATE('Seguimiento OIT'!AB25-'Seguimiento OIT'!AA25+1," dias")),"-") -> - | AD25: =IFERROR(IF(Z25="Vencido",(TODAY()-AB25)+1,"-"),"-") -> - | AE25: Validación de ofertas, fue enviada por Cesar Muñoz el 15-0626 | AF25: *Conformidad OC 204- HR 142277-2026 *Conformidad OC 205- HR 142311-2026 *03-07-26 OIT brindò su opinion favorable via correo electrònico | AG25: https://mefgobpe1.sharepoint.com/:f:/t/DireccindelaOficinadeInfraestructuraTecnolgica/IgDky8i02ETlQK-qjRtzCLJNAY7eP5CRffdnZDdkunAdmLo?e=H75nC0 | AH25: NO | AI25: =IFERROR(IF(AH25="SI",VLOOKUP(A25,$C$4:$AL$151,15,FALSE),"-"),"Sin tramite") -> - | AJ25: =IFERROR(IF(AH25="SI",VLOOKUP(A25,$C$4:$AL$151,7,FALSE),"-"),"Sin HR") -> - | AK25: =IF(AH25="SI",IFERROR(IF(VLOOKUP(A25,$C$4:$AL$151,25,FALSE)="","Sin registro",VLOOKUP(A25,$C$4:$AL$151,25,FALSE)),"Sin registro"),"-") -> - | AL25: =IF(AH25="SI",IFERROR(IF(VLOOKUP(A25,$C$4:$AL$151,26,FALSE)="","Sin registro",VLOOKUP(A25,$C$4:$AL$151,26,FALSE)),"Sin registro"),"-") -> -
A26: REQ-2026-0023 | B26: =IF(OR(Q26="Desistido",Q26="No corresponde Atención OGTI",Q26="Para reformulación",Q26="Paralizado",Q26="-",Z26="Renovado",AND(AH26="NO",Z26="Culminado")),"NO","SI") -> NO | C26: - | D26: NO | E26: Contratación Directa | F26: Nuevo requerimiento | G26: Bienes | H26: Adquisición de lectoras externas de CD/DVD para el Tribunal Fiscal | I26: *117491-2026 (Requerimiento) **111690-2026 (Req inicial) ***114232-2026 (Apoyo presupuestal) | J26: Lectoras externas de CD/DVD (30 unidades) | K26: Soporte Tecnico | L26: Napoleon Alva Vasquez | M26: Ronald Yrupailla Diaz | N26: Tribunal Fiscal | O26: 3157.04 | P26: 46170 | Q26: Ejecutado | R26: - | S26: - | T26: =IFERROR(IF(OR(Q26="Ejecutado",Q26="No corresponde atención OGTI",Q26="Desistido",Q26="-",Q26="Para reformulación"),"-",IF(OR(S26="-",S26=""),"Falta fecha_estado",NETWORKDAYS(S26,TODAY(),{"02/04/2026";"03/04/2026";"30/06/2026"}))),"-") -> - | U26: Orden de Compra | V26: 0000200-2026 | W26: 46191 | X26: RAM STORE S.A.C. | Y26: Napoleon Alva Vasquez | Z26: =IFERROR(IF(Q26="-","-",IF(Q26="Proceso de implementación/Activación/Entrega","Proceso de implementación/Activación/Entrega",IF(OR(Q26="Desistido",Q26="No corresponde atención OGTI",Q26="Para reformulación"),Q26,IF(AND(Q26="Ejecutado",AA26="No aplica",AB26="No Aplica"),"Culminado",IF(Q26="Ejecutado",IF(AND(AC26="-",G26="Bienes"),"Culminado",IF(AC26="-","Falta informacion",IF(AND(AB26-TODAY()>=0,AB26-TODAY()<=90),"Vigente_por vencer",IF(AND(AH26<>"SI",AB26<TODAY()),"Culminado",IF(AND(AH26="SI",AB26<TODAY(),OR(AK26="Sin Registro",AL26="Sin Registro")),"Vencido",IF(AND(AH26="SI",AB26<TODAY(),AK26>AA26,AL26>AB26),"Renovado","Vigente")))))),"En tramite"))))),"-") -> Culminado | AA26: - | AB26: - | AC26: =IFERROR(IF(OR(AA26="-",AA26="",AB26="-",AB26=""),"-",CONCATENATE('Seguimiento OIT'!AB26-'Seguimiento OIT'!AA26+1," dias")),"-") -> - | AD26: =IFERROR(IF(Z26="Vencido",(TODAY()-AB26)+1,"-"),"-") -> - | AE26: Validación de ofertas, fue enviada por Cesar Muñoz el 08-0626 | AF26: *Plazo maximo de entrega 28-06-26 *Conformidad 142198-2026 | AG26: https://mefgobpe1.sharepoint.com/:f:/t/DireccindelaOficinadeInfraestructuraTecnolgica/IgARkGxBhBLuTIDw-AnIkVpjAQdVJ4Q7KQrpsR9OBEzSV3E?e=hICdmD | AH26: NO | AI26: =IFERROR(IF(AH26="SI",VLOOKUP(A26,$C$4:$AL$151,15,FALSE),"-"),"Sin tramite") -> - | AJ26: =IFERROR(IF(AH26="SI",VLOOKUP(A26,$C$4:$AL$151,7,FALSE),"-"),"Sin HR") -> - | AK26: =IF(AH26="SI",IFERROR(IF(VLOOKUP(A26,$C$4:$AL$151,25,FALSE)="","Sin registro",VLOOKUP(A26,$C$4:$AL$151,25,FALSE)),"Sin registro"),"-") -> - | AL26: =IF(AH26="SI",IFERROR(IF(VLOOKUP(A26,$C$4:$AL$151,26,FALSE)="","Sin registro",VLOOKUP(A26,$C$4:$AL$151,26,FALSE)),"Sin registro"),"-") -> -
A27: REQ-2026-0024 | B27: =IF(OR(Q27="Desistido",Q27="No corresponde Atención OGTI",Q27="Para reformulación",Q27="Paralizado",Q27="-",Z27="Renovado",AND(AH27="NO",Z27="Culminado")),"NO","SI") -> SI | C27: - | D27: NO | E27: Contratación Directa | F27: Nuevo requerimiento (Apoyo técnico AUS) | G27: Servicios | H27: Servicio de suscripción anual a plataforma web para descarga de fotografías, imágenes y vectores | I27: 099186-2026 | J27: Freepick - Magnific (02 Unidades) | K27: Soporte Tecnico | L27: Napoleon Alva Vasquez | M27: Ronald Yrupailla Diaz | N27: Oficina de Comunicaciones | O27: 1958.8 | P27: 46188 | Q27: Ejecutado | R27: - | S27: - | T27: =IFERROR(IF(OR(Q27="Ejecutado",Q27="No corresponde atención OGTI",Q27="Desistido",Q27="-",Q27="Para reformulación"),"-",IF(OR(S27="-",S27=""),"Falta fecha_estado",NETWORKDAYS(S27,TODAY(),{"02/04/2026";"03/04/2026";"30/06/2026"}))),"-") -> - | U27: Orden de Servicio | V27: 0002992-2026 | W27: 46189 | X27: CUBICERP PERU S.R.L. | Y27: Rosa Alvarado Saavedra, ralvarado@mef.gob.pe / Josue Levano consultor_oc53@mef.gob.pe (Oficina de Comunicaciones) | Z27: =IFERROR(IF(Q27="-","-",IF(Q27="Proceso de implementación/Activación/Entrega","Proceso de implementación/Activación/Entrega",IF(OR(Q27="Desistido",Q27="No corresponde atención OGTI",Q27="Para reformulación"),Q27,IF(AND(Q27="Ejecutado",AA27="No aplica",AB27="No Aplica"),"Culminado",IF(Q27="Ejecutado",IF(AND(AC27="-",G27="Bienes"),"Culminado",IF(AC27="-","Falta informacion",IF(AND(AB27-TODAY()>=0,AB27-TODAY()<=90),"Vigente_por vencer",IF(AND(AH27<>"SI",AB27<TODAY()),"Culminado",IF(AND(AH27="SI",AB27<TODAY(),OR(AK27="Sin Registro",AL27="Sin Registro")),"Vencido",IF(AND(AH27="SI",AB27<TODAY(),AK27>AA27,AL27>AB27),"Renovado","Vigente")))))),"En tramite"))))),"-") -> Vigente | AA27: 46192 | AB27: 46556 | AC27: =IFERROR(IF(OR(AA27="-",AA27="",AB27="-",AB27=""),"-",CONCATENATE('Seguimiento OIT'!AB27-'Seguimiento OIT'!AA27+1," dias")),"-") -> 365 dias | AD27: =IFERROR(IF(Z27="Vencido",(TODAY()-AB27)+1,"-"),"-") -> - | AE27: Validación de ofertas, fue enviada por Napoleon Alva el 15-06-26 | AF27: *Plazo maximo de activación 23-06-26 *Conformidad HR 136390-2026 | AG27: https://mefgobpe1.sharepoint.com/:f:/t/DireccindelaOficinadeInfraestructuraTecnolgica/IgDoXKLz4NE9Tqyf56JnMjHPAcHoSL-YGFCuyQgQ-wd8rb8?e=ZAiGSf | AH27: NO | AI27: =IFERROR(IF(AH27="SI",VLOOKUP(A27,$C$4:$AL$151,15,FALSE),"-"),"Sin tramite") -> - | AJ27: =IFERROR(IF(AH27="SI",VLOOKUP(A27,$C$4:$AL$151,7,FALSE),"-"),"Sin HR") -> - | AK27: =IF(AH27="SI",IFERROR(IF(VLOOKUP(A27,$C$4:$AL$151,25,FALSE)="","Sin registro",VLOOKUP(A27,$C$4:$AL$151,25,FALSE)),"Sin registro"),"-") -> - | AL27: =IF(AH27="SI",IFERROR(IF(VLOOKUP(A27,$C$4:$AL$151,26,FALSE)="","Sin registro",VLOOKUP(A27,$C$4:$AL$151,26,FALSE)),"Sin registro"),"-") -> -
A28: REQ-2026-0025 | B28: =IF(OR(Q28="Desistido",Q28="No corresponde Atención OGTI",Q28="Para reformulación",Q28="Paralizado",Q28="-",Z28="Renovado",AND(AH28="NO",Z28="Culminado")),"NO","SI") -> NO | C28: - | D28: NO | E28: Contratación Directa | F28: Nuevo requerimiento (Apoyo técnico AUS) | G28: Bienes | H28: Adquisición de 300 USB | I28: Correo electrónico 05-06-26 | J28: Dispositivo USB (300 unidades) | K28: Soporte Tecnico | L28: Napoleon Alva Vasquez | M28: Ronald Yrupailla Diaz | N28: Dirección General de Programación Multianual de Inversiones | O28: - | P28: 46178 | Q28: No corresponde atención OGTI | R28: - | S28: - | T28: =IFERROR(IF(OR(Q28="Ejecutado",Q28="No corresponde atención OGTI",Q28="Desistido",Q28="-",Q28="Para reformulación"),"-",IF(OR(S28="-",S28=""),"Falta fecha_estado",NETWORKDAYS(S28,TODAY(),{"02/04/2026";"03/04/2026";"30/06/2026"}))),"-") -> - | U28: - | V28: - | W28: - | X28: - | Y28: - | Z28: =IFERROR(IF(Q28="-","-",IF(Q28="Proceso de implementación/Activación/Entrega","Proceso de implementación/Activación/Entrega",IF(OR(Q28="Desistido",Q28="No corresponde atención OGTI",Q28="Para reformulación"),Q28,IF(AND(Q28="Ejecutado",AA28="No aplica",AB28="No Aplica"),"Culminado",IF(Q28="Ejecutado",IF(AND(AC28="-",G28="Bienes"),"Culminado",IF(AC28="-","Falta informacion",IF(AND(AB28-TODAY()>=0,AB28-TODAY()<=90),"Vigente_por vencer",IF(AND(AH28<>"SI",AB28<TODAY()),"Culminado",IF(AND(AH28="SI",AB28<TODAY(),OR(AK28="Sin Registro",AL28="Sin Registro")),"Vencido",IF(AND(AH28="SI",AB28<TODAY(),AK28>AA28,AL28>AB28),"Renovado","Vigente")))))),"En tramite"))))),"-") -> No corresponde atención OGTI | AA28: - | AB28: - | AC28: =IFERROR(IF(OR(AA28="-",AA28="",AB28="-",AB28=""),"-",CONCATENATE('Seguimiento OIT'!AB28-'Seguimiento OIT'!AA28+1," dias")),"-") -> - | AD28: =IFERROR(IF(Z28="Vencido",(TODAY()-AB28)+1,"-"),"-") -> - | AE28: *No crresponde atención de OGTI, considerando que corresponde a merchandising institucional. *Se remitió EETT referenciales | AF28: - | AG28: https://mefgobpe1.sharepoint.com/:f:/t/DireccindelaOficinadeInfraestructuraTecnolgica/IgBLxDtaZfKnRrwzowRjwG-_ASZQ5oP-5uso6q0-otUe3aY?e=M1mghK | AH28: NO | AI28: =IFERROR(IF(AH28="SI",VLOOKUP(A28,$C$4:$AL$151,15,FALSE),"-"),"Sin tramite") -> - | AJ28: =IFERROR(IF(AH28="SI",VLOOKUP(A28,$C$4:$AL$151,7,FALSE),"-"),"Sin HR") -> - | AK28: =IF(AH28="SI",IFERROR(IF(VLOOKUP(A28,$C$4:$AL$151,25,FALSE)="","Sin registro",VLOOKUP(A28,$C$4:$AL$151,25,FALSE)),"Sin registro"),"-") -> - | AL28: =IF(AH28="SI",IFERROR(IF(VLOOKUP(A28,$C$4:$AL$151,26,FALSE)="","Sin registro",VLOOKUP(A28,$C$4:$AL$151,26,FALSE)),"Sin registro"),"-") -> -
A29: REQ-2026-0026 | B29: =IF(OR(Q29="Desistido",Q29="No corresponde Atención OGTI",Q29="Para reformulación",Q29="Paralizado",Q29="-",Z29="Renovado",AND(AH29="NO",Z29="Culminado")),"NO","SI") -> SI | C29: - | D29: NO | E29: Contratación Directa | F29: Nuevo requerimiento (Apoyo técnico AUS) | G29: Bienes | H29: Adquisición de discos blu-ray para grabación de microformas con valor legal. | I29: *133762-2026 (Requerimiento) **125462-2026 (Req Inicial) | J29: Discos Blu-Ray (1500 unidades) | K29: Soporte Tecnico | L29: Napoleon Alva Vasquez | M29: Ronald Yrupailla Diaz | N29: Oficina General de Servicios al Usuario | O29: 2520 | P29: 46190 | Q29: Emisión de Conformidad | R29: Área Usuaria | S29: 46224 | T29: =IFERROR(IF(OR(Q29="Ejecutado",Q29="No corresponde atención OGTI",Q29="Desistido",Q29="-",Q29="Para reformulación"),"-",IF(OR(S29="-",S29=""),"Falta fecha_estado",NETWORKDAYS(S29,TODAY(),{"02/04/2026";"03/04/2026";"30/06/2026"}))),"-") -> 9 | U29: Orden de Compra | V29: 0000231-2026 | W29: 30-06-26 | X29: T&G INFORMATICA SOCIEDAD ANONIMA CERRADA | Y29: Napoleon Alva Vasquez | Z29: =IFERROR(IF(Q29="-","-",IF(Q29="Proceso de implementación/Activación/Entrega","Proceso de implementación/Activación/Entrega",IF(OR(Q29="Desistido",Q29="No corresponde atención OGTI",Q29="Para reformulación"),Q29,IF(AND(Q29="Ejecutado",AA29="No aplica",AB29="No Aplica"),"Culminado",IF(Q29="Ejecutado",IF(AND(AC29="-",G29="Bienes"),"Culminado",IF(AC29="-","Falta informacion",IF(AND(AB29-TODAY()>=0,AB29-TODAY()<=90),"Vigente_por vencer",IF(AND(AH29<>"SI",AB29<TODAY()),"Culminado",IF(AND(AH29="SI",AB29<TODAY(),OR(AK29="Sin Registro",AL29="Sin Registro")),"Vencido",IF(AND(AH29="SI",AB29<TODAY(),AK29>AA29,AL29>AB29),"Renovado","Vigente")))))),"En tramite"))))),"-") -> En tramite | AA29: - | AB29: - | AC29: =IFERROR(IF(OR(AA29="-",AA29="",AB29="-",AB29=""),"-",CONCATENATE('Seguimiento OIT'!AB29-'Seguimiento OIT'!AA29+1," dias")),"-") -> - | AD29: =IFERROR(IF(Z29="Vencido",(TODAY()-AB29)+1,"-"),"-") -> - | AE29: - | AF29: *Tramite de Conformidad 153251-2026, area usuaria reportò una observación | AG29: https://mefgobpe1.sharepoint.com/:f:/t/DireccindelaOficinadeInfraestructuraTecnolgica/IgBXA1N5IM_fSbK-4mBAuULUAebZf_uVcw4YU2bBO9snkQ0?e=zzrCXa | AH29: NO | AI29: =IFERROR(IF(AH29="SI",VLOOKUP(A29,$C$4:$AL$151,15,FALSE),"-"),"Sin tramite") -> - | AJ29: =IFERROR(IF(AH29="SI",VLOOKUP(A29,$C$4:$AL$151,7,FALSE),"-"),"Sin HR") -> - | AK29: =IF(AH29="SI",IFERROR(IF(VLOOKUP(A29,$C$4:$AL$151,25,FALSE)="","Sin registro",VLOOKUP(A29,$C$4:$AL$151,25,FALSE)),"Sin registro"),"-") -> - | AL29: =IF(AH29="SI",IFERROR(IF(VLOOKUP(A29,$C$4:$AL$151,26,FALSE)="","Sin registro",VLOOKUP(A29,$C$4:$AL$151,26,FALSE)),"Sin registro"),"-") -> -
A30: REQ-2026-0027 | B30: =IF(OR(Q30="Desistido",Q30="No corresponde Atención OGTI",Q30="Para reformulación",Q30="Paralizado",Q30="-",Z30="Renovado",AND(AH30="NO",Z30="Culminado")),"NO","SI") -> SI | C30: - | D30: NO | E30: Contratación Directa | F30: Nuevo requerimiento (Apoyo técnico AUS) | G30: Bienes | H30: Adquisición de Soporte Cooler | I30: Correo electrónico 04-06-26 | J30: Soporte cooler para laptop | K30: Soporte Tecnico | L30: Napoleon Alva Vasquez | M30: Ronald Yrupailla Diaz | N30: Dirección General de Presupuesto Público | O30: Pendiente | P30: 46177 | Q30: Apoyo presupuestal | R30: Área Usuaria | S30: 46189 | T30: =IFERROR(IF(OR(Q30="Ejecutado",Q30="No corresponde atención OGTI",Q30="Desistido",Q30="-",Q30="Para reformulación"),"-",IF(OR(S30="-",S30=""),"Falta fecha_estado",NETWORKDAYS(S30,TODAY(),{"02/04/2026";"03/04/2026";"30/06/2026"}))),"-") -> 33 | U30: - | V30: - | W30: - | X30: - | Y30: - | Z30: =IFERROR(IF(Q30="-","-",IF(Q30="Proceso de implementación/Activación/Entrega","Proceso de implementación/Activación/Entrega",IF(OR(Q30="Desistido",Q30="No corresponde atención OGTI",Q30="Para reformulación"),Q30,IF(AND(Q30="Ejecutado",AA30="No aplica",AB30="No Aplica"),"Culminado",IF(Q30="Ejecutado",IF(AND(AC30="-",G30="Bienes"),"Culminado",IF(AC30="-","Falta informacion",IF(AND(AB30-TODAY()>=0,AB30-TODAY()<=90),"Vigente_por vencer",IF(AND(AH30<>"SI",AB30<TODAY()),"Culminado",IF(AND(AH30="SI",AB30<TODAY(),OR(AK30="Sin Registro",AL30="Sin Registro")),"Vencido",IF(AND(AH30="SI",AB30<TODAY(),AK30>AA30,AL30>AB30),"Renovado","Vigente")))))),"En tramite"))))),"-") -> En tramite | AA30: - | AB30: - | AC30: =IFERROR(IF(OR(AA30="-",AA30="",AB30="-",AB30=""),"-",CONCATENATE('Seguimiento OIT'!AB30-'Seguimiento OIT'!AA30+1," dias")),"-") -> - | AD30: =IFERROR(IF(Z30="Vencido",(TODAY()-AB30)+1,"-"),"-") -> - | AE30: Con fecha 16-06-26 se remitió por correo, al área usuaria, datos referenciales para revisión | AF30: - | AG30: https://mefgobpe1.sharepoint.com/:f:/t/DireccindelaOficinadeInfraestructuraTecnolgica/IgA5gBlY8VItRq97esaRWn-MAcTFFz3f8TojpHvQYGpQOXE?e=djA0vM | AH30: NO | AI30: =IFERROR(IF(AH30="SI",VLOOKUP(A30,$C$4:$AL$151,15,FALSE),"-"),"Sin tramite") -> - | AJ30: =IFERROR(IF(AH30="SI",VLOOKUP(A30,$C$4:$AL$151,7,FALSE),"-"),"Sin HR") -> - | AK30: =IF(AH30="SI",IFERROR(IF(VLOOKUP(A30,$C$4:$AL$151,25,FALSE)="","Sin registro",VLOOKUP(A30,$C$4:$AL$151,25,FALSE)),"Sin registro"),"-") -> - | AL30: =IF(AH30="SI",IFERROR(IF(VLOOKUP(A30,$C$4:$AL$151,26,FALSE)="","Sin registro",VLOOKUP(A30,$C$4:$AL$151,26,FALSE)),"Sin registro"),"-") -> -
A31: REQ-2026-0028 | B31: =IF(OR(Q31="Desistido",Q31="No corresponde Atención OGTI",Q31="Para reformulación",Q31="Paralizado",Q31="-",Z31="Renovado",AND(AH31="NO",Z31="Culminado")),"NO","SI") -> NO | C31: - | D31: NO | E31: Contratación Directa | F31: Nuevo requerimiento | G31: Bienes | H31: Adquisición de televisores para la Oficina General de Servicios al Usuario (OGSU) | I31: 125560-2026 | J31: Televisor (02 unidades) | K31: Soporte Tecnico | L31: Napoleon Alva Vasquez | M31: Ronald Yrupailla Diaz | N31: Oficina General de Servicios al Usuario | O31: - | P31: 46181 | Q31: Para reformulación | R31: OIT-Soporte Tecnico | S31: 46196 | T31: =IFERROR(IF(OR(Q31="Ejecutado",Q31="No corresponde atención OGTI",Q31="Desistido",Q31="-",Q31="Para reformulación"),"-",IF(OR(S31="-",S31=""),"Falta fecha_estado",NETWORKDAYS(S31,TODAY(),{"02/04/2026";"03/04/2026";"30/06/2026"}))),"-") -> - | U31: - | V31: - | W31: - | X31: - | Y31: - | Z31: =IFERROR(IF(Q31="-","-",IF(Q31="Proceso de implementación/Activación/Entrega","Proceso de implementación/Activación/Entrega",IF(OR(Q31="Desistido",Q31="No corresponde atención OGTI",Q31="Para reformulación"),Q31,IF(AND(Q31="Ejecutado",AA31="No aplica",AB31="No Aplica"),"Culminado",IF(Q31="Ejecutado",IF(AND(AC31="-",G31="Bienes"),"Culminado",IF(AC31="-","Falta informacion",IF(AND(AB31-TODAY()>=0,AB31-TODAY()<=90),"Vigente_por vencer",IF(AND(AH31<>"SI",AB31<TODAY()),"Culminado",IF(AND(AH31="SI",AB31<TODAY(),OR(AK31="Sin Registro",AL31="Sin Registro")),"Vencido",IF(AND(AH31="SI",AB31<TODAY(),AK31>AA31,AL31>AB31),"Renovado","Vigente")))))),"En tramite"))))),"-") -> Para reformulación | AA31: - | AB31: - | AC31: =IFERROR(IF(OR(AA31="-",AA31="",AB31="-",AB31=""),"-",CONCATENATE('Seguimiento OIT'!AB31-'Seguimiento OIT'!AA31+1," dias")),"-") -> - | AD31: =IFERROR(IF(Z31="Vencido",(TODAY()-AB31)+1,"-"),"-") -> - | AE31: *Según lo coordinado se tramitará con nueva HR agosto 26 | AF31: - | AG31: https://mefgobpe1.sharepoint.com/:f:/t/DireccindelaOficinadeInfraestructuraTecnolgica/IgBa6v7XUA2jT6nfQhjbJIQhAdGoEhfA_JT7N7P07K2kCj8?e=jm37EK | AH31: NO | AI31: =IFERROR(IF(AH31="SI",VLOOKUP(A31,$C$4:$AL$151,15,FALSE),"-"),"Sin tramite") -> - | AJ31: =IFERROR(IF(AH31="SI",VLOOKUP(A31,$C$4:$AL$151,7,FALSE),"-"),"Sin HR") -> - | AK31: =IF(AH31="SI",IFERROR(IF(VLOOKUP(A31,$C$4:$AL$151,25,FALSE)="","Sin registro",VLOOKUP(A31,$C$4:$AL$151,25,FALSE)),"Sin registro"),"-") -> - | AL31: =IF(AH31="SI",IFERROR(IF(VLOOKUP(A31,$C$4:$AL$151,26,FALSE)="","Sin registro",VLOOKUP(A31,$C$4:$AL$151,26,FALSE)),"Sin registro"),"-") -> -
A32: REQ-2026-0029 | B32: =IF(OR(Q32="Desistido",Q32="No corresponde Atención OGTI",Q32="Para reformulación",Q32="Paralizado",Q32="-",Z32="Renovado",AND(AH32="NO",Z32="Culminado")),"NO","SI") -> NO | C32: - | D32: NO | E32: Contratación Directa | F32: Nuevo requerimiento | G32: Bienes | H32: Adquisición de televisores para el Tribunal Fiscal | I32: 125560-2026 | J32: Televisor (01 unidad) | K32: Soporte Tecnico | L32: Napoleon Alva Vasquez | M32: Ronald Yrupailla Diaz | N32: Tribunal Fiscal | O32: - | P32: 46181 | Q32: Para reformulación | R32: OIT-Soporte Tecnico | S32: 46196 | T32: =IFERROR(IF(OR(Q32="Ejecutado",Q32="No corresponde atención OGTI",Q32="Desistido",Q32="-",Q32="Para reformulación"),"-",IF(OR(S32="-",S32=""),"Falta fecha_estado",NETWORKDAYS(S32,TODAY(),{"02/04/2026";"03/04/2026";"30/06/2026"}))),"-") -> - | U32: - | V32: - | W32: - | X32: - | Y32: - | Z32: =IFERROR(IF(Q32="-","-",IF(Q32="Proceso de implementación/Activación/Entrega","Proceso de implementación/Activación/Entrega",IF(OR(Q32="Desistido",Q32="No corresponde atención OGTI",Q32="Para reformulación"),Q32,IF(AND(Q32="Ejecutado",AA32="No aplica",AB32="No Aplica"),"Culminado",IF(Q32="Ejecutado",IF(AND(AC32="-",G32="Bienes"),"Culminado",IF(AC32="-","Falta informacion",IF(AND(AB32-TODAY()>=0,AB32-TODAY()<=90),"Vigente_por vencer",IF(AND(AH32<>"SI",AB32<TODAY()),"Culminado",IF(AND(AH32="SI",AB32<TODAY(),OR(AK32="Sin Registro",AL32="Sin Registro")),"Vencido",IF(AND(AH32="SI",AB32<TODAY(),AK32>AA32,AL32>AB32),"Renovado","Vigente")))))),"En tramite"))))),"-") -> Para reformulación | AA32: - | AB32: - | AC32: =IFERROR(IF(OR(AA32="-",AA32="",AB32="-",AB32=""),"-",CONCATENATE('Seguimiento OIT'!AB32-'Seguimiento OIT'!AA32+1," dias")),"-") -> - | AD32: =IFERROR(IF(Z32="Vencido",(TODAY()-AB32)+1,"-"),"-") -> - | AE32: *Según lo coordinado se tramitará con nueva HR agosto 26 | AF32: - | AG32: https://mefgobpe1.sharepoint.com/:f:/t/DireccindelaOficinadeInfraestructuraTecnolgica/IgBa6v7XUA2jT6nfQhjbJIQhAdGoEhfA_JT7N7P07K2kCj8?e=jm37EK | AH32: NO | AI32: =IFERROR(IF(AH32="SI",VLOOKUP(A32,$C$4:$AL$151,15,FALSE),"-"),"Sin tramite") -> - | AJ32: =IFERROR(IF(AH32="SI",VLOOKUP(A32,$C$4:$AL$151,7,FALSE),"-"),"Sin HR") -> - | AK32: =IF(AH32="SI",IFERROR(IF(VLOOKUP(A32,$C$4:$AL$151,25,FALSE)="","Sin registro",VLOOKUP(A32,$C$4:$AL$151,25,FALSE)),"Sin registro"),"-") -> - | AL32: =IF(AH32="SI",IFERROR(IF(VLOOKUP(A32,$C$4:$AL$151,26,FALSE)="","Sin registro",VLOOKUP(A32,$C$4:$AL$151,26,FALSE)),"Sin registro"),"-") -> -
A33: REQ-2026-0030 | B33: =IF(OR(Q33="Desistido",Q33="No corresponde Atención OGTI",Q33="Para reformulación",Q33="Paralizado",Q33="-",Z33="Renovado",AND(AH33="NO",Z33="Culminado")),"NO","SI") -> SI | C33: - | D33: NO | E33: Contratación Directa | F33: Renovación | G33: Servicios | H33: Servicio de conectividad de red entre la Sede del Centro de Capacitaciones (CCM) y la sede del ex tribunal fiscal San isidro del Ministerio de Economía y Finanzas | I33: I-247338-2025 (Requerimiento) | J33: Conectividad de red | K33: Redes y Comunicaciones | L33: Elliot Hans Lindo Claudet | M33: Elliot Hans Lindo Claudet | N33: Oficina de Infraestructura Tecnológica | O33: 42480 | Q33: Ejecutado | R33: - | S33: - | T33: =IFERROR(IF(OR(Q33="Ejecutado",Q33="No corresponde atención OGTI",Q33="Desistido",Q33="-",Q33="Para reformulación"),"-",IF(OR(S33="-",S33=""),"Falta fecha_estado",NETWORKDAYS(S33,TODAY(),{"02/04/2026";"03/04/2026";"30/06/2026"}))),"-") -> - | U33: Contrato | V33: 059-2025-EF/43.03 | W33: 46021 | X33: GDT PERÚ S.A | Y33: Elliot Hans Lindo Claudet | Z33: =IFERROR(IF(Q33="-","-",IF(Q33="Proceso de implementación/Activación/Entrega","Proceso de implementación/Activación/Entrega",IF(OR(Q33="Desistido",Q33="No corresponde atención OGTI",Q33="Para reformulación"),Q33,IF(AND(Q33="Ejecutado",AA33="No aplica",AB33="No Aplica"),"Culminado",IF(Q33="Ejecutado",IF(AND(AC33="-",G33="Bienes"),"Culminado",IF(AC33="-","Falta informacion",IF(AND(AB33-TODAY()>=0,AB33-TODAY()<=90),"Vigente_por vencer",IF(AND(AH33<>"SI",AB33<TODAY()),"Culminado",IF(AND(AH33="SI",AB33<TODAY(),OR(AK33="Sin Registro",AL33="Sin Registro")),"Vencido",IF(AND(AH33="SI",AB33<TODAY(),AK33>AA33,AL33>AB33),"Renovado","Vigente")))))),"En tramite"))))),"-") -> Vigente | AA33: 46047 | AB33: 46411 | AC33: =IFERROR(IF(OR(AA33="-",AA33="",AB33="-",AB33=""),"-",CONCATENATE('Seguimiento OIT'!AB33-'Seguimiento OIT'!AA33+1," dias")),"-") -> 365 dias | AD33: =IFERROR(IF(Z33="Vencido",(TODAY()-AB33)+1,"-"),"-") -> - | AE33: - | AG33: https://mefgobpe1.sharepoint.com/:f:/t/DireccindelaOficinadeInfraestructuraTecnolgica/IgA0R5MMthTbQLxbmjQ4a9jDATdvi_mCfsIDW4JFeRnA_r0?e=gtG8Ku | AH33: NO | AI33: =IFERROR(IF(AH33="SI",VLOOKUP(A33,$C$4:$AL$151,15,FALSE),"-"),"Sin tramite") -> - | AJ33: =IFERROR(IF(AH33="SI",VLOOKUP(A33,$C$4:$AL$151,7,FALSE),"-"),"Sin HR") -> - | AK33: =IF(AH33="SI",IFERROR(IF(VLOOKUP(A33,$C$4:$AL$151,25,FALSE)="","Sin registro",VLOOKUP(A33,$C$4:$AL$151,25,FALSE)),"Sin registro"),"-") -> - | AL33: =IF(AH33="SI",IFERROR(IF(VLOOKUP(A33,$C$4:$AL$151,26,FALSE)="","Sin registro",VLOOKUP(A33,$C$4:$AL$151,26,FALSE)),"Sin registro"),"-") -> -
A34: REQ-2026-0031 | B34: =IF(OR(Q34="Desistido",Q34="No corresponde Atención OGTI",Q34="Para reformulación",Q34="Paralizado",Q34="-",Z34="Renovado",AND(AH34="NO",Z34="Culminado")),"NO","SI") -> SI | C34: - | D34: NO | E34: Contratación Directa | F34: Nuevo requerimiento | G34: Bienes | H34: Adquisición de accesorios informáticos para equipos de cómputo de la Dirección General de Presupuesto Público | I34: 105280-2026 | J34: *Dos (02) Puntero laser inalámbrico para presentación de diapositivas *Dos (02) Extensores inalámbrico de señal HDMI/VGA *Diez (10) Memoria Portátil USB con cifrado | K34: Soporte Tecnico | L34: Napoleon Alva Vasquez | M34: Ronald Yrupailla Diaz | N34: Dirección General de Presupuesto Público | O34: 1966 | P34: 46185 | Q34: Proceso de implementación/Activación/Entrega | R34: OIT-Soporte Tecnico | S34: 46216 | T34: =IFERROR(IF(OR(Q34="Ejecutado",Q34="No corresponde atención OGTI",Q34="Desistido",Q34="-",Q34="Para reformulación"),"-",IF(OR(S34="-",S34=""),"Falta fecha_estado",NETWORKDAYS(S34,TODAY(),{"02/04/2026";"03/04/2026";"30/06/2026"}))),"-") -> 15 | U34: Orden de Compra | V34: 0000239-2026 | W34: 13-07-26 | X34: RAINFA E.I.R.L. | Y34: Napoleon Alva Vasquez | Z34: =IFERROR(IF(Q34="-","-",IF(Q34="Proceso de implementación/Activación/Entrega","Proceso de implementación/Activación/Entrega",IF(OR(Q34="Desistido",Q34="No corresponde atención OGTI",Q34="Para reformulación"),Q34,IF(AND(Q34="Ejecutado",AA34="No aplica",AB34="No Aplica"),"Culminado",IF(Q34="Ejecutado",IF(AND(AC34="-",G34="Bienes"),"Culminado",IF(AC34="-","Falta informacion",IF(AND(AB34-TODAY()>=0,AB34-TODAY()<=90),"Vigente_por vencer",IF(AND(AH34<>"SI",AB34<TODAY()),"Culminado",IF(AND(AH34="SI",AB34<TODAY(),OR(AK34="Sin Registro",AL34="Sin Registro")),"Vencido",IF(AND(AH34="SI",AB34<TODAY(),AK34>AA34,AL34>AB34),"Renovado","Vigente")))))),"En tramite"))))),"-") -> Proceso de implementación/Activación/Entrega | AA34: - | AB34: - | AC34: =IFERROR(IF(OR(AA34="-",AA34="",AB34="-",AB34=""),"-",CONCATENATE('Seguimiento OIT'!AB34-'Seguimiento OIT'!AA34+1," dias")),"-") -> - | AD34: =IFERROR(IF(Z34="Vencido",(TODAY()-AB34)+1,"-"),"-") -> - | AE34: - | AF34: Conformidad (HR 163396-2026) | AG34: https://mefgobpe1.sharepoint.com/:f:/t/DireccindelaOficinadeInfraestructuraTecnolgica/IgClC0OTToCDT6oGNBM5jfewAeFgWpwpzloVtV_wDB75PUA?e=1HQdlB | AH34: NO | AI34: =IFERROR(IF(AH34="SI",VLOOKUP(A34,$C$4:$AL$151,15,FALSE),"-"),"Sin tramite") -> - | AJ34: =IFERROR(IF(AH34="SI",VLOOKUP(A34,$C$4:$AL$151,7,FALSE),"-"),"Sin HR") -> - | AK34: =IF(AH34="SI",IFERROR(IF(VLOOKUP(A34,$C$4:$AL$151,25,FALSE)="","Sin registro",VLOOKUP(A34,$C$4:$AL$151,25,FALSE)),"Sin registro"),"-") -> - | AL34: =IF(AH34="SI",IFERROR(IF(VLOOKUP(A34,$C$4:$AL$151,26,FALSE)="","Sin registro",VLOOKUP(A34,$C$4:$AL$151,26,FALSE)),"Sin registro"),"-") -> -
A35: REQ-2026-0032 | B35: =IF(OR(Q35="Desistido",Q35="No corresponde Atención OGTI",Q35="Para reformulación",Q35="Paralizado",Q35="-",Z35="Renovado",AND(AH35="NO",Z35="Culminado")),"NO","SI") -> NO | C35: - | D35: NO | E35: Contratación Directa | F35: Nuevo requerimiento | G35: Bienes | H35: Adquisición de Auriculares | I35: Correo electrónico 04-06-26 | J35: Auriculares | K35: Soporte Tecnico | L35: Napoleon Alva Vasquez | M35: Ronald Yrupailla Diaz | N35: Oficina de Comunicaciones | O35: - | P35: 46127 | Q35: Desistido | R35: Área Usuaria | S35: 46162 | T35: =IFERROR(IF(OR(Q35="Ejecutado",Q35="No corresponde atención OGTI",Q35="Desistido",Q35="-",Q35="Para reformulación"),"-",IF(OR(S35="-",S35=""),"Falta fecha_estado",NETWORKDAYS(S35,TODAY(),{"02/04/2026";"03/04/2026";"30/06/2026"}))),"-") -> - | U35: - | V35: - | W35: - | X35: - | Y35: - | Z35: =IFERROR(IF(Q35="-","-",IF(Q35="Proceso de implementación/Activación/Entrega","Proceso de implementación/Activación/Entrega",IF(OR(Q35="Desistido",Q35="No corresponde atención OGTI",Q35="Para reformulación"),Q35,IF(AND(Q35="Ejecutado",AA35="No aplica",AB35="No Aplica"),"Culminado",IF(Q35="Ejecutado",IF(AND(AC35="-",G35="Bienes"),"Culminado",IF(AC35="-","Falta informacion",IF(AND(AB35-TODAY()>=0,AB35-TODAY()<=90),"Vigente_por vencer",IF(AND(AH35<>"SI",AB35<TODAY()),"Culminado",IF(AND(AH35="SI",AB35<TODAY(),OR(AK35="Sin Registro",AL35="Sin Registro")),"Vencido",IF(AND(AH35="SI",AB35<TODAY(),AK35>AA35,AL35>AB35),"Renovado","Vigente")))))),"En tramite"))))),"-") -> Desistido | AA35: - | AB35: - | AC35: =IFERROR(IF(OR(AA35="-",AA35="",AB35="-",AB35=""),"-",CONCATENATE('Seguimiento OIT'!AB35-'Seguimiento OIT'!AA35+1," dias")),"-") -> - | AD35: =IFERROR(IF(Z35="Vencido",(TODAY()-AB35)+1,"-"),"-") -> - | AE35: Con fecha 20-05-26, el área usuaria desistió del requerimiento a través de correo electrónico. | AF35: - | AG35: https://mefgobpe1.sharepoint.com/:f:/t/DireccindelaOficinadeInfraestructuraTecnolgica/IgA90WhNiS2ISL-dyIhAIXhKAWgrgtxNRaQbDF3PoJd1trE?e=0SUbeb | AH35: NO | AI35: =IFERROR(IF(AH35="SI",VLOOKUP(A35,$C$4:$AL$151,15,FALSE),"-"),"Sin tramite") -> - | AJ35: =IFERROR(IF(AH35="SI",VLOOKUP(A35,$C$4:$AL$151,7,FALSE),"-"),"Sin HR") -> - | AK35: =IF(AH35="SI",IFERROR(IF(VLOOKUP(A35,$C$4:$AL$151,25,FALSE)="","Sin registro",VLOOKUP(A35,$C$4:$AL$151,25,FALSE)),"Sin registro"),"-") -> - | AL35: =IF(AH35="SI",IFERROR(IF(VLOOKUP(A35,$C$4:$AL$151,26,FALSE)="","Sin registro",VLOOKUP(A35,$C$4:$AL$151,26,FALSE)),"Sin registro"),"-") -> -
A36: REQ-2026-0033 | B36: =IF(OR(Q36="Desistido",Q36="No corresponde Atención OGTI",Q36="Para reformulación",Q36="Paralizado",Q36="-",Z36="Renovado",AND(AH36="NO",Z36="Culminado")),"NO","SI") -> NO | C36: - | D36: NO | E36: Contratación Directa | F36: Nuevo requerimiento | G36: Servicios | H36: Servicio de interconexión mediante enlace de fibra gestionada | I36: 070507-2026 | J36: Enlace de fibra entre el CPD principal y el CPD de contingencia | K36: Redes y Comunicaciones | L36: Elliot Hans Lindo Claudet | M36: José Romucho Sotelo | N36: Oficina de Infraestructura Tecnológica | O36: - | P36: 46104 | Q36: Desistido | R36: Área Usuaria | S36: 46134 | T36: =IFERROR(IF(OR(Q36="Ejecutado",Q36="No corresponde atención OGTI",Q36="Desistido",Q36="-",Q36="Para reformulación"),"-",IF(OR(S36="-",S36=""),"Falta fecha_estado",NETWORKDAYS(S36,TODAY(),{"02/04/2026";"03/04/2026";"30/06/2026"}))),"-") -> - | U36: - | V36: - | W36: - | X36: - | Y36: - | Z36: =IFERROR(IF(Q36="-","-",IF(Q36="Proceso de implementación/Activación/Entrega","Proceso de implementación/Activación/Entrega",IF(OR(Q36="Desistido",Q36="No corresponde atención OGTI",Q36="Para reformulación"),Q36,IF(AND(Q36="Ejecutado",AA36="No aplica",AB36="No Aplica"),"Culminado",IF(Q36="Ejecutado",IF(AND(AC36="-",G36="Bienes"),"Culminado",IF(AC36="-","Falta informacion",IF(AND(AB36-TODAY()>=0,AB36-TODAY()<=90),"Vigente_por vencer",IF(AND(AH36<>"SI",AB36<TODAY()),"Culminado",IF(AND(AH36="SI",AB36<TODAY(),OR(AK36="Sin Registro",AL36="Sin Registro")),"Vencido",IF(AND(AH36="SI",AB36<TODAY(),AK36>AA36,AL36>AB36),"Renovado","Vigente")))))),"En tramite"))))),"-") -> Desistido | AA36: - | AB36: - | AC36: =IFERROR(IF(OR(AA36="-",AA36="",AB36="-",AB36=""),"-",CONCATENATE('Seguimiento OIT'!AB36-'Seguimiento OIT'!AA36+1," dias")),"-") -> - | AD36: =IFERROR(IF(Z36="Vencido",(TODAY()-AB36)+1,"-"),"-") -> - | AE36: Con fecha 22-04-26, el área usuaria (Redes) desistió de requerimiento | AF36: - | AG36: - | AH36: NO | AI36: =IFERROR(IF(AH36="SI",VLOOKUP(A36,$C$4:$AL$151,15,FALSE),"-"),"Sin tramite") -> - | AJ36: =IFERROR(IF(AH36="SI",VLOOKUP(A36,$C$4:$AL$151,7,FALSE),"-"),"Sin HR") -> - | AK36: =IF(AH36="SI",IFERROR(IF(VLOOKUP(A36,$C$4:$AL$151,25,FALSE)="","Sin registro",VLOOKUP(A36,$C$4:$AL$151,25,FALSE)),"Sin registro"),"-") -> - | AL36: =IF(AH36="SI",IFERROR(IF(VLOOKUP(A36,$C$4:$AL$151,26,FALSE)="","Sin registro",VLOOKUP(A36,$C$4:$AL$151,26,FALSE)),"Sin registro"),"-") -> -
A37: REQ-2026-0034 | B37: =IF(OR(Q37="Desistido",Q37="No corresponde Atención OGTI",Q37="Para reformulación",Q37="Paralizado",Q37="-",Z37="Renovado",AND(AH37="NO",Z37="Culminado")),"NO","SI") -> NO | C37: - | D37: NO | E37: Contratación Directa | F37: Nuevo requerimiento | G37: Bienes | H37: Adquisición de televisores para la sala de asesores del despacho del MEF | I37: 092506-2026 | J37: Televisores (02 unidades) | K37: Soporte Tecnico | L37: Napoleon Alva Vasquez | M37: Ronald Yrupailla Diaz | N37: Despacho Ministerial | O37: - | P37: 46136 | Q37: Desistido | R37: OIT-Jefatura | S37: 46142 | T37: =IFERROR(IF(OR(Q37="Ejecutado",Q37="No corresponde atención OGTI",Q37="Desistido",Q37="-",Q37="Para reformulación"),"-",IF(OR(S37="-",S37=""),"Falta fecha_estado",NETWORKDAYS(S37,TODAY(),{"02/04/2026";"03/04/2026";"30/06/2026"}))),"-") -> - | U37: - | V37: - | W37: - | X37: - | Y37: - | Z37: =IFERROR(IF(Q37="-","-",IF(Q37="Proceso de implementación/Activación/Entrega","Proceso de implementación/Activación/Entrega",IF(OR(Q37="Desistido",Q37="No corresponde atención OGTI",Q37="Para reformulación"),Q37,IF(AND(Q37="Ejecutado",AA37="No aplica",AB37="No Aplica"),"Culminado",IF(Q37="Ejecutado",IF(AND(AC37="-",G37="Bienes"),"Culminado",IF(AC37="-","Falta informacion",IF(AND(AB37-TODAY()>=0,AB37-TODAY()<=90),"Vigente_por vencer",IF(AND(AH37<>"SI",AB37<TODAY()),"Culminado",IF(AND(AH37="SI",AB37<TODAY(),OR(AK37="Sin Registro",AL37="Sin Registro")),"Vencido",IF(AND(AH37="SI",AB37<TODAY(),AK37>AA37,AL37>AB37),"Renovado","Vigente")))))),"En tramite"))))),"-") -> Desistido | AA37: - | AB37: - | AC37: =IFERROR(IF(OR(AA37="-",AA37="",AB37="-",AB37=""),"-",CONCATENATE('Seguimiento OIT'!AB37-'Seguimiento OIT'!AA37+1," dias")),"-") -> - | AD37: =IFERROR(IF(Z37="Vencido",(TODAY()-AB37)+1,"-"),"-") -> - | AE37: Con fecha 30-04-26, el área usuaria desistió de requerimiento | AF37: - | AG37: https://mefgobpe1.sharepoint.com/:f:/t/DireccindelaOficinadeInfraestructuraTecnolgica/IgD0BRP6axX4RZWju57kPBYLAfg195MIEez6fBiAsKEFHQ0?e=9E2aRp | AH37: NO | AI37: =IFERROR(IF(AH37="SI",VLOOKUP(A37,$C$4:$AL$151,15,FALSE),"-"),"Sin tramite") -> - | AJ37: =IFERROR(IF(AH37="SI",VLOOKUP(A37,$C$4:$AL$151,7,FALSE),"-"),"Sin HR") -> - | AK37: =IF(AH37="SI",IFERROR(IF(VLOOKUP(A37,$C$4:$AL$151,25,FALSE)="","Sin registro",VLOOKUP(A37,$C$4:$AL$151,25,FALSE)),"Sin registro"),"-") -> - | AL37: =IF(AH37="SI",IFERROR(IF(VLOOKUP(A37,$C$4:$AL$151,26,FALSE)="","Sin registro",VLOOKUP(A37,$C$4:$AL$151,26,FALSE)),"Sin registro"),"-") -> -
A38: REQ-2026-0035 | B38: =IF(OR(Q38="Desistido",Q38="No corresponde Atención OGTI",Q38="Para reformulación",Q38="Paralizado",Q38="-",Z38="Renovado",AND(AH38="NO",Z38="Culminado")),"NO","SI") -> SI | C38: - | D38: NO | E38: Contratación Directa | F38: Nuevo requerimiento | G38: Servicios | H38: Servicio de implementación, soporte y mantenimiento de software de gestión de recursos humanos | I38: *097913-2026 (Requerimiento) **083567-2026 (Apoyo presupuestal) | J38: Sistema de Gestión de Recursos Humanos | K38: Jefatura OIT | L38: José Romucho Sotelo | M38: José Romucho Sotelo | N38: Oficina de Sistemas de Información | O38: 25500 | P38: 46153 | Q38: Proceso de implementación/Activación/Entrega | R38: OIT-Jefatura | S38: 46182 | T38: =IFERROR(IF(OR(Q38="Ejecutado",Q38="No corresponde atención OGTI",Q38="Desistido",Q38="-",Q38="Para reformulación"),"-",IF(OR(S38="-",S38=""),"Falta fecha_estado",NETWORKDAYS(S38,TODAY(),{"02/04/2026";"03/04/2026";"30/06/2026"}))),"-") -> 38 | U38: Contrato | V38: 012-2026-EF/43.03/CM | W38: 46181 | X38: Informatica y proyectos E.I.R.L | Y38: José Romucho Sotelo | Z38: =IFERROR(IF(Q38="-","-",IF(Q38="Proceso de implementación/Activación/Entrega","Proceso de implementación/Activación/Entrega",IF(OR(Q38="Desistido",Q38="No corresponde atención OGTI",Q38="Para reformulación"),Q38,IF(AND(Q38="Ejecutado",AA38="No aplica",AB38="No Aplica"),"Culminado",IF(Q38="Ejecutado",IF(AND(AC38="-",G38="Bienes"),"Culminado",IF(AC38="-","Falta informacion",IF(AND(AB38-TODAY()>=0,AB38-TODAY()<=90),"Vigente_por vencer",IF(AND(AH38<>"SI",AB38<TODAY()),"Culminado",IF(AND(AH38="SI",AB38<TODAY(),OR(AK38="Sin Registro",AL38="Sin Registro")),"Vencido",IF(AND(AH38="SI",AB38<TODAY(),AK38>AA38,AL38>AB38),"Renovado","Vigente")))))),"En tramite"))))),"-") -> Proceso de implementación/Activación/Entrega | AA38: - | AB38: - | AC38: =IFERROR(IF(OR(AA38="-",AA38="",AB38="-",AB38=""),"-",CONCATENATE('Seguimiento OIT'!AB38-'Seguimiento OIT'!AA38+1," dias")),"-") -> - | AD38: =IFERROR(IF(Z38="Vencido",(TODAY()-AB38)+1,"-"),"-") -> - | AE38: - | AF38: *Plazo máximo de implementación 07/08/2026 | AG38: https://mefgobpe1.sharepoint.com/:f:/t/DireccindelaOficinadeInfraestructuraTecnolgica/IgBnvm7wfHfYTa7oXSw1DWjXAUKkhZUZyDEbdETPv5R5BMk?e=8vTbdb | AH38: NO | AI38: =IFERROR(IF(AH38="SI",VLOOKUP(A38,$C$4:$AL$151,15,FALSE),"-"),"Sin tramite") -> - | AJ38: =IFERROR(IF(AH38="SI",VLOOKUP(A38,$C$4:$AL$151,7,FALSE),"-"),"Sin HR") -> - | AK38: =IF(AH38="SI",IFERROR(IF(VLOOKUP(A38,$C$4:$AL$151,25,FALSE)="","Sin registro",VLOOKUP(A38,$C$4:$AL$151,25,FALSE)),"Sin registro"),"-") -> - | AL38: =IF(AH38="SI",IFERROR(IF(VLOOKUP(A38,$C$4:$AL$151,26,FALSE)="","Sin registro",VLOOKUP(A38,$C$4:$AL$151,26,FALSE)),"Sin registro"),"-") -> -
A39: REQ-2026-0036 | B39: =IF(OR(Q39="Desistido",Q39="No corresponde Atención OGTI",Q39="Para reformulación",Q39="Paralizado",Q39="-",Z39="Renovado",AND(AH39="NO",Z39="Culminado")),"NO","SI") -> SI | C39: - | D39: NO | E39: Contratación Directa | F39: Nuevo requerimiento | G39: Bienes | H39: Adquisición de equipamiento y licencia de software para la optimización de la plataforma de gestión de colas de la Oficina General de Servicios al Usuario (OGSU) | I39: *091410-2026 (Requerimiento) **079134-2026 (Apoyo presupuestal) ***075012-2026 (Req Inicial) | J39: *Dispensador de tickets *Licencia de software de administración de colas | K39: Soporte Tecnico | L39: Napoleon Alva Vasquez | M39: Ronald Yrupailla Diaz | N39: Oficina General de Servicios al Usuario | O39: 21830 | P39: 46139 | Q39: Proceso de implementación/Activación/Entrega | R39: OIT-Soporte Tecnico | S39: 46175 | T39: =IFERROR(IF(OR(Q39="Ejecutado",Q39="No corresponde atención OGTI",Q39="Desistido",Q39="-",Q39="Para reformulación"),"-",IF(OR(S39="-",S39=""),"Falta fecha_estado",NETWORKDAYS(S39,TODAY(),{"02/04/2026";"03/04/2026";"30/06/2026"}))),"-") -> 43 | U39: Orden de Compra | V39: 0000176-2026 | W39: 46174 | X39: BISSNETCORP S.A.C. | Y39: Napoleon Alva Vasquez | Z39: =IFERROR(IF(Q39="-","-",IF(Q39="Proceso de implementación/Activación/Entrega","Proceso de implementación/Activación/Entrega",IF(OR(Q39="Desistido",Q39="No corresponde atención OGTI",Q39="Para reformulación"),Q39,IF(AND(Q39="Ejecutado",AA39="No aplica",AB39="No Aplica"),"Culminado",IF(Q39="Ejecutado",IF(AND(AC39="-",G39="Bienes"),"Culminado",IF(AC39="-","Falta informacion",IF(AND(AB39-TODAY()>=0,AB39-TODAY()<=90),"Vigente_por vencer",IF(AND(AH39<>"SI",AB39<TODAY()),"Culminado",IF(AND(AH39="SI",AB39<TODAY(),OR(AK39="Sin Registro",AL39="Sin Registro")),"Vencido",IF(AND(AH39="SI",AB39<TODAY(),AK39>AA39,AL39>AB39),"Renovado","Vigente")))))),"En tramite"))))),"-") -> Proceso de implementación/Activación/Entrega | AA39: - | AB39: - | AC39: =IFERROR(IF(OR(AA39="-",AA39="",AB39="-",AB39=""),"-",CONCATENATE('Seguimiento OIT'!AB39-'Seguimiento OIT'!AA39+1," dias")),"-") -> - | AD39: =IFERROR(IF(Z39="Vencido",(TODAY()-AB39)+1,"-"),"-") -> - | AE39: - | AF39: *Plazo máximo de implementación 15/08/2026 *Conformidad 127910-2026 (Observado) *Nueva conformidad 154990-2026 *Solicitud de Ampliacion 157935-2026 | AG39: https://mefgobpe1.sharepoint.com/:f:/t/DireccindelaOficinadeInfraestructuraTecnolgica/IgDLwoyF5lpGQ5jG9Cn-O4x1Ae70d7frLSLOU3QZ6DDmJjw?e=MkM4RD | AH39: NO | AI39: =IFERROR(IF(AH39="SI",VLOOKUP(A39,$C$4:$AL$151,15,FALSE),"-"),"Sin tramite") -> - | AJ39: =IFERROR(IF(AH39="SI",VLOOKUP(A39,$C$4:$AL$151,7,FALSE),"-"),"Sin HR") -> - | AK39: =IF(AH39="SI",IFERROR(IF(VLOOKUP(A39,$C$4:$AL$151,25,FALSE)="","Sin registro",VLOOKUP(A39,$C$4:$AL$151,25,FALSE)),"Sin registro"),"-") -> - | AL39: =IF(AH39="SI",IFERROR(IF(VLOOKUP(A39,$C$4:$AL$151,26,FALSE)="","Sin registro",VLOOKUP(A39,$C$4:$AL$151,26,FALSE)),"Sin registro"),"-") -> -
A40: REQ-2026-0037 | B40: =IF(OR(Q40="Desistido",Q40="No corresponde Atención OGTI",Q40="Para reformulación",Q40="Paralizado",Q40="-",Z40="Renovado",AND(AH40="NO",Z40="Culminado")),"NO","SI") -> SI | C40: - | D40: NO | E40: Contratación Directa | F40: Nuevo requerimiento | G40: Bienes | H40: Adquisición de equipamiento y licencia de software para la optimización de la plataforma de gestión de colas del Tribunal Fiscal | I40: *091410-2026 (Requerimiento) **079134-2026 (Apoyo presupuestal) ***075012-2026 (Req Inicial) | J40: *Dispensador de tickets *Licencia de software de administración de colas | K40: Soporte Tecnico | L40: Napoleon Alva Vasquez | M40: Ronald Yrupailla Diaz | N40: Tribunal Fiscal | O40: 21830 | P40: 46139 | Q40: Proceso de implementación/Activación/Entrega | R40: OIT-Soporte Tecnico | S40: 46175 | T40: =IFERROR(IF(OR(Q40="Ejecutado",Q40="No corresponde atención OGTI",Q40="Desistido",Q40="-",Q40="Para reformulación"),"-",IF(OR(S40="-",S40=""),"Falta fecha_estado",NETWORKDAYS(S40,TODAY(),{"02/04/2026";"03/04/2026";"30/06/2026"}))),"-") -> 43 | U40: Orden de Compra | V40: 0000176-2026 | W40: 46174 | X40: BISSNETCORP S.A.C. | Y40: Napoleon Alva Vasquez | Z40: =IFERROR(IF(Q40="-","-",IF(Q40="Proceso de implementación/Activación/Entrega","Proceso de implementación/Activación/Entrega",IF(OR(Q40="Desistido",Q40="No corresponde atención OGTI",Q40="Para reformulación"),Q40,IF(AND(Q40="Ejecutado",AA40="No aplica",AB40="No Aplica"),"Culminado",IF(Q40="Ejecutado",IF(AND(AC40="-",G40="Bienes"),"Culminado",IF(AC40="-","Falta informacion",IF(AND(AB40-TODAY()>=0,AB40-TODAY()<=90),"Vigente_por vencer",IF(AND(AH40<>"SI",AB40<TODAY()),"Culminado",IF(AND(AH40="SI",AB40<TODAY(),OR(AK40="Sin Registro",AL40="Sin Registro")),"Vencido",IF(AND(AH40="SI",AB40<TODAY(),AK40>AA40,AL40>AB40),"Renovado","Vigente")))))),"En tramite"))))),"-") -> Proceso de implementación/Activación/Entrega | AA40: - | AB40: - | AC40: =IFERROR(IF(OR(AA40="-",AA40="",AB40="-",AB40=""),"-",CONCATENATE('Seguimiento OIT'!AB40-'Seguimiento OIT'!AA40+1," dias")),"-") -> - | AD40: =IFERROR(IF(Z40="Vencido",(TODAY()-AB40)+1,"-"),"-") -> - | AE40: - | AF40: *Plazo máximo de implementación 15/08/2026 *Conformidad 127910-2026 (Observado) *Nueva conformidad 154990-2026 *Solicitud de Ampliacion 157935-2026 | AG40: https://mefgobpe1.sharepoint.com/:f:/t/DireccindelaOficinadeInfraestructuraTecnolgica/IgDLwoyF5lpGQ5jG9Cn-O4x1Ae70d7frLSLOU3QZ6DDmJjw?e=MkM4RD | AH40: NO | AI40: =IFERROR(IF(AH40="SI",VLOOKUP(A40,$C$4:$AL$151,15,FALSE),"-"),"Sin tramite") -> - | AJ40: =IFERROR(IF(AH40="SI",VLOOKUP(A40,$C$4:$AL$151,7,FALSE),"-"),"Sin HR") -> - | AK40: =IF(AH40="SI",IFERROR(IF(VLOOKUP(A40,$C$4:$AL$151,25,FALSE)="","Sin registro",VLOOKUP(A40,$C$4:$AL$151,25,FALSE)),"Sin registro"),"-") -> - | AL40: =IF(AH40="SI",IFERROR(IF(VLOOKUP(A40,$C$4:$AL$151,26,FALSE)="","Sin registro",VLOOKUP(A40,$C$4:$AL$151,26,FALSE)),"Sin registro"),"-") -> -
A41: REQ-2026-0048 | B41: =IF(OR(Q41="Desistido",Q41="No corresponde Atención OGTI",Q41="Para reformulación",Q41="Paralizado",Q41="-",Z41="Renovado",AND(AH41="NO",Z41="Culminado")),"NO","SI") -> SI | C41: - | D41: NO | E41: Procesos de Contratación | F41: Renovación | G41: Servicios | H41: Servicio De Continuidad Operativa Para Los Equipos De Red Del Ministerio De Economía Y Finanzas | I41: - | J41: Mantenimiento preventivo, soporte especializado y mantenimiento correctivo | K41: Redes y Comunicaciones | L41: Elliot Hans Lindo Claudet | M41: Elliot Hans Lindo Claudet | N41: Oficina de Infraestructura Tecnológica | O41: 474624 | P41: - | Q41: Ejecutado | R41: - | S41: - | T41: =IFERROR(IF(OR(Q41="Ejecutado",Q41="No corresponde atención OGTI",Q41="Desistido",Q41="-",Q41="Para reformulación"),"-",IF(OR(S41="-",S41=""),"Falta fecha_estado",NETWORKDAYS(S41,TODAY(),{"02/04/2026";"03/04/2026";"30/06/2026"}))),"-") -> - | U41: Contrato | V41: 005-2026-EF/43.03 | W41: 46050 | X41: SMART GLOBAL SOCIEDAD ANÓNIMA CERRADA | Y41: Elliot Hans Lindo Claudet | Z41: =IFERROR(IF(Q41="-","-",IF(Q41="Proceso de implementación/Activación/Entrega","Proceso de implementación/Activación/Entrega",IF(OR(Q41="Desistido",Q41="No corresponde atención OGTI",Q41="Para reformulación"),Q41,IF(AND(Q41="Ejecutado",AA41="No aplica",AB41="No Aplica"),"Culminado",IF(Q41="Ejecutado",IF(AND(AC41="-",G41="Bienes"),"Culminado",IF(AC41="-","Falta informacion",IF(AND(AB41-TODAY()>=0,AB41-TODAY()<=90),"Vigente_por vencer",IF(AND(AH41<>"SI",AB41<TODAY()),"Culminado",IF(AND(AH41="SI",AB41<TODAY(),OR(AK41="Sin Registro",AL41="Sin Registro")),"Vencido",IF(AND(AH41="SI",AB41<TODAY(),AK41>AA41,AL41>AB41),"Renovado","Vigente")))))),"En tramite"))))),"-") -> Vigente | AA41: 46052 | AB41: 46416 | AC41: =IFERROR(IF(OR(AA41="-",AA41="",AB41="-",AB41=""),"-",CONCATENATE('Seguimiento OIT'!AB41-'Seguimiento OIT'!AA41+1," dias")),"-") -> 365 dias | AD41: =IFERROR(IF(Z41="Vencido",(TODAY()-AB41)+1,"-"),"-") -> - | AE41: - | AF41: Se envíara el requerimiento para su continuidad en Julio 2026 | AG41: https://mefgobpe1.sharepoint.com/:f:/t/DireccindelaOficinadeInfraestructuraTecnolgica/IgBfTpEMBO_EQ6wESvhiY_MLAZrBPKth1991sMRDZRtoipI?e=YqP7ZP | AH41: NO | AI41: =IFERROR(IF(AH41="SI",VLOOKUP(A41,$C$4:$AL$151,15,FALSE),"-"),"Sin tramite") -> - | AJ41: =IFERROR(IF(AH41="SI",VLOOKUP(A41,$C$4:$AL$151,7,FALSE),"-"),"Sin HR") -> - | AK41: =IF(AH41="SI",IFERROR(IF(VLOOKUP(A41,$C$4:$AL$151,25,FALSE)="","Sin registro",VLOOKUP(A41,$C$4:$AL$151,25,FALSE)),"Sin registro"),"-") -> - | AL41: =IF(AH41="SI",IFERROR(IF(VLOOKUP(A41,$C$4:$AL$151,26,FALSE)="","Sin registro",VLOOKUP(A41,$C$4:$AL$151,26,FALSE)),"Sin registro"),"-") -> -
A42: REQ-2026-0038 | B42: =IF(OR(Q42="Desistido",Q42="No corresponde Atención OGTI",Q42="Para reformulación",Q42="Paralizado",Q42="-",Z42="Renovado",AND(AH42="NO",Z42="Culminado")),"NO","SI") -> SI | C42: - | D42: NO | E42: Contratación Directa | F42: Nuevo requerimiento | G42: Servicios | H42: Servicio de internet inalámbrico portátil (Módem) para el Tribunal Fiscal | I42: I-230553-2025 | J42: Internet Inalámbrico Portátil TF | K42: Redes y Comunicaciones | L42: Elliot Hans Lindo Claudet | M42: Elliot Hans Lindo Claudet | N42: Tribunal Fiscal | O42: 3176 | Q42: Ejecutado | R42: - | S42: - | T42: =IFERROR(IF(OR(Q42="Ejecutado",Q42="No corresponde atención OGTI",Q42="Desistido",Q42="-",Q42="Para reformulación"),"-",IF(OR(S42="-",S42=""),"Falta fecha_estado",NETWORKDAYS(S42,TODAY(),{"02/04/2026";"03/04/2026";"30/06/2026"}))),"-") -> - | U42: - | W42: 46009 | X42: ENTEL PERU S.A. | Y42: Elliot Hans Lindo Claudet | Z42: =IFERROR(IF(Q42="-","-",IF(Q42="Proceso de implementación/Activación/Entrega","Proceso de implementación/Activación/Entrega",IF(OR(Q42="Desistido",Q42="No corresponde atención OGTI",Q42="Para reformulación"),Q42,IF(AND(Q42="Ejecutado",AA42="No aplica",AB42="No Aplica"),"Culminado",IF(Q42="Ejecutado",IF(AND(AC42="-",G42="Bienes"),"Culminado",IF(AC42="-","Falta informacion",IF(AND(AB42-TODAY()>=0,AB42-TODAY()<=90),"Vigente_por vencer",IF(AND(AH42<>"SI",AB42<TODAY()),"Culminado",IF(AND(AH42="SI",AB42<TODAY(),OR(AK42="Sin Registro",AL42="Sin Registro")),"Vencido",IF(AND(AH42="SI",AB42<TODAY(),AK42>AA42,AL42>AB42),"Renovado","Vigente")))))),"En tramite"))))),"-") -> Vigente | AA42: 46037 | AB42: 46401 | AC42: =IFERROR(IF(OR(AA42="-",AA42="",AB42="-",AB42=""),"-",CONCATENATE('Seguimiento OIT'!AB42-'Seguimiento OIT'!AA42+1," dias")),"-") -> 365 dias | AD42: =IFERROR(IF(Z42="Vencido",(TODAY()-AB42)+1,"-"),"-") -> - | AE42: - | AF42: Consultar. Hr indica previsión presupuestal | AH42: NO | AI42: =IFERROR(IF(AH42="SI",VLOOKUP(A42,$C$4:$AL$151,15,FALSE),"-"),"Sin tramite") -> - | AJ42: =IFERROR(IF(AH42="SI",VLOOKUP(A42,$C$4:$AL$151,7,FALSE),"-"),"Sin HR") -> - | AK42: =IF(AH42="SI",IFERROR(IF(VLOOKUP(A42,$C$4:$AL$151,25,FALSE)="","Sin registro",VLOOKUP(A42,$C$4:$AL$151,25,FALSE)),"Sin registro"),"-") -> - | AL42: =IF(AH42="SI",IFERROR(IF(VLOOKUP(A42,$C$4:$AL$151,26,FALSE)="","Sin registro",VLOOKUP(A42,$C$4:$AL$151,26,FALSE)),"Sin registro"),"-") -> -
A43: REQ-2026-0039 | B43: =IF(OR(Q43="Desistido",Q43="No corresponde Atención OGTI",Q43="Para reformulación",Q43="Paralizado",Q43="-",Z43="Renovado",AND(AH43="NO",Z43="Culminado")),"NO","SI") -> SI | C43: - | D43: NO | E43: Contratación Directa | F43: Nuevo requerimiento | G43: Servicios | H43: Servicio de escaneo bajo demanda para la Procuraduría Pública y la Plataforma de Atención al usuario del Ministerio de Economía y Finanzas. | I43: 248761-2025 | J43: Alquiler de escáneres para procuraduría | K43: Redes y Comunicaciones | L43: Elliot Hans Lindo Claudet | M43: Elliot Hans Lindo Claudet | N43: Oficina de Infraestructura Tecnológica | O43: 42700 | Q43: Ejecutado | R43: - | S43: - | T43: =IFERROR(IF(OR(Q43="Ejecutado",Q43="No corresponde atención OGTI",Q43="Desistido",Q43="-",Q43="Para reformulación"),"-",IF(OR(S43="-",S43=""),"Falta fecha_estado",NETWORKDAYS(S43,TODAY(),{"02/04/2026";"03/04/2026";"30/06/2026"}))),"-") -> - | U43: Contrato | W43: 46015 | X43: GRUPO VENTURA PERU S.A.C. | Y43: Elliot Hans Lindo Claudet | Z43: =IFERROR(IF(Q43="-","-",IF(Q43="Proceso de implementación/Activación/Entrega","Proceso de implementación/Activación/Entrega",IF(OR(Q43="Desistido",Q43="No corresponde atención OGTI",Q43="Para reformulación"),Q43,IF(AND(Q43="Ejecutado",AA43="No aplica",AB43="No Aplica"),"Culminado",IF(Q43="Ejecutado",IF(AND(AC43="-",G43="Bienes"),"Culminado",IF(AC43="-","Falta informacion",IF(AND(AB43-TODAY()>=0,AB43-TODAY()<=90),"Vigente_por vencer",IF(AND(AH43<>"SI",AB43<TODAY()),"Culminado",IF(AND(AH43="SI",AB43<TODAY(),OR(AK43="Sin Registro",AL43="Sin Registro")),"Vencido",IF(AND(AH43="SI",AB43<TODAY(),AK43>AA43,AL43>AB43),"Renovado","Vigente")))))),"En tramite"))))),"-") -> Vigente | AA43: 46019 | AB43: 46382 | AC43: =IFERROR(IF(OR(AA43="-",AA43="",AB43="-",AB43=""),"-",CONCATENATE('Seguimiento OIT'!AB43-'Seguimiento OIT'!AA43+1," dias")),"-") -> 364 dias | AD43: =IFERROR(IF(Z43="Vencido",(TODAY()-AB43)+1,"-"),"-") -> - | AE43: - | AF43: Se enviara requerimiento para continuidad Oct 2026 | AH43: NO | AI43: =IFERROR(IF(AH43="SI",VLOOKUP(A43,$C$4:$AL$151,15,FALSE),"-"),"Sin tramite") -> - | AJ43: =IFERROR(IF(AH43="SI",VLOOKUP(A43,$C$4:$AL$151,7,FALSE),"-"),"Sin HR") -> - | AK43: =IF(AH43="SI",IFERROR(IF(VLOOKUP(A43,$C$4:$AL$151,25,FALSE)="","Sin registro",VLOOKUP(A43,$C$4:$AL$151,25,FALSE)),"Sin registro"),"-") -> - | AL43: =IF(AH43="SI",IFERROR(IF(VLOOKUP(A43,$C$4:$AL$151,26,FALSE)="","Sin registro",VLOOKUP(A43,$C$4:$AL$151,26,FALSE)),"Sin registro"),"-") -> -
A44: REQ-2026-0040 | B44: =IF(OR(Q44="Desistido",Q44="No corresponde Atención OGTI",Q44="Para reformulación",Q44="Paralizado",Q44="-",Z44="Renovado",AND(AH44="NO",Z44="Culminado")),"NO","SI") -> NO | C44: - | D44: NO | E44: Contratación Directa | F44: Nuevo requerimiento | G44: Servicios | H44: Servicio de soporte técnico a la infraestructura tecnológica para la atención de alertas detectadas en el equipamiento de almacenamiento de la marca IBM | I44: 044917-2026 | J44: Mantenimiento IBM FlashSystem 9200-CPD Principal | K44: Computo | L44: Rolly Villegas Delgado | M44: Anthony Céspedes Molina | N44: Oficina de Infraestructura Tecnológica | O44: 40000 | P44: 46085 | Q44: Ejecutado | R44: - | S44: - | T44: =IFERROR(IF(OR(Q44="Ejecutado",Q44="No corresponde atención OGTI",Q44="Desistido",Q44="-",Q44="Para reformulación"),"-",IF(OR(S44="-",S44=""),"Falta fecha_estado",NETWORKDAYS(S44,TODAY(),{"02/04/2026";"03/04/2026";"30/06/2026"}))),"-") -> - | U44: Orden de Servicio | V44: 0002412-2026 | W44: 46150 | X44: IT STORAGE EIRL | Y44: Anthony Céspedes Molina | Z44: =IFERROR(IF(Q44="-","-",IF(Q44="Proceso de implementación/Activación/Entrega","Proceso de implementación/Activación/Entrega",IF(OR(Q44="Desistido",Q44="No corresponde atención OGTI",Q44="Para reformulación"),Q44,IF(AND(Q44="Ejecutado",AA44="No aplica",AB44="No Aplica"),"Culminado",IF(Q44="Ejecutado",IF(AND(AC44="-",G44="Bienes"),"Culminado",IF(AC44="-","Falta informacion",IF(AND(AB44-TODAY()>=0,AB44-TODAY()<=90),"Vigente_por vencer",IF(AND(AH44<>"SI",AB44<TODAY()),"Culminado",IF(AND(AH44="SI",AB44<TODAY(),OR(AK44="Sin Registro",AL44="Sin Registro")),"Vencido",IF(AND(AH44="SI",AB44<TODAY(),AK44>AA44,AL44>AB44),"Renovado","Vigente")))))),"En tramite"))))),"-") -> Culminado | AA44: No aplica | AB44: No Aplica | AC44: =IFERROR(IF(OR(AA44="-",AA44="",AB44="-",AB44=""),"-",CONCATENATE('Seguimiento OIT'!AB44-'Seguimiento OIT'!AA44+1," dias")),"-") -> - | AD44: =IFERROR(IF(Z44="Vencido",(TODAY()-AB44)+1,"-"),"-") -> - | AE44: - | AF44: *Plazo máximo de ejecución 07/07/2026 *HR de conformidad 139989-2026 | AG44: https://mefgobpe1.sharepoint.com/:f:/t/DireccindelaOficinadeInfraestructuraTecnolgica/IgCnzxNk-eJ5SYfMig5joajHATNiVaCYfk9WMvuLvUi8HX8?e=PZJj3r | AH44: NO | AI44: =IFERROR(IF(AH44="SI",VLOOKUP(A44,$C$4:$AL$151,15,FALSE),"-"),"Sin tramite") -> - | AJ44: =IFERROR(IF(AH44="SI",VLOOKUP(A44,$C$4:$AL$151,7,FALSE),"-"),"Sin HR") -> - | AK44: =IF(AH44="SI",IFERROR(IF(VLOOKUP(A44,$C$4:$AL$151,25,FALSE)="","Sin registro",VLOOKUP(A44,$C$4:$AL$151,25,FALSE)),"Sin registro"),"-") -> - | AL44: =IF(AH44="SI",IFERROR(IF(VLOOKUP(A44,$C$4:$AL$151,26,FALSE)="","Sin registro",VLOOKUP(A44,$C$4:$AL$151,26,FALSE)),"Sin registro"),"-") -> -
A45: REQ-2026-0041 | B45: =IF(OR(Q45="Desistido",Q45="No corresponde Atención OGTI",Q45="Para reformulación",Q45="Paralizado",Q45="-",Z45="Renovado",AND(AH45="NO",Z45="Culminado")),"NO","SI") -> NO | C45: - | D45: NO | E45: Contratación Directa | F45: Nuevo requerimiento | G45: Servicios | H45: Servicio de provisión y gestión de equipamiento para infraestructura de networking | I45: 070521-2026 | J45: Provisión de equipamiento networking - CPD Contingencia | K45: Redes y Comunicaciones | L45: Elliot Hans Lindo Claudet | M45: Elliot Hans Lindo Claudet | N45: Oficina de Infraestructura Tecnológica | O45: 43966.8 | P45: 46107 | Q45: Ejecutado | R45: - | S45: - | T45: =IFERROR(IF(OR(Q45="Ejecutado",Q45="No corresponde atención OGTI",Q45="Desistido",Q45="-",Q45="Para reformulación"),"-",IF(OR(S45="-",S45=""),"Falta fecha_estado",NETWORKDAYS(S45,TODAY(),{"02/04/2026";"03/04/2026";"30/06/2026"}))),"-") -> - | U45: Orden de Servicio | V45: 0001981-2026 | W45: 46127 | X45: GTD PERÚ S.A | Y45: Elliot Hans Lindo Claudet | Z45: =IFERROR(IF(Q45="-","-",IF(Q45="Proceso de implementación/Activación/Entrega","Proceso de implementación/Activación/Entrega",IF(OR(Q45="Desistido",Q45="No corresponde atención OGTI",Q45="Para reformulación"),Q45,IF(AND(Q45="Ejecutado",AA45="No aplica",AB45="No Aplica"),"Culminado",IF(Q45="Ejecutado",IF(AND(AC45="-",G45="Bienes"),"Culminado",IF(AC45="-","Falta informacion",IF(AND(AB45-TODAY()>=0,AB45-TODAY()<=90),"Vigente_por vencer",IF(AND(AH45<>"SI",AB45<TODAY()),"Culminado",IF(AND(AH45="SI",AB45<TODAY(),OR(AK45="Sin Registro",AL45="Sin Registro")),"Vencido",IF(AND(AH45="SI",AB45<TODAY(),AK45>AA45,AL45>AB45),"Renovado","Vigente")))))),"En tramite"))))),"-") -> Culminado | AA45: 46133 | AB45: 46222 | AC45: =IFERROR(IF(OR(AA45="-",AA45="",AB45="-",AB45=""),"-",CONCATENATE('Seguimiento OIT'!AB45-'Seguimiento OIT'!AA45+1," dias")),"-") -> 90 dias | AD45: =IFERROR(IF(Z45="Vencido",(TODAY()-AB45)+1,"-"),"-") -> - | AE45: - | AF45: *Entregable 01- 114723-2026 | AG45: https://mefgobpe1.sharepoint.com/:f:/t/DireccindelaOficinadeInfraestructuraTecnolgica/IgAiRw1f-SK6SL9hZ__gV0JPAZMJCyiR2Op7RyTWw4edO2c?e=Ob19Gs | AH45: NO | AI45: =IFERROR(IF(AH45="SI",VLOOKUP(A45,$C$4:$AL$151,15,FALSE),"-"),"Sin tramite") -> - | AJ45: =IFERROR(IF(AH45="SI",VLOOKUP(A45,$C$4:$AL$151,7,FALSE),"-"),"Sin HR") -> - | AK45: =IF(AH45="SI",IFERROR(IF(VLOOKUP(A45,$C$4:$AL$151,25,FALSE)="","Sin registro",VLOOKUP(A45,$C$4:$AL$151,25,FALSE)),"Sin registro"),"-") -> - | AL45: =IF(AH45="SI",IFERROR(IF(VLOOKUP(A45,$C$4:$AL$151,26,FALSE)="","Sin registro",VLOOKUP(A45,$C$4:$AL$151,26,FALSE)),"Sin registro"),"-") -> -
A46: REQ-2026-0042 | B46: =IF(OR(Q46="Desistido",Q46="No corresponde Atención OGTI",Q46="Para reformulación",Q46="Paralizado",Q46="-",Z46="Renovado",AND(AH46="NO",Z46="Culminado")),"NO","SI") -> SI | C46: - | D46: NO | E46: Contratación Directa | F46: Nuevo requerimiento | G46: Bienes | H46: Adquisición de dispositivos USB para la DGPMACDF | I46: *027113-2026 (Requerimiento) **087667-2026 (Ref compra Audif) | J46: Dispositivo USB (20 unidades) | K46: Soporte Tecnico | L46: Napoleon Alva Vasquez | M46: Ronald Yrupailla Diaz | N46: Dirección General de Política Macroeconómica y Descentralización Fiscal | O46: Pendiente | P46: 46160 | Q46: Apoyo presupuestal | R46: Área Usuaria | S46: 46174 | T46: =IFERROR(IF(OR(Q46="Ejecutado",Q46="No corresponde atención OGTI",Q46="Desistido",Q46="-",Q46="Para reformulación"),"-",IF(OR(S46="-",S46=""),"Falta fecha_estado",NETWORKDAYS(S46,TODAY(),{"02/04/2026";"03/04/2026";"30/06/2026"}))),"-") -> 44 | U46: - | V46: - | W46: - | X46: - | Y46: - | Z46: =IFERROR(IF(Q46="-","-",IF(Q46="Proceso de implementación/Activación/Entrega","Proceso de implementación/Activación/Entrega",IF(OR(Q46="Desistido",Q46="No corresponde atención OGTI",Q46="Para reformulación"),Q46,IF(AND(Q46="Ejecutado",AA46="No aplica",AB46="No Aplica"),"Culminado",IF(Q46="Ejecutado",IF(AND(AC46="-",G46="Bienes"),"Culminado",IF(AC46="-","Falta informacion",IF(AND(AB46-TODAY()>=0,AB46-TODAY()<=90),"Vigente_por vencer",IF(AND(AH46<>"SI",AB46<TODAY()),"Culminado",IF(AND(AH46="SI",AB46<TODAY(),OR(AK46="Sin Registro",AL46="Sin Registro")),"Vencido",IF(AND(AH46="SI",AB46<TODAY(),AK46>AA46,AL46>AB46),"Renovado","Vigente")))))),"En tramite"))))),"-") -> En tramite | AA46: - | AB46: - | AC46: =IFERROR(IF(OR(AA46="-",AA46="",AB46="-",AB46=""),"-",CONCATENATE('Seguimiento OIT'!AB46-'Seguimiento OIT'!AA46+1," dias")),"-") -> - | AD46: =IFERROR(IF(Z46="Vencido",(TODAY()-AB46)+1,"-"),"-") -> - | AE46: *Con fecha 01-06-26, se remitió por correo modelos y precios referenciales. *Con INFORME N° 0834-2026-EF/44.02 se remitió información referencial | AF46: - | AG46: https://mefgobpe1.sharepoint.com/:f:/t/DireccindelaOficinadeInfraestructuraTecnolgica/IgCVNZbyk9aoSJ7piqo7XJl0AfIZwHvZejp26QI5X1Gr0Ik?e=dJuPrW | AH46: NO | AI46: =IFERROR(IF(AH46="SI",VLOOKUP(A46,$C$4:$AL$151,15,FALSE),"-"),"Sin tramite") -> - | AJ46: =IFERROR(IF(AH46="SI",VLOOKUP(A46,$C$4:$AL$151,7,FALSE),"-"),"Sin HR") -> - | AK46: =IF(AH46="SI",IFERROR(IF(VLOOKUP(A46,$C$4:$AL$151,25,FALSE)="","Sin registro",VLOOKUP(A46,$C$4:$AL$151,25,FALSE)),"Sin registro"),"-") -> - | AL46: =IF(AH46="SI",IFERROR(IF(VLOOKUP(A46,$C$4:$AL$151,26,FALSE)="","Sin registro",VLOOKUP(A46,$C$4:$AL$151,26,FALSE)),"Sin registro"),"-") -> -
A47: REQ-2026-0043 | B47: =IF(OR(Q47="Desistido",Q47="No corresponde Atención OGTI",Q47="Para reformulación",Q47="Paralizado",Q47="-",Z47="Renovado",AND(AH47="NO",Z47="Culminado")),"NO","SI") -> SI | C47: - | D47: NO | E47: Contratación Directa | F47: Nuevo requerimiento | G47: Bienes | H47: Adquisición de proyectores | I47: 077790-2026 | J47: Proyector Multimedia (02 unidades) | K47: Soporte Tecnico | L47: Napoleon Alva Vasquez | M47: Ronald Yrupailla Diaz | N47: Dirección General de Política Macroeconómica y Descentralización Fiscal | O47: Pendiente | P47: 46157 | Q47: Apoyo presupuestal | R47: Área Usuaria | S47: 46169 | T47: =IFERROR(IF(OR(Q47="Ejecutado",Q47="No corresponde atención OGTI",Q47="Desistido",Q47="-",Q47="Para reformulación"),"-",IF(OR(S47="-",S47=""),"Falta fecha_estado",NETWORKDAYS(S47,TODAY(),{"02/04/2026";"03/04/2026";"30/06/2026"}))),"-") -> 47 | U47: - | V47: - | W47: - | X47: - | Y47: - | Z47: =IFERROR(IF(Q47="-","-",IF(Q47="Proceso de implementación/Activación/Entrega","Proceso de implementación/Activación/Entrega",IF(OR(Q47="Desistido",Q47="No corresponde atención OGTI",Q47="Para reformulación"),Q47,IF(AND(Q47="Ejecutado",AA47="No aplica",AB47="No Aplica"),"Culminado",IF(Q47="Ejecutado",IF(AND(AC47="-",G47="Bienes"),"Culminado",IF(AC47="-","Falta informacion",IF(AND(AB47-TODAY()>=0,AB47-TODAY()<=90),"Vigente_por vencer",IF(AND(AH47<>"SI",AB47<TODAY()),"Culminado",IF(AND(AH47="SI",AB47<TODAY(),OR(AK47="Sin Registro",AL47="Sin Registro")),"Vencido",IF(AND(AH47="SI",AB47<TODAY(),AK47>AA47,AL47>AB47),"Renovado","Vigente")))))),"En tramite"))))),"-") -> En tramite | AA47: - | AB47: - | AC47: =IFERROR(IF(OR(AA47="-",AA47="",AB47="-",AB47=""),"-",CONCATENATE('Seguimiento OIT'!AB47-'Seguimiento OIT'!AA47+1," dias")),"-") -> - | AD47: =IFERROR(IF(Z47="Vencido",(TODAY()-AB47)+1,"-"),"-") -> - | AE47: *Con INFORME N° 0680-2026-EF/44.02 se remitió precios referenciales para transferencia presupuestal | AF47: - | AG47: https://mefgobpe1.sharepoint.com/:f:/t/DireccindelaOficinadeInfraestructuraTecnolgica/IgBUPSsg35-qQp6tZtqKWwwPAb2SNicKo9peNvNYzi6Jkdo?e=bH0dAj | AH47: NO | AI47: =IFERROR(IF(AH47="SI",VLOOKUP(A47,$C$4:$AL$151,15,FALSE),"-"),"Sin tramite") -> - | AJ47: =IFERROR(IF(AH47="SI",VLOOKUP(A47,$C$4:$AL$151,7,FALSE),"-"),"Sin HR") -> - | AK47: =IF(AH47="SI",IFERROR(IF(VLOOKUP(A47,$C$4:$AL$151,25,FALSE)="","Sin registro",VLOOKUP(A47,$C$4:$AL$151,25,FALSE)),"Sin registro"),"-") -> - | AL47: =IF(AH47="SI",IFERROR(IF(VLOOKUP(A47,$C$4:$AL$151,26,FALSE)="","Sin registro",VLOOKUP(A47,$C$4:$AL$151,26,FALSE)),"Sin registro"),"-") -> -
A48: REQ-2026-0044 | B48: =IF(OR(Q48="Desistido",Q48="No corresponde Atención OGTI",Q48="Para reformulación",Q48="Paralizado",Q48="-",Z48="Renovado",AND(AH48="NO",Z48="Culminado")),"NO","SI") -> SI | C48: - | D48: NO | E48: Contratación Directa | F48: Nuevo requerimiento | G48: Bienes | H48: Adquisición de dispositivos USB para la Dirección General de Tesoro Público | I48: 071517-2026 | J48: Dispositivo USB (60 unidades) | K48: Soporte Tecnico | L48: Napoleon Alva Vasquez | M48: Ronald Yrupailla Diaz | N48: Dirección General del Tesoro Público | O48: Pendiente | P48: 46155 | Q48: Apoyo presupuestal | R48: Área Usuaria | S48: 46178 | T48: =IFERROR(IF(OR(Q48="Ejecutado",Q48="No corresponde atención OGTI",Q48="Desistido",Q48="-",Q48="Para reformulación"),"-",IF(OR(S48="-",S48=""),"Falta fecha_estado",NETWORKDAYS(S48,TODAY(),{"02/04/2026";"03/04/2026";"30/06/2026"}))),"-") -> 40 | U48: - | V48: - | W48: - | X48: - | Y48: - | Z48: =IFERROR(IF(Q48="-","-",IF(Q48="Proceso de implementación/Activación/Entrega","Proceso de implementación/Activación/Entrega",IF(OR(Q48="Desistido",Q48="No corresponde atención OGTI",Q48="Para reformulación"),Q48,IF(AND(Q48="Ejecutado",AA48="No aplica",AB48="No Aplica"),"Culminado",IF(Q48="Ejecutado",IF(AND(AC48="-",G48="Bienes"),"Culminado",IF(AC48="-","Falta informacion",IF(AND(AB48-TODAY()>=0,AB48-TODAY()<=90),"Vigente_por vencer",IF(AND(AH48<>"SI",AB48<TODAY()),"Culminado",IF(AND(AH48="SI",AB48<TODAY(),OR(AK48="Sin Registro",AL48="Sin Registro")),"Vencido",IF(AND(AH48="SI",AB48<TODAY(),AK48>AA48,AL48>AB48),"Renovado","Vigente")))))),"En tramite"))))),"-") -> En tramite | AA48: - | AB48: - | AC48: =IFERROR(IF(OR(AA48="-",AA48="",AB48="-",AB48=""),"-",CONCATENATE('Seguimiento OIT'!AB48-'Seguimiento OIT'!AA48+1," dias")),"-") -> - | AD48: =IFERROR(IF(Z48="Vencido",(TODAY()-AB48)+1,"-"),"-") -> - | AE48: *Con fecha 05-06-26, se remitió por correo modelos y precios referenciales | AF48: - | AG48: https://mefgobpe1.sharepoint.com/:f:/t/DireccindelaOficinadeInfraestructuraTecnolgica/IgD2flBX7GfSTbMs7KOQ1x80AcrUHCVL3miZVXO0HQRN_Xw?e=HMbsvN | AH48: NO | AI48: =IFERROR(IF(AH48="SI",VLOOKUP(A48,$C$4:$AL$151,15,FALSE),"-"),"Sin tramite") -> - | AJ48: =IFERROR(IF(AH48="SI",VLOOKUP(A48,$C$4:$AL$151,7,FALSE),"-"),"Sin HR") -> - | AK48: =IF(AH48="SI",IFERROR(IF(VLOOKUP(A48,$C$4:$AL$151,25,FALSE)="","Sin registro",VLOOKUP(A48,$C$4:$AL$151,25,FALSE)),"Sin registro"),"-") -> - | AL48: =IF(AH48="SI",IFERROR(IF(VLOOKUP(A48,$C$4:$AL$151,26,FALSE)="","Sin registro",VLOOKUP(A48,$C$4:$AL$151,26,FALSE)),"Sin registro"),"-") -> -
A49: REQ-2026-0045 | B49: =IF(OR(Q49="Desistido",Q49="No corresponde Atención OGTI",Q49="Para reformulación",Q49="Paralizado",Q49="-",Z49="Renovado",AND(AH49="NO",Z49="Culminado")),"NO","SI") -> SI | C49: - | D49: NO | E49: Contratación Directa | F49: Nuevo requerimiento | G49: Bienes | H49: Adquisición de Soporte Cooler para ConectaMEF | I49: 067981-2026 | J49: Soporte cooler para laptop | K49: Soporte Tecnico | L49: Napoleon Alva Vasquez | M49: Ronald Yrupailla Diaz | N49: Oficina General de Servicios al Usuario | O49: Pendiente | P49: 46153 | Q49: Apoyo presupuestal | R49: Área Usuaria | S49: 46168 | T49: =IFERROR(IF(OR(Q49="Ejecutado",Q49="No corresponde atención OGTI",Q49="Desistido",Q49="-",Q49="Para reformulación"),"-",IF(OR(S49="-",S49=""),"Falta fecha_estado",NETWORKDAYS(S49,TODAY(),{"02/04/2026";"03/04/2026";"30/06/2026"}))),"-") -> 48 | U49: - | V49: - | W49: - | X49: - | Y49: - | Z49: =IFERROR(IF(Q49="-","-",IF(Q49="Proceso de implementación/Activación/Entrega","Proceso de implementación/Activación/Entrega",IF(OR(Q49="Desistido",Q49="No corresponde atención OGTI",Q49="Para reformulación"),Q49,IF(AND(Q49="Ejecutado",AA49="No aplica",AB49="No Aplica"),"Culminado",IF(Q49="Ejecutado",IF(AND(AC49="-",G49="Bienes"),"Culminado",IF(AC49="-","Falta informacion",IF(AND(AB49-TODAY()>=0,AB49-TODAY()<=90),"Vigente_por vencer",IF(AND(AH49<>"SI",AB49<TODAY()),"Culminado",IF(AND(AH49="SI",AB49<TODAY(),OR(AK49="Sin Registro",AL49="Sin Registro")),"Vencido",IF(AND(AH49="SI",AB49<TODAY(),AK49>AA49,AL49>AB49),"Renovado","Vigente")))))),"En tramite"))))),"-") -> En tramite | AA49: - | AB49: - | AC49: =IFERROR(IF(OR(AA49="-",AA49="",AB49="-",AB49=""),"-",CONCATENATE('Seguimiento OIT'!AB49-'Seguimiento OIT'!AA49+1," dias")),"-") -> - | AD49: =IFERROR(IF(Z49="Vencido",(TODAY()-AB49)+1,"-"),"-") -> - | AE49: *Con INFORME N° 0674-2026-EF/44.02 se remitió precios referenciales para transferencia presupuestal | AF49: - | AG49: https://mefgobpe1.sharepoint.com/:f:/t/DireccindelaOficinadeInfraestructuraTecnolgica/IgBKbKB4mdN1SbnHlk94zmKFAWpR_Tc_rBU2iTcW91S3K-c?e=TEIgtQ | AH49: NO | AI49: =IFERROR(IF(AH49="SI",VLOOKUP(A49,$C$4:$AL$151,15,FALSE),"-"),"Sin tramite") -> - | AJ49: =IFERROR(IF(AH49="SI",VLOOKUP(A49,$C$4:$AL$151,7,FALSE),"-"),"Sin HR") -> - | AK49: =IF(AH49="SI",IFERROR(IF(VLOOKUP(A49,$C$4:$AL$151,25,FALSE)="","Sin registro",VLOOKUP(A49,$C$4:$AL$151,25,FALSE)),"Sin registro"),"-") -> - | AL49: =IF(AH49="SI",IFERROR(IF(VLOOKUP(A49,$C$4:$AL$151,26,FALSE)="","Sin registro",VLOOKUP(A49,$C$4:$AL$151,26,FALSE)),"Sin registro"),"-") -> -
A50: REQ-2026-0049 | B50: =IF(OR(Q50="Desistido",Q50="No corresponde Atención OGTI",Q50="Para reformulación",Q50="Paralizado",Q50="-",Z50="Renovado",AND(AH50="NO",Z50="Culminado")),"NO","SI") -> SI | C50: - | D50: NO | E50: Procesos de Contratación | F50: Nuevo requerimiento | G50: Bienes | H50: Adquisición de kit de capacitación para ConectaMEF | I50: 082193-2026 | J50: *Proyector multimedia *Camara WEB *Parlantes *Maletin | K50: Soporte Tecnico | L50: Napoleon Alva Vasquez | M50: Ronald Yrupailla Diaz | N50: Oficina General de Servicios al Usuario | O50: Pendiente | P50: 46155 | Q50: Apoyo presupuestal | R50: Área Usuaria | S50: 46182 | T50: =IFERROR(IF(OR(Q50="Ejecutado",Q50="No corresponde atención OGTI",Q50="Desistido",Q50="-",Q50="Para reformulación"),"-",IF(OR(S50="-",S50=""),"Falta fecha_estado",NETWORKDAYS(S50,TODAY(),{"02/04/2026";"03/04/2026";"30/06/2026"}))),"-") -> 38 | U50: - | V50: - | W50: - | X50: - | Y50: - | Z50: =IFERROR(IF(Q50="-","-",IF(Q50="Proceso de implementación/Activación/Entrega","Proceso de implementación/Activación/Entrega",IF(OR(Q50="Desistido",Q50="No corresponde atención OGTI",Q50="Para reformulación"),Q50,IF(AND(Q50="Ejecutado",AA50="No aplica",AB50="No Aplica"),"Culminado",IF(Q50="Ejecutado",IF(AND(AC50="-",G50="Bienes"),"Culminado",IF(AC50="-","Falta informacion",IF(AND(AB50-TODAY()>=0,AB50-TODAY()<=90),"Vigente_por vencer",IF(AND(AH50<>"SI",AB50<TODAY()),"Culminado",IF(AND(AH50="SI",AB50<TODAY(),OR(AK50="Sin Registro",AL50="Sin Registro")),"Vencido",IF(AND(AH50="SI",AB50<TODAY(),AK50>AA50,AL50>AB50),"Renovado","Vigente")))))),"En tramite"))))),"-") -> En tramite | AA50: - | AB50: - | AC50: =IFERROR(IF(OR(AA50="-",AA50="",AB50="-",AB50=""),"-",CONCATENATE('Seguimiento OIT'!AB50-'Seguimiento OIT'!AA50+1," dias")),"-") -> - | AD50: =IFERROR(IF(Z50="Vencido",(TODAY()-AB50)+1,"-"),"-") -> - | AE50: *Con INFORME N° 0766-2026-EF/44.02 se remitió precios referenciales para transferencia presupuestal | AF50: - | AG50: https://mefgobpe1.sharepoint.com/:f:/t/DireccindelaOficinadeInfraestructuraTecnolgica/IgAc7H8GoPbfTr8WCDZnFkZnAaacb9TajeH91vfdbrGth4g?e=zAuHF0 | AH50: NO | AI50: =IFERROR(IF(AH50="SI",VLOOKUP(A50,$C$4:$AL$151,15,FALSE),"-"),"Sin tramite") -> - | AJ50: =IFERROR(IF(AH50="SI",VLOOKUP(A50,$C$4:$AL$151,7,FALSE),"-"),"Sin HR") -> - | AK50: =IF(AH50="SI",IFERROR(IF(VLOOKUP(A50,$C$4:$AL$151,25,FALSE)="","Sin registro",VLOOKUP(A50,$C$4:$AL$151,25,FALSE)),"Sin registro"),"-") -> - | AL50: =IF(AH50="SI",IFERROR(IF(VLOOKUP(A50,$C$4:$AL$151,26,FALSE)="","Sin registro",VLOOKUP(A50,$C$4:$AL$151,26,FALSE)),"Sin registro"),"-") -> -
A51: REQ-2026-0046 | B51: =IF(OR(Q51="Desistido",Q51="No corresponde Atención OGTI",Q51="Para reformulación",Q51="Paralizado",Q51="-",Z51="Renovado",AND(AH51="NO",Z51="Culminado")),"NO","SI") -> SI | C51: - | D51: NO | E51: Contratación Directa | F51: Nuevo requerimiento | G51: Servicios | H51: Servicio para la provisión de servicios de inteligencia artificial mediante APIs en la nube | I51: 151979-2026 (Requerimiento) 131349-2026 (Apoyo presupuestal) 143286-2026 (Apoyo presupuestal v2) | J51: Azure Open IA | K51: Jefatura OIT | L51: José Romucho Sotelo | M51: Ronald Yrupailla Diaz | N51: Oficina de Sistemas de Información | O51: Pendiente | P51: 46216 | Q51: Estudio de Mercado | R51: OAB | S51: 46219 | T51: =IFERROR(IF(OR(Q51="Ejecutado",Q51="No corresponde atención OGTI",Q51="Desistido",Q51="-",Q51="Para reformulación"),"-",IF(OR(S51="-",S51=""),"Falta fecha_estado",NETWORKDAYS(S51,TODAY(),{"02/04/2026";"03/04/2026";"30/06/2026"}))),"-") -> 12 | U51: - | V51: - | W51: - | X51: - | Y51: - | Z51: =IFERROR(IF(Q51="-","-",IF(Q51="Proceso de implementación/Activación/Entrega","Proceso de implementación/Activación/Entrega",IF(OR(Q51="Desistido",Q51="No corresponde atención OGTI",Q51="Para reformulación"),Q51,IF(AND(Q51="Ejecutado",AA51="No aplica",AB51="No Aplica"),"Culminado",IF(Q51="Ejecutado",IF(AND(AC51="-",G51="Bienes"),"Culminado",IF(AC51="-","Falta informacion",IF(AND(AB51-TODAY()>=0,AB51-TODAY()<=90),"Vigente_por vencer",IF(AND(AH51<>"SI",AB51<TODAY()),"Culminado",IF(AND(AH51="SI",AB51<TODAY(),OR(AK51="Sin Registro",AL51="Sin Registro")),"Vencido",IF(AND(AH51="SI",AB51<TODAY(),AK51>AA51,AL51>AB51),"Renovado","Vigente")))))),"En tramite"))))),"-") -> En tramite | AA51: - | AB51: - | AC51: =IFERROR(IF(OR(AA51="-",AA51="",AB51="-",AB51=""),"-",CONCATENATE('Seguimiento OIT'!AB51-'Seguimiento OIT'!AA51+1," dias")),"-") -> - | AD51: =IFERROR(IF(Z51="Vencido",(TODAY()-AB51)+1,"-"),"-") -> - | AE51: *Con Memorando N° 3253 -2026-EF/44.01 se remitió precios referenciales para transferencia presupuestal | AF51: - | AG51: https://mefgobpe1.sharepoint.com/:f:/t/DireccindelaOficinadeInfraestructuraTecnolgica/IgAsBDCJ9xclRbhEFK5UxzHqATql7VV08pXZIbXrDfZyuAk?e=efmGad | AH51: NO | AI51: =IFERROR(IF(AH51="SI",VLOOKUP(A51,$C$4:$AL$151,15,FALSE),"-"),"Sin tramite") -> - | AJ51: =IFERROR(IF(AH51="SI",VLOOKUP(A51,$C$4:$AL$151,7,FALSE),"-"),"Sin HR") -> - | AK51: =IF(AH51="SI",IFERROR(IF(VLOOKUP(A51,$C$4:$AL$151,25,FALSE)="","Sin registro",VLOOKUP(A51,$C$4:$AL$151,25,FALSE)),"Sin registro"),"-") -> - | AL51: =IF(AH51="SI",IFERROR(IF(VLOOKUP(A51,$C$4:$AL$151,26,FALSE)="","Sin registro",VLOOKUP(A51,$C$4:$AL$151,26,FALSE)),"Sin registro"),"-") -> -
A52: REQ-2026-0047 | B52: =IF(OR(Q52="Desistido",Q52="No corresponde Atención OGTI",Q52="Para reformulación",Q52="Paralizado",Q52="-",Z52="Renovado",AND(AH52="NO",Z52="Culminado")),"NO","SI") -> SI | C52: - | D52: NO | E52: Contratación Directa | F52: Nuevo requerimiento | G52: Servicios | H52: Servicio de suscripción a plataforma en la nube de inteligencia artificial generativa para el desarrollo de soluciones digitales | I52: 113265-2026 (Requerimiento) 131349-2026 (Apoyo presupuestal) 143286-2026 (Apoyo presupuestal v2) | J52: Cloude Code IA | K52: Jefatura OIT | L52: José Romucho Sotelo | M52: Ronald Yrupailla Diaz | N52: Oficina de Sistemas de Información | O52: Pendiente | P52: 46216 | Q52: Revisión OAB | R52: OAB | S52: 46227 | T52: =IFERROR(IF(OR(Q52="Ejecutado",Q52="No corresponde atención OGTI",Q52="Desistido",Q52="-",Q52="Para reformulación"),"-",IF(OR(S52="-",S52=""),"Falta fecha_estado",NETWORKDAYS(S52,TODAY(),{"02/04/2026";"03/04/2026";"30/06/2026"}))),"-") -> 6 | U52: - | V52: - | W52: - | X52: - | Y52: - | Z52: =IFERROR(IF(Q52="-","-",IF(Q52="Proceso de implementación/Activación/Entrega","Proceso de implementación/Activación/Entrega",IF(OR(Q52="Desistido",Q52="No corresponde atención OGTI",Q52="Para reformulación"),Q52,IF(AND(Q52="Ejecutado",AA52="No aplica",AB52="No Aplica"),"Culminado",IF(Q52="Ejecutado",IF(AND(AC52="-",G52="Bienes"),"Culminado",IF(AC52="-","Falta informacion",IF(AND(AB52-TODAY()>=0,AB52-TODAY()<=90),"Vigente_por vencer",IF(AND(AH52<>"SI",AB52<TODAY()),"Culminado",IF(AND(AH52="SI",AB52<TODAY(),OR(AK52="Sin Registro",AL52="Sin Registro")),"Vencido",IF(AND(AH52="SI",AB52<TODAY(),AK52>AA52,AL52>AB52),"Renovado","Vigente")))))),"En tramite"))))),"-") -> En tramite | AA52: - | AB52: - | AC52: =IFERROR(IF(OR(AA52="-",AA52="",AB52="-",AB52=""),"-",CONCATENATE('Seguimiento OIT'!AB52-'Seguimiento OIT'!AA52+1," dias")),"-") -> - | AD52: =IFERROR(IF(Z52="Vencido",(TODAY()-AB52)+1,"-"),"-") -> - | AE52: - | AF52: - | AG52: https://mefgobpe1.sharepoint.com/:f:/t/DireccindelaOficinadeInfraestructuraTecnolgica/IgD6JLj_wjUgRJ2H1glPSFJGAasqmd1zXLL-AaCy1G5coZw?e=ydeWx0 | AH52: NO | AI52: =IFERROR(IF(AH52="SI",VLOOKUP(A52,$C$4:$AL$151,15,FALSE),"-"),"Sin tramite") -> - | AJ52: =IFERROR(IF(AH52="SI",VLOOKUP(A52,$C$4:$AL$151,7,FALSE),"-"),"Sin HR") -> - | AK52: =IF(AH52="SI",IFERROR(IF(VLOOKUP(A52,$C$4:$AL$151,25,FALSE)="","Sin registro",VLOOKUP(A52,$C$4:$AL$151,25,FALSE)),"Sin registro"),"-") -> - | AL52: =IF(AH52="SI",IFERROR(IF(VLOOKUP(A52,$C$4:$AL$151,26,FALSE)="","Sin registro",VLOOKUP(A52,$C$4:$AL$151,26,FALSE)),"Sin registro"),"-") -> -
A53: REQ-2026-0050 | B53: =IF(OR(Q53="Desistido",Q53="No corresponde Atención OGTI",Q53="Para reformulación",Q53="Paralizado",Q53="-",Z53="Renovado",AND(AH53="NO",Z53="Culminado")),"NO","SI") -> SI | C53: - | D53: NO | E53: Procesos de Contratación | F53: Complementario | G53: Servicios | H53: Servicio de alquiler de equipos de computo portátiles a demanda | I53: 169540-2025 | J53: Alquiler de laptops | K53: Soporte Tecnico | L53: Napoleon Alva Vasquez | M53: Napoleon Alva Vasquez | N53: Ministerio de Economía y Finanzas | O53: 142110 | P53: 45891 | Q53: Ejecutado | R53: - | T53: =IFERROR(IF(OR(Q53="Ejecutado",Q53="No corresponde atención OGTI",Q53="Desistido",Q53="-",Q53="Para reformulación"),"-",IF(OR(S53="-",S53=""),"Falta fecha_estado",NETWORKDAYS(S53,TODAY(),{"02/04/2026";"03/04/2026";"30/06/2026"}))),"-") -> - | U53: Contrato complementario | V53: 006-2024-EF/43.03 | W53: 45905 | X53: Corporacion Winware S.A.C | Y53: Napoleon Alva Vasquez | Z53: =IFERROR(IF(Q53="-","-",IF(Q53="Proceso de implementación/Activación/Entrega","Proceso de implementación/Activación/Entrega",IF(OR(Q53="Desistido",Q53="No corresponde atención OGTI",Q53="Para reformulación"),Q53,IF(AND(Q53="Ejecutado",AA53="No aplica",AB53="No Aplica"),"Culminado",IF(Q53="Ejecutado",IF(AND(AC53="-",G53="Bienes"),"Culminado",IF(AC53="-","Falta informacion",IF(AND(AB53-TODAY()>=0,AB53-TODAY()<=90),"Vigente_por vencer",IF(AND(AH53<>"SI",AB53<TODAY()),"Culminado",IF(AND(AH53="SI",AB53<TODAY(),OR(AK53="Sin Registro",AL53="Sin Registro")),"Vencido",IF(AND(AH53="SI",AB53<TODAY(),AK53>AA53,AL53>AB53),"Renovado","Vigente")))))),"En tramite"))))),"-") -> Vigente_por vencer | AA53: 45905 | AB53: 46295 | AC53: =IFERROR(IF(OR(AA53="-",AA53="",AB53="-",AB53=""),"-",CONCATENATE('Seguimiento OIT'!AB53-'Seguimiento OIT'!AA53+1," dias")),"-") -> 391 dias | AD53: =IFERROR(IF(Z53="Vencido",(TODAY()-AB53)+1,"-"),"-") -> - | AE53: - | AF53: *Conformidad HR 132908-2026 (Periodo 06-05-2026 al 05-06-2026) *Fecha fin vigencia es aproximado | AG53: https://mefgobpe1.sharepoint.com/:f:/t/DireccindelaOficinadeInfraestructuraTecnolgica/IgATdf9CJN8cQbQcvblcs8u0ATMqLMN04WtNZ6TgjWlgCPw?e=d0qxUi | AH53: NO | AI53: =IFERROR(IF(AH53="SI",VLOOKUP(A53,$C$4:$AL$151,15,FALSE),"-"),"Sin tramite") -> - | AJ53: =IFERROR(IF(AH53="SI",VLOOKUP(A53,$C$4:$AL$151,7,FALSE),"-"),"Sin HR") -> - | AK53: =IF(AH53="SI",IFERROR(IF(VLOOKUP(A53,$C$4:$AL$151,25,FALSE)="","Sin registro",VLOOKUP(A53,$C$4:$AL$151,25,FALSE)),"Sin registro"),"-") -> - | AL53: =IF(AH53="SI",IFERROR(IF(VLOOKUP(A53,$C$4:$AL$151,26,FALSE)="","Sin registro",VLOOKUP(A53,$C$4:$AL$151,26,FALSE)),"Sin registro"),"-") -> -
A54: REQ-2026-0052 | B54: =IF(OR(Q54="Desistido",Q54="No corresponde Atención OGTI",Q54="Para reformulación",Q54="Paralizado",Q54="-",Z54="Renovado",AND(AH54="NO",Z54="Culminado")),"NO","SI") -> SI | C54: - | D54: NO | E54: Contratación Directa | F54: Nuevo requerimiento | G54: Servicios | H54: Servicio de mantenimiento preventivo y correctivo de los equipos capturadores de imagen del Tribunal Fiscal | I54: 069485-2023 | J54: Mantenimiento preventivo y correctivo de escaneres del Tribunal Fiscal | K54: Soporte Tecnico | L54: Napoleon Alva Vasquez | M54: Napoleon Alva Vasquez | N54: Tribunal Fiscal | O54: 27760 | P54: 45139 | Q54: Ejecutado | R54: - | T54: =IFERROR(IF(OR(Q54="Ejecutado",Q54="No corresponde atención OGTI",Q54="Desistido",Q54="-",Q54="Para reformulación"),"-",IF(OR(S54="-",S54=""),"Falta fecha_estado",NETWORKDAYS(S54,TODAY(),{"02/04/2026";"03/04/2026";"30/06/2026"}))),"-") -> - | U54: Contrato | V54: 015 -2024-EF/43.03/ASP | W54: 45384 | X54: 2BM COMPANY E.I.R.L. | Y54: Napoleon Alva Vasquez | Z54: =IFERROR(IF(Q54="-","-",IF(Q54="Proceso de implementación/Activación/Entrega","Proceso de implementación/Activación/Entrega",IF(OR(Q54="Desistido",Q54="No corresponde atención OGTI",Q54="Para reformulación"),Q54,IF(AND(Q54="Ejecutado",AA54="No aplica",AB54="No Aplica"),"Culminado",IF(Q54="Ejecutado",IF(AND(AC54="-",G54="Bienes"),"Culminado",IF(AC54="-","Falta informacion",IF(AND(AB54-TODAY()>=0,AB54-TODAY()<=90),"Vigente_por vencer",IF(AND(AH54<>"SI",AB54<TODAY()),"Culminado",IF(AND(AH54="SI",AB54<TODAY(),OR(AK54="Sin Registro",AL54="Sin Registro")),"Vencido",IF(AND(AH54="SI",AB54<TODAY(),AK54>AA54,AL54>AB54),"Renovado","Vigente")))))),"En tramite"))))),"-") -> Vigente_por vencer | AA54: 45580 | AB54: 46309 | AC54: =IFERROR(IF(OR(AA54="-",AA54="",AB54="-",AB54=""),"-",CONCATENATE('Seguimiento OIT'!AB54-'Seguimiento OIT'!AA54+1," dias")),"-") -> 730 dias | AD54: =IFERROR(IF(Z54="Vencido",(TODAY()-AB54)+1,"-"),"-") -> - | AE54: - | AF54: *Conformidad HR 090980-2026 (5to trimestre) | AG54: https://mefgobpe1.sharepoint.com/:f:/t/DireccindelaOficinadeInfraestructuraTecnolgica/IgAyYKR9Rz3GTqRhpARK_UGzAaAiC3mq1StM2p9W0NbDjMI?e=rVekIq | AH54: NO | AI54: =IFERROR(IF(AH54="SI",VLOOKUP(A54,$C$4:$AL$151,15,FALSE),"-"),"Sin tramite") -> - | AJ54: =IFERROR(IF(AH54="SI",VLOOKUP(A54,$C$4:$AL$151,7,FALSE),"-"),"Sin HR") -> - | AK54: =IF(AH54="SI",IFERROR(IF(VLOOKUP(A54,$C$4:$AL$151,25,FALSE)="","Sin registro",VLOOKUP(A54,$C$4:$AL$151,25,FALSE)),"Sin registro"),"-") -> - | AL54: =IF(AH54="SI",IFERROR(IF(VLOOKUP(A54,$C$4:$AL$151,26,FALSE)="","Sin registro",VLOOKUP(A54,$C$4:$AL$151,26,FALSE)),"Sin registro"),"-") -> -
A55: REQ-2026-0051 | B55: =IF(OR(Q55="Desistido",Q55="No corresponde Atención OGTI",Q55="Para reformulación",Q55="Paralizado",Q55="-",Z55="Renovado",AND(AH55="NO",Z55="Culminado")),"NO","SI") -> SI | C55: - | D55: NO | E55: Contratación Directa | F55: Renovación | G55: Servicios | H55: Servicio de internet inalámbrico portátil para el Ministerio de Economía y Finanzas (MEF) | I55: 119855-2026 | J55: Internet Inalámbrico Portátil MEF | K55: Redes y Comunicaciones | L55: Elliot Hans Lindo Claudet | M55: Elliot Hans Lindo Claudet | N55: Oficina de Infraestructura Tecnológica | O55: 39880 | P55: 46174 | Q55: Proceso de implementación/Activación/Entrega | R55: - | S55: 46217 | T55: =IFERROR(IF(OR(Q55="Ejecutado",Q55="No corresponde atención OGTI",Q55="Desistido",Q55="-",Q55="Para reformulación"),"-",IF(OR(S55="-",S55=""),"Falta fecha_estado",NETWORKDAYS(S55,TODAY(),{"02/04/2026";"03/04/2026";"30/06/2026"}))),"-") -> 14 | U55: Contrato | V55: N° 015-2026-EF/43.03/CM | W55: 46217 | X55: ENTEL PERU S.A. | Y55: Edgar Aguilar Pérez | Z55: =IFERROR(IF(Q55="-","-",IF(Q55="Proceso de implementación/Activación/Entrega","Proceso de implementación/Activación/Entrega",IF(OR(Q55="Desistido",Q55="No corresponde atención OGTI",Q55="Para reformulación"),Q55,IF(AND(Q55="Ejecutado",AA55="No aplica",AB55="No Aplica"),"Culminado",IF(Q55="Ejecutado",IF(AND(AC55="-",G55="Bienes"),"Culminado",IF(AC55="-","Falta informacion",IF(AND(AB55-TODAY()>=0,AB55-TODAY()<=90),"Vigente_por vencer",IF(AND(AH55<>"SI",AB55<TODAY()),"Culminado",IF(AND(AH55="SI",AB55<TODAY(),OR(AK55="Sin Registro",AL55="Sin Registro")),"Vencido",IF(AND(AH55="SI",AB55<TODAY(),AK55>AA55,AL55>AB55),"Renovado","Vigente")))))),"En tramite"))))),"-") -> Proceso de implementación/Activación/Entrega | AC55: =IFERROR(IF(OR(AA55="-",AA55="",AB55="-",AB55=""),"-",CONCATENATE('Seguimiento OIT'!AB55-'Seguimiento OIT'!AA55+1," dias")),"-") -> - | AD55: =IFERROR(IF(Z55="Vencido",(TODAY()-AB55)+1,"-"),"-") -> - | AE55: Ref. Contrato N° 006-2025-EF/43.03/CM | AF55: En proceso de la entrega de los dispositivos inalambricos y activación del servicio | AG55: https://mefgobpe1.sharepoint.com/:f:/t/DireccindelaOficinadeInfraestructuraTecnolgica/IgDjhjGF19JDRIeDwDUfIO7FAev45khWbVZ8VK4cB271cGM?e=U1nujC | AH55: NO | AI55: =IFERROR(IF(AH55="SI",VLOOKUP(A55,$C$4:$AL$151,15,FALSE),"-"),"Sin tramite") -> - | AJ55: =IFERROR(IF(AH55="SI",VLOOKUP(A55,$C$4:$AL$151,7,FALSE),"-"),"Sin HR") -> - | AK55: =IF(AH55="SI",IFERROR(IF(VLOOKUP(A55,$C$4:$AL$151,25,FALSE)="","Sin registro",VLOOKUP(A55,$C$4:$AL$151,25,FALSE)),"Sin registro"),"-") -> - | AL55: =IF(AH55="SI",IFERROR(IF(VLOOKUP(A55,$C$4:$AL$151,26,FALSE)="","Sin registro",VLOOKUP(A55,$C$4:$AL$151,26,FALSE)),"Sin registro"),"-") -> -
A56: REQ-2026-0053 | B56: =IF(OR(Q56="Desistido",Q56="No corresponde Atención OGTI",Q56="Para reformulación",Q56="Paralizado",Q56="-",Z56="Renovado",AND(AH56="NO",Z56="Culminado")),"NO","SI") -> NO | C56: - | D56: NO | E56: Contratación Directa | F56: Nuevo requerimiento | G56: Servicios | H56: Servicio de soporte técnico para la recuperación del dispositivo contenedor de respaldos IBM | I56: 124367-2026 (Requerimiento) 131349-2026 (Apoyo presupuestal) | J56: Mantenimiento correctivo Storage IBM | K56: Computo | L56: Rolly Villegas Delgado | M56: Anthony Céspedes Molina | N56: Oficina de Infraestructura Tecnológica | O56: - | P56: 46182 | Q56: Desistido | R56: - | S56: - | T56: =IFERROR(IF(OR(Q56="Ejecutado",Q56="No corresponde atención OGTI",Q56="Desistido",Q56="-",Q56="Para reformulación"),"-",IF(OR(S56="-",S56=""),"Falta fecha_estado",NETWORKDAYS(S56,TODAY(),{"02/04/2026";"03/04/2026";"30/06/2026"}))),"-") -> - | U56: - | Y56: - | Z56: =IFERROR(IF(Q56="-","-",IF(Q56="Proceso de implementación/Activación/Entrega","Proceso de implementación/Activación/Entrega",IF(OR(Q56="Desistido",Q56="No corresponde atención OGTI",Q56="Para reformulación"),Q56,IF(AND(Q56="Ejecutado",AA56="No aplica",AB56="No Aplica"),"Culminado",IF(Q56="Ejecutado",IF(AND(AC56="-",G56="Bienes"),"Culminado",IF(AC56="-","Falta informacion",IF(AND(AB56-TODAY()>=0,AB56-TODAY()<=90),"Vigente_por vencer",IF(AND(AH56<>"SI",AB56<TODAY()),"Culminado",IF(AND(AH56="SI",AB56<TODAY(),OR(AK56="Sin Registro",AL56="Sin Registro")),"Vencido",IF(AND(AH56="SI",AB56<TODAY(),AK56>AA56,AL56>AB56),"Renovado","Vigente")))))),"En tramite"))))),"-") -> Desistido | AC56: =IFERROR(IF(OR(AA56="-",AA56="",AB56="-",AB56=""),"-",CONCATENATE('Seguimiento OIT'!AB56-'Seguimiento OIT'!AA56+1," dias")),"-") -> - | AD56: =IFERROR(IF(Z56="Vencido",(TODAY()-AB56)+1,"-"),"-") -> - | AE56: EL REQUERIMIENTO SE ATENDERÁ CON LA CONTRATACIÓN DEL SERVICIO DE GARANTÍA EXTENDIDA DE IBM QUE YA ESTÁ EN PROCESO CON HR 009025-2026. | AF56: - | AG56: https://mefgobpe1.sharepoint.com/:f:/t/DireccindelaOficinadeInfraestructuraTecnolgica/IgCg747yJeBUTKCdhcPm7-mBAX9LiZoZbY3IE0iFTh64jTg?e=TdPR2U | AH56: NO | AI56: =IFERROR(IF(AH56="SI",VLOOKUP(A56,$C$4:$AL$151,15,FALSE),"-"),"Sin tramite") -> - | AJ56: =IFERROR(IF(AH56="SI",VLOOKUP(A56,$C$4:$AL$151,7,FALSE),"-"),"Sin HR") -> - | AK56: =IF(AH56="SI",IFERROR(IF(VLOOKUP(A56,$C$4:$AL$151,25,FALSE)="","Sin registro",VLOOKUP(A56,$C$4:$AL$151,25,FALSE)),"Sin registro"),"-") -> - | AL56: =IF(AH56="SI",IFERROR(IF(VLOOKUP(A56,$C$4:$AL$151,26,FALSE)="","Sin registro",VLOOKUP(A56,$C$4:$AL$151,26,FALSE)),"Sin registro"),"-") -> -
A57: REQ-2026-0054 | B57: =IF(OR(Q57="Desistido",Q57="No corresponde Atención OGTI",Q57="Para reformulación",Q57="Paralizado",Q57="-",Z57="Renovado",AND(AH57="NO",Z57="Culminado")),"NO","SI") -> SI | C57: - | D57: 2026 | E57: Procesos de Contratación | F57: Nuevo requerimiento | G57: Servicios | H57: Servicio de Mantenimiento Preventivo y Correctivo de la Central Telefónica marca Alcatel-Lucent, modelo OMNIPCX Enterprise “o equivalente” del MEF | I57: 098165-2026 (Requerimiento) 131349-2026 (Apoyo presupuestal) | J57: Mantenimiento preventivo y correctivo Central Telefonica Alcatel-Lucent | K57: Telefonía | L57: Isaias Bolivar Reaño | M57: Isaias Bolivar Reaño | N57: Oficina de Infraestructura Tecnológica | O57: Pendiente | P57: 46146 | Q57: Apoyo presupuestal | R57: OGTI | S57: 46197 | T57: =IFERROR(IF(OR(Q57="Ejecutado",Q57="No corresponde atención OGTI",Q57="Desistido",Q57="-",Q57="Para reformulación"),"-",IF(OR(S57="-",S57=""),"Falta fecha_estado",NETWORKDAYS(S57,TODAY(),{"02/04/2026";"03/04/2026";"30/06/2026"}))),"-") -> 27 | U57: - | Y57: - | Z57: =IFERROR(IF(Q57="-","-",IF(Q57="Proceso de implementación/Activación/Entrega","Proceso de implementación/Activación/Entrega",IF(OR(Q57="Desistido",Q57="No corresponde atención OGTI",Q57="Para reformulación"),Q57,IF(AND(Q57="Ejecutado",AA57="No aplica",AB57="No Aplica"),"Culminado",IF(Q57="Ejecutado",IF(AND(AC57="-",G57="Bienes"),"Culminado",IF(AC57="-","Falta informacion",IF(AND(AB57-TODAY()>=0,AB57-TODAY()<=90),"Vigente_por vencer",IF(AND(AH57<>"SI",AB57<TODAY()),"Culminado",IF(AND(AH57="SI",AB57<TODAY(),OR(AK57="Sin Registro",AL57="Sin Registro")),"Vencido",IF(AND(AH57="SI",AB57<TODAY(),AK57>AA57,AL57>AB57),"Renovado","Vigente")))))),"En tramite"))))),"-") -> En tramite | AC57: =IFERROR(IF(OR(AA57="-",AA57="",AB57="-",AB57=""),"-",CONCATENATE('Seguimiento OIT'!AB57-'Seguimiento OIT'!AA57+1," dias")),"-") -> - | AD57: =IFERROR(IF(Z57="Vencido",(TODAY()-AB57)+1,"-"),"-") -> - | AE57: - | AF57: - | AG57: https://mefgobpe1.sharepoint.com/:f:/t/DireccindelaOficinadeInfraestructuraTecnolgica/IgAfm3sUuE2QSrQPsgMB-VRcAWR5KZowvjZjVPZ4sAyd1yw?e=c931SK | AH57: NO | AI57: =IFERROR(IF(AH57="SI",VLOOKUP(A57,$C$4:$AL$151,15,FALSE),"-"),"Sin tramite") -> - | AJ57: =IFERROR(IF(AH57="SI",VLOOKUP(A57,$C$4:$AL$151,7,FALSE),"-"),"Sin HR") -> - | AK57: =IF(AH57="SI",IFERROR(IF(VLOOKUP(A57,$C$4:$AL$151,25,FALSE)="","Sin registro",VLOOKUP(A57,$C$4:$AL$151,25,FALSE)),"Sin registro"),"-") -> - | AL57: =IF(AH57="SI",IFERROR(IF(VLOOKUP(A57,$C$4:$AL$151,26,FALSE)="","Sin registro",VLOOKUP(A57,$C$4:$AL$151,26,FALSE)),"Sin registro"),"-") -> -
A58: REQ-2026-0055 | B58: =IF(OR(Q58="Desistido",Q58="No corresponde Atención OGTI",Q58="Para reformulación",Q58="Paralizado",Q58="-",Z58="Renovado",AND(AH58="NO",Z58="Culminado")),"NO","SI") -> SI | C58: - | D58: NO | E58: Contratación Directa | F58: Nuevo requerimiento | G58: Servicios | H58: Servicio de soporte técnico para la plataforma virtual de infraestructura de TI de la marca VMWARE BY BROADCOM | I58: 151365-2026 (Requerimiento) 131349-2026 (Apoyo presupuestal) 096068-2026 (Requerimiento inicial) | J58: Soporte horas - VMWARE By Broadcom | K58: Computo | L58: Rolly Villegas Delgado | M58: Anthony Céspedes Molina | N58: Oficina de Infraestructura Tecnológica | O58: Pendiente | P58: 46178 | Q58: En tramite | R58: OGTI | S58: 46225 | T58: =IFERROR(IF(OR(Q58="Ejecutado",Q58="No corresponde atención OGTI",Q58="Desistido",Q58="-",Q58="Para reformulación"),"-",IF(OR(S58="-",S58=""),"Falta fecha_estado",NETWORKDAYS(S58,TODAY(),{"02/04/2026";"03/04/2026";"30/06/2026"}))),"-") -> 8 | U58: - | Y58: - | Z58: =IFERROR(IF(Q58="-","-",IF(Q58="Proceso de implementación/Activación/Entrega","Proceso de implementación/Activación/Entrega",IF(OR(Q58="Desistido",Q58="No corresponde atención OGTI",Q58="Para reformulación"),Q58,IF(AND(Q58="Ejecutado",AA58="No aplica",AB58="No Aplica"),"Culminado",IF(Q58="Ejecutado",IF(AND(AC58="-",G58="Bienes"),"Culminado",IF(AC58="-","Falta informacion",IF(AND(AB58-TODAY()>=0,AB58-TODAY()<=90),"Vigente_por vencer",IF(AND(AH58<>"SI",AB58<TODAY()),"Culminado",IF(AND(AH58="SI",AB58<TODAY(),OR(AK58="Sin Registro",AL58="Sin Registro")),"Vencido",IF(AND(AH58="SI",AB58<TODAY(),AK58>AA58,AL58>AB58),"Renovado","Vigente")))))),"En tramite"))))),"-") -> En tramite | AC58: =IFERROR(IF(OR(AA58="-",AA58="",AB58="-",AB58=""),"-",CONCATENATE('Seguimiento OIT'!AB58-'Seguimiento OIT'!AA58+1," dias")),"-") -> - | AD58: =IFERROR(IF(Z58="Vencido",(TODAY()-AB58)+1,"-"),"-") -> - | AE58: - | AF58: - | AG58: https://mefgobpe1.sharepoint.com/:f:/t/DireccindelaOficinadeInfraestructuraTecnolgica/IgDYbygM1TKCTaKjM2TxGG1GAUtmVpnsR3k6dcpXEvhYdUY?e=lsBvaX | AH58: NO | AI58: =IFERROR(IF(AH58="SI",VLOOKUP(A58,$C$4:$AL$151,15,FALSE),"-"),"Sin tramite") -> - | AJ58: =IFERROR(IF(AH58="SI",VLOOKUP(A58,$C$4:$AL$151,7,FALSE),"-"),"Sin HR") -> - | AK58: =IF(AH58="SI",IFERROR(IF(VLOOKUP(A58,$C$4:$AL$151,25,FALSE)="","Sin registro",VLOOKUP(A58,$C$4:$AL$151,25,FALSE)),"Sin registro"),"-") -> - | AL58: =IF(AH58="SI",IFERROR(IF(VLOOKUP(A58,$C$4:$AL$151,26,FALSE)="","Sin registro",VLOOKUP(A58,$C$4:$AL$151,26,FALSE)),"Sin registro"),"-") -> -
A59: REQ-2026-0056 | B59: =IF(OR(Q59="Desistido",Q59="No corresponde Atención OGTI",Q59="Para reformulación",Q59="Paralizado",Q59="-",Z59="Renovado",AND(AH59="NO",Z59="Culminado")),"NO","SI") -> SI | C59: - | D59: 2026 | E59: Procesos de Contratación | F59: Renovación | G59: Servicios | H59: Servicio de transmisión de datos para los CONECTAMEF a nivel nacional. ÍTEM 1: Servicio de transmisión de datos para los CONECTAMEF Principal CP SER-SM-1-2026-EF/43-1 | I59: 261474-2025 (Requerimiento) 111575-2026 (Apoyo Presupuestal) *150342-2026 (Contrato) | J59: Transmisión de datos- CONECTAMEF a nivel nacional- Item1 Principal | K59: Redes y Comunicaciones | L59: Elliot Hans Lindo Claudet | M59: Elliot Hans Lindo Claudet | N59: Oficina de Infraestructura Tecnológica | O59: 15225600 | P59: 46006 | Q59: Proceso de implementación/Activación/Entrega | R59: OIT-Redes y Comunicaciones | S59: 46218 | T59: =IFERROR(IF(OR(Q59="Ejecutado",Q59="No corresponde atención OGTI",Q59="Desistido",Q59="-",Q59="Para reformulación"),"-",IF(OR(S59="-",S59=""),"Falta fecha_estado",NETWORKDAYS(S59,TODAY(),{"02/04/2026";"03/04/2026";"30/06/2026"}))),"-") -> 13 | U59: Contrato | V59: N° 042-2026-EF/43.03 | W59: 46216 | X59: ENTEL PERU S.A. | Y59: Elliot Hans Lindo Claudet | Z59: =IFERROR(IF(Q59="-","-",IF(Q59="Proceso de implementación/Activación/Entrega","Proceso de implementación/Activación/Entrega",IF(OR(Q59="Desistido",Q59="No corresponde atención OGTI",Q59="Para reformulación"),Q59,IF(AND(Q59="Ejecutado",AA59="No aplica",AB59="No Aplica"),"Culminado",IF(Q59="Ejecutado",IF(AND(AC59="-",G59="Bienes"),"Culminado",IF(AC59="-","Falta informacion",IF(AND(AB59-TODAY()>=0,AB59-TODAY()<=90),"Vigente_por vencer",IF(AND(AH59<>"SI",AB59<TODAY()),"Culminado",IF(AND(AH59="SI",AB59<TODAY(),OR(AK59="Sin Registro",AL59="Sin Registro")),"Vencido",IF(AND(AH59="SI",AB59<TODAY(),AK59>AA59,AL59>AB59),"Renovado","Vigente")))))),"En tramite"))))),"-") -> Proceso de implementación/Activación/Entrega | AA59: 46217 | AB59: 46292 | AC59: =IFERROR(IF(OR(AA59="-",AA59="",AB59="-",AB59=""),"-",CONCATENATE('Seguimiento OIT'!AB59-'Seguimiento OIT'!AA59+1," dias")),"-") -> 76 dias | AD59: =IFERROR(IF(Z59="Vencido",(TODAY()-AB59)+1,"-"),"-") -> - | AE59: - | AF59: Son 69 días de implementación + 10 días del acta de activación, luego iniciaria el servicio | AG59: https://mefgobpe1.sharepoint.com/:f:/t/DireccindelaOficinadeInfraestructuraTecnolgica/IgCzqnpWYXwQRoTRJy4Ukaz-Aft5ctBNoB3Tm9DuplAl7P0?e=TbLOBC | AH59: NO | AI59: =IFERROR(IF(AH59="SI",VLOOKUP(A59,$C$4:$AL$151,15,FALSE),"-"),"Sin tramite") -> - | AJ59: =IFERROR(IF(AH59="SI",VLOOKUP(A59,$C$4:$AL$151,7,FALSE),"-"),"Sin HR") -> - | AK59: =IF(AH59="SI",IFERROR(IF(VLOOKUP(A59,$C$4:$AL$151,25,FALSE)="","Sin registro",VLOOKUP(A59,$C$4:$AL$151,25,FALSE)),"Sin registro"),"-") -> - | AL59: =IF(AH59="SI",IFERROR(IF(VLOOKUP(A59,$C$4:$AL$151,26,FALSE)="","Sin registro",VLOOKUP(A59,$C$4:$AL$151,26,FALSE)),"Sin registro"),"-") -> -
A60: REQ-2026-0057 | B60: =IF(OR(Q60="Desistido",Q60="No corresponde Atención OGTI",Q60="Para reformulación",Q60="Paralizado",Q60="-",Z60="Renovado",AND(AH60="NO",Z60="Culminado")),"NO","SI") -> SI | C60: REQ-2026-0056 | D60: 2026 | E60: Contratación Directa | F60: Complementario | G60: Servicios | H60: Servicio de transmisión de datos para los CONECTAMEF a nivel nacional. ÍTEM 1: Servicio de transmisión de datos para los CONECTAMEF principal- COMPLEMENTARIO | I60: 262254-2025 | J60: Transmisión de datos- CONECTAMEF a nivel nacional- Item1 Complementario | K60: Redes y Comunicaciones | L60: Elliot Hans Lindo Claudet | M60: Elliot Hans Lindo Claudet | N60: Oficina de Infraestructura Tecnológica | O60: 2316392.6 | P60: 46007 | Q60: Ejecutado | R60: - | S60: - | T60: =IFERROR(IF(OR(Q60="Ejecutado",Q60="No corresponde atención OGTI",Q60="Desistido",Q60="-",Q60="Para reformulación"),"-",IF(OR(S60="-",S60=""),"Falta fecha_estado",NETWORKDAYS(S60,TODAY(),{"02/04/2026";"03/04/2026";"30/06/2026"}))),"-") -> - | U60: Contrato | V60: N° 001 -2026-EF/43.03 | W60: 46043 | X60: CONSORCIO AMERICATEL PERÚ S.A & ENTEL PERÚ S.A. | Y60: Elliot Hans Lindo Claudet | Z60: =IFERROR(IF(Q60="-","-",IF(Q60="Proceso de implementación/Activación/Entrega","Proceso de implementación/Activación/Entrega",IF(OR(Q60="Desistido",Q60="No corresponde atención OGTI",Q60="Para reformulación"),Q60,IF(AND(Q60="Ejecutado",AA60="No aplica",AB60="No Aplica"),"Culminado",IF(Q60="Ejecutado",IF(AND(AC60="-",G60="Bienes"),"Culminado",IF(AC60="-","Falta informacion",IF(AND(AB60-TODAY()>=0,AB60-TODAY()<=90),"Vigente_por vencer",IF(AND(AH60<>"SI",AB60<TODAY()),"Culminado",IF(AND(AH60="SI",AB60<TODAY(),OR(AK60="Sin Registro",AL60="Sin Registro")),"Vencido",IF(AND(AH60="SI",AB60<TODAY(),AK60>AA60,AL60>AB60),"Renovado","Vigente")))))),"En tramite"))))),"-") -> Vigente_por vencer | AA60: 46044 | AB60: 46261 | AC60: =IFERROR(IF(OR(AA60="-",AA60="",AB60="-",AB60=""),"-",CONCATENATE('Seguimiento OIT'!AB60-'Seguimiento OIT'!AA60+1," dias")),"-") -> 218 dias | AH60: NO | AI60: =IFERROR(IF(AH60="SI",VLOOKUP(A60,$C$4:$AL$151,15,FALSE),"-"),"Sin tramite") -> - | AJ60: =IFERROR(IF(AH60="SI",VLOOKUP(A60,$C$4:$AL$151,7,FALSE),"-"),"Sin HR") -> - | AK60: =IF(AH60="SI",IFERROR(IF(VLOOKUP(A60,$C$4:$AL$151,25,FALSE)="","Sin registro",VLOOKUP(A60,$C$4:$AL$151,25,FALSE)),"Sin registro"),"-") -> - | AL60: =IF(AH60="SI",IFERROR(IF(VLOOKUP(A60,$C$4:$AL$151,26,FALSE)="","Sin registro",VLOOKUP(A60,$C$4:$AL$151,26,FALSE)),"Sin registro"),"-") -> -
A61: REQ-2026-0058 | B61: =IF(OR(Q61="Desistido",Q61="No corresponde Atención OGTI",Q61="Para reformulación",Q61="Paralizado",Q61="-",Z61="Renovado",AND(AH61="NO",Z61="Culminado")),"NO","SI") -> SI | C61: - | D61: 2026 | E61: Procesos de Contratación | F61: Renovación | G61: Servicios | H61: Servicio de Transmisión de datos para los CONECTAMEF A Nivel Nacional -ITEM N° 2: Servicio de Transmisión de datos para los CONECTAMEF A Nivel Nacional Principal | I61: 261474-2025 (Requerimiento) 111575-2026 (Apoyo Presupuestal) *150353-2026 (Contrato) | J61: Transmisión de datos- CONECTAMEF a nivel nacional- Item 2 Secundario | K61: Redes y Comunicaciones | L61: Elliot Hans Lindo Claudet | M61: Elliot Hans Lindo Claudet | N61: Oficina de Infraestructura Tecnológica | O61: 2931120 | P61: 46006 | Q61: Proceso de implementación/Activación/Entrega | R61: OIT-Redes y Comunicaciones | S61: 46218 | T61: =IFERROR(IF(OR(Q61="Ejecutado",Q61="No corresponde atención OGTI",Q61="Desistido",Q61="-",Q61="Para reformulación"),"-",IF(OR(S61="-",S61=""),"Falta fecha_estado",NETWORKDAYS(S61,TODAY(),{"02/04/2026";"03/04/2026";"30/06/2026"}))),"-") -> 13 | U61: Contrato | V61: N° 043-2026-EF/43.03 | W61: 46216 | X61: GTD PERÚ S.A. | Y61: Elliot Hans Lindo Claudet | Z61: =IFERROR(IF(Q61="-","-",IF(Q61="Proceso de implementación/Activación/Entrega","Proceso de implementación/Activación/Entrega",IF(OR(Q61="Desistido",Q61="No corresponde atención OGTI",Q61="Para reformulación"),Q61,IF(AND(Q61="Ejecutado",AA61="No aplica",AB61="No Aplica"),"Culminado",IF(Q61="Ejecutado",IF(AND(AC61="-",G61="Bienes"),"Culminado",IF(AC61="-","Falta informacion",IF(AND(AB61-TODAY()>=0,AB61-TODAY()<=90),"Vigente_por vencer",IF(AND(AH61<>"SI",AB61<TODAY()),"Culminado",IF(AND(AH61="SI",AB61<TODAY(),OR(AK61="Sin Registro",AL61="Sin Registro")),"Vencido",IF(AND(AH61="SI",AB61<TODAY(),AK61>AA61,AL61>AB61),"Renovado","Vigente")))))),"En tramite"))))),"-") -> Proceso de implementación/Activación/Entrega | AA61: 46217 | AB61: 46292 | AC61: =IFERROR(IF(OR(AA61="-",AA61="",AB61="-",AB61=""),"-",CONCATENATE('Seguimiento OIT'!AB61-'Seguimiento OIT'!AA61+1," dias")),"-") -> 76 dias | AD61: =IFERROR(IF(Z61="Vencido",(TODAY()-AB61)+1,"-"),"-") -> - | AE61: - | AF61: Son 69 días de implementación + 10 días del acta de activación, luego iniciaria el servicio | AG61: https://mefgobpe1.sharepoint.com/:f:/t/DireccindelaOficinadeInfraestructuraTecnolgica/IgCzqnpWYXwQRoTRJy4Ukaz-Aft5ctBNoB3Tm9DuplAl7P0?e=TbLOBC | AH61: NO | AI61: =IFERROR(IF(AH61="SI",VLOOKUP(A61,$C$4:$AL$151,15,FALSE),"-"),"Sin tramite") -> - | AJ61: =IFERROR(IF(AH61="SI",VLOOKUP(A61,$C$4:$AL$151,7,FALSE),"-"),"Sin HR") -> - | AK61: =IF(AH61="SI",IFERROR(IF(VLOOKUP(A61,$C$4:$AL$151,25,FALSE)="","Sin registro",VLOOKUP(A61,$C$4:$AL$151,25,FALSE)),"Sin registro"),"-") -> - | AL61: =IF(AH61="SI",IFERROR(IF(VLOOKUP(A61,$C$4:$AL$151,26,FALSE)="","Sin registro",VLOOKUP(A61,$C$4:$AL$151,26,FALSE)),"Sin registro"),"-") -> -
A62: REQ-2026-0059 | B62: =IF(OR(Q62="Desistido",Q62="No corresponde Atención OGTI",Q62="Para reformulación",Q62="Paralizado",Q62="-",Z62="Renovado",AND(AH62="NO",Z62="Culminado")),"NO","SI") -> SI | C62: REQ-2026-0058 | D62: 2026 | E62: Contratación Directa | F62: Complementario | G62: Servicios | H62: Servicio de Transmisión de datos para los CONECTAMEF A Nivel Nacional -ITEM N° 2: Servicio de Transmisión de datos para los CONECTAMEF A Nivel Nacional- COMPLEMENTARIO | I62: 043898-2026 | J62: Transmisión de datos- CONECTAMEF a nivel nacional- Item 2 Secundario COMPLEMENTARIO | K62: Redes y Comunicaciones | L62: Elliot Hans Lindo Claudet | M62: Elliot Hans Lindo Claudet | N62: Oficina de Infraestructura Tecnológica | O62: 713553.55 | P62: 46079 | Q62: Ejecutado | R62: - | S62: 46121 | T62: =IFERROR(IF(OR(Q62="Ejecutado",Q62="No corresponde atención OGTI",Q62="Desistido",Q62="-",Q62="Para reformulación"),"-",IF(OR(S62="-",S62=""),"Falta fecha_estado",NETWORKDAYS(S62,TODAY(),{"02/04/2026";"03/04/2026";"30/06/2026"}))),"-") -> - | U62: Contrato | V62: N.º 014-2026-EF/43.03 | W62: 46108 | X62: GTD PERÚ S.A. | Y62: Elliot Hans Lindo Claudet | Z62: =IFERROR(IF(Q62="-","-",IF(Q62="Proceso de implementación/Activación/Entrega","Proceso de implementación/Activación/Entrega",IF(OR(Q62="Desistido",Q62="No corresponde atención OGTI",Q62="Para reformulación"),Q62,IF(AND(Q62="Ejecutado",AA62="No aplica",AB62="No Aplica"),"Culminado",IF(Q62="Ejecutado",IF(AND(AC62="-",G62="Bienes"),"Culminado",IF(AC62="-","Falta informacion",IF(AND(AB62-TODAY()>=0,AB62-TODAY()<=90),"Vigente_por vencer",IF(AND(AH62<>"SI",AB62<TODAY()),"Culminado",IF(AND(AH62="SI",AB62<TODAY(),OR(AK62="Sin Registro",AL62="Sin Registro")),"Vencido",IF(AND(AH62="SI",AB62<TODAY(),AK62>AA62,AL62>AB62),"Renovado","Vigente")))))),"En tramite"))))),"-") -> Vigente | AA62: 46109 | AB62: 46328 | AC62: =IFERROR(IF(OR(AA62="-",AA62="",AB62="-",AB62=""),"-",CONCATENATE('Seguimiento OIT'!AB62-'Seguimiento OIT'!AA62+1," dias")),"-") -> 220 dias | AD62: =IFERROR(IF(Z62="Vencido",(TODAY()-AB62)+1,"-"),"-") -> - | AE62: - | AF62: CONTRATACIÓN COMPLEMENTARIA: CONTRATO N° 101-2023-EF/43.03 | AG62: REQ-2026-0059- Transm. datos CONECTAMEF(complementario) | AH62: NO | AI62: =IFERROR(IF(AH62="SI",VLOOKUP(A62,$C$4:$AL$151,15,FALSE),"-"),"Sin tramite") -> - | AJ62: =IFERROR(IF(AH62="SI",VLOOKUP(A62,$C$4:$AL$151,7,FALSE),"-"),"Sin HR") -> - | AK62: =IF(AH62="SI",IFERROR(IF(VLOOKUP(A62,$C$4:$AL$151,25,FALSE)="","Sin registro",VLOOKUP(A62,$C$4:$AL$151,25,FALSE)),"Sin registro"),"-") -> - | AL62: =IF(AH62="SI",IFERROR(IF(VLOOKUP(A62,$C$4:$AL$151,26,FALSE)="","Sin registro",VLOOKUP(A62,$C$4:$AL$151,26,FALSE)),"Sin registro"),"-") -> -
A63: REQ-2026-0060 | B63: =IF(OR(Q63="Desistido",Q63="No corresponde Atención OGTI",Q63="Para reformulación",Q63="Paralizado",Q63="-",Z63="Renovado",AND(AH63="NO",Z63="Culminado")),"NO","SI") -> SI | C63: - | D63: NO | E63: Procesos de Contratación | F63: Renovación | G63: Servicios | H63: Servicio de suscripción de licencias de software para la creación, diseño y edición de gráficos, audio y video de la marca adobe creative cloud | I63: 158572-2025 | J63: Adobe Creative Cloud Pro for teams | K63: Jefatura OIT | L63: José Romucho Sotelo | M63: José Romucho Sotelo | N63: Oficina de Comunicaciones | O63: 111647 | P63: 45876 | Q63: Ejecutado | R63: - | S63: - | T63: =IFERROR(IF(OR(Q63="Ejecutado",Q63="No corresponde atención OGTI",Q63="Desistido",Q63="-",Q63="Para reformulación"),"-",IF(OR(S63="-",S63=""),"Falta fecha_estado",NETWORKDAYS(S63,TODAY(),{"02/04/2026";"03/04/2026";"30/06/2026"}))),"-") -> - | U63: Contrato | V63: 093-2025-EF/43.03 | W63: 46344 | X63: DATA CLOUD TECHNOLOGY S.A.C. | Y63: José Romucho Sotelo | Z63: =IFERROR(IF(Q63="-","-",IF(Q63="Proceso de implementación/Activación/Entrega","Proceso de implementación/Activación/Entrega",IF(OR(Q63="Desistido",Q63="No corresponde atención OGTI",Q63="Para reformulación"),Q63,IF(AND(Q63="Ejecutado",AA63="No aplica",AB63="No Aplica"),"Culminado",IF(Q63="Ejecutado",IF(AND(AC63="-",G63="Bienes"),"Culminado",IF(AC63="-","Falta informacion",IF(AND(AB63-TODAY()>=0,AB63-TODAY()<=90),"Vigente_por vencer",IF(AND(AH63<>"SI",AB63<TODAY()),"Culminado",IF(AND(AH63="SI",AB63<TODAY(),OR(AK63="Sin Registro",AL63="Sin Registro")),"Vencido",IF(AND(AH63="SI",AB63<TODAY(),AK63>AA63,AL63>AB63),"Renovado","Vigente")))))),"En tramite"))))),"-") -> Vigente | AA63: 45980 | AB63: 46344 | AC63: =IFERROR(IF(OR(AA63="-",AA63="",AB63="-",AB63=""),"-",CONCATENATE('Seguimiento OIT'!AB63-'Seguimiento OIT'!AA63+1," dias")),"-") -> 365 dias | AD63: =IFERROR(IF(Z63="Vencido",(TODAY()-AB63)+1,"-"),"-") -> - | AE63: - | AF63: HR de conformidad 241293-2025 / 247184-2025 | AG63: https://mefgobpe1.sharepoint.com/:f:/t/DireccindelaOficinadeInfraestructuraTecnolgica/IgBtK6uPW3S7SZhwksSHI3nJAdWej7VDdzuGOMEHsdLr9CA?e=fCIs7m | AH63: NO | AI63: =IFERROR(IF(AH63="SI",VLOOKUP(A63,$C$4:$AL$151,15,FALSE),"-"),"Sin tramite") -> - | AJ63: =IFERROR(IF(AH63="SI",VLOOKUP(A63,$C$4:$AL$151,7,FALSE),"-"),"Sin HR") -> - | AK63: =IF(AH63="SI",IFERROR(IF(VLOOKUP(A63,$C$4:$AL$151,25,FALSE)="","Sin registro",VLOOKUP(A63,$C$4:$AL$151,25,FALSE)),"Sin registro"),"-") -> - | AL63: =IF(AH63="SI",IFERROR(IF(VLOOKUP(A63,$C$4:$AL$151,26,FALSE)="","Sin registro",VLOOKUP(A63,$C$4:$AL$151,26,FALSE)),"Sin registro"),"-") -> -
A64: REQ-2026-0061 | B64: =IF(OR(Q64="Desistido",Q64="No corresponde Atención OGTI",Q64="Para reformulación",Q64="Paralizado",Q64="-",Z64="Renovado",AND(AH64="NO",Z64="Culminado")),"NO","SI") -> SI | C64: - | D64: NO | E64: Contratación Directa | F64: Nuevo requerimiento | G64: Servicios | H64: Servicio de suscripción de licencias de Software de análisis y visualización de datos estadísticos basados en inteligencia de negocios para el MEF. | I64: 178898-2025 | J64: Power BI Premium (04 Unidades) | K64: Jefatura OIT | L64: José Romucho Sotelo | M64: Ronald Yrupailla Diaz | N64: Oficina General de Tecnologías de la Información | O64: 4625.6 | P64: 45904 | Q64: Ejecutado | R64: - | S64: - | T64: =IFERROR(IF(OR(Q64="Ejecutado",Q64="No corresponde atención OGTI",Q64="Desistido",Q64="-",Q64="Para reformulación"),"-",IF(OR(S64="-",S64=""),"Falta fecha_estado",NETWORKDAYS(S64,TODAY(),{"02/04/2026";"03/04/2026";"30/06/2026"}))),"-") -> - | U64: Orden de Servicio | V64: 0003795-2025 | W64: 45917 | X64: ARGOSYSTEMS PERU S.R.L. | Y64: José Romucho Sotelo | Z64: =IFERROR(IF(Q64="-","-",IF(Q64="Proceso de implementación/Activación/Entrega","Proceso de implementación/Activación/Entrega",IF(OR(Q64="Desistido",Q64="No corresponde atención OGTI",Q64="Para reformulación"),Q64,IF(AND(Q64="Ejecutado",AA64="No aplica",AB64="No Aplica"),"Culminado",IF(Q64="Ejecutado",IF(AND(AC64="-",G64="Bienes"),"Culminado",IF(AC64="-","Falta informacion",IF(AND(AB64-TODAY()>=0,AB64-TODAY()<=90),"Vigente_por vencer",IF(AND(AH64<>"SI",AB64<TODAY()),"Culminado",IF(AND(AH64="SI",AB64<TODAY(),OR(AK64="Sin Registro",AL64="Sin Registro")),"Vencido",IF(AND(AH64="SI",AB64<TODAY(),AK64>AA64,AL64>AB64),"Renovado","Vigente")))))),"En tramite"))))),"-") -> Vigente_por vencer | AA64: 45918 | AB64: 46282 | AC64: =IFERROR(IF(OR(AA64="-",AA64="",AB64="-",AB64=""),"-",CONCATENATE('Seguimiento OIT'!AB64-'Seguimiento OIT'!AA64+1," dias")),"-") -> 365 dias | AD64: =IFERROR(IF(Z64="Vencido",(TODAY()-AB64)+1,"-"),"-") -> - | AE64: - | AF64: HR de conformidad 198009-2025 / 197203-2025 | AG64: https://mefgobpe1.sharepoint.com/:f:/t/DireccindelaOficinadeInfraestructuraTecnolgica/IgAEewIqEfzdT7p2uxd-rSgwAam28LF-LGdBOGV8EOP4pMc?e=vDKb8S | AH64: NO | AI64: =IFERROR(IF(AH64="SI",VLOOKUP(A64,$C$4:$AL$151,15,FALSE),"-"),"Sin tramite") -> - | AJ64: =IFERROR(IF(AH64="SI",VLOOKUP(A64,$C$4:$AL$151,7,FALSE),"-"),"Sin HR") -> - | AK64: =IF(AH64="SI",IFERROR(IF(VLOOKUP(A64,$C$4:$AL$151,25,FALSE)="","Sin registro",VLOOKUP(A64,$C$4:$AL$151,25,FALSE)),"Sin registro"),"-") -> - | AL64: =IF(AH64="SI",IFERROR(IF(VLOOKUP(A64,$C$4:$AL$151,26,FALSE)="","Sin registro",VLOOKUP(A64,$C$4:$AL$151,26,FALSE)),"Sin registro"),"-") -> -
A65: REQ-2026-0062 | B65: =IF(OR(Q65="Desistido",Q65="No corresponde Atención OGTI",Q65="Para reformulación",Q65="Paralizado",Q65="-",Z65="Renovado",AND(AH65="NO",Z65="Culminado")),"NO","SI") -> SI | C65: - | D65: NO | E65: Contratación Directa | F65: Nuevo requerimiento | G65: Servicios | H65: Servicio de suscripción de licencias de Software de análisis y visualización de datos estadísticos basados en inteligencia de negocios para el MEF. | I65: 196585-2025 | J65: Power BI Premium (32 Unidades) | K65: Jefatura OIT | L65: Carlos Joet Ortiz Alberca | M65: Julio Arturo Molina Garate | N65: Oficina de Gobierno de TI | O65: 35872 | P65: 45945 | Q65: Ejecutado | R65: - | S65: - | T65: =IFERROR(IF(OR(Q65="Ejecutado",Q65="No corresponde atención OGTI",Q65="Desistido",Q65="-",Q65="Para reformulación"),"-",IF(OR(S65="-",S65=""),"Falta fecha_estado",NETWORKDAYS(S65,TODAY(),{"02/04/2026";"03/04/2026";"30/06/2026"}))),"-") -> - | U65: Orden de Servicio | V65: 0004381-2025 | W65: 45979 | X65: NOVENTIQ INTERNATIONAL PERU S.A.C. | Y65: Julio Arturo Molina Garate | Z65: =IFERROR(IF(Q65="-","-",IF(Q65="Proceso de implementación/Activación/Entrega","Proceso de implementación/Activación/Entrega",IF(OR(Q65="Desistido",Q65="No corresponde atención OGTI",Q65="Para reformulación"),Q65,IF(AND(Q65="Ejecutado",AA65="No aplica",AB65="No Aplica"),"Culminado",IF(Q65="Ejecutado",IF(AND(AC65="-",G65="Bienes"),"Culminado",IF(AC65="-","Falta informacion",IF(AND(AB65-TODAY()>=0,AB65-TODAY()<=90),"Vigente_por vencer",IF(AND(AH65<>"SI",AB65<TODAY()),"Culminado",IF(AND(AH65="SI",AB65<TODAY(),OR(AK65="Sin Registro",AL65="Sin Registro")),"Vencido",IF(AND(AH65="SI",AB65<TODAY(),AK65>AA65,AL65>AB65),"Renovado","Vigente")))))),"En tramite"))))),"-") -> Vigente | AA65: 45986 | AB65: 46350 | AC65: =IFERROR(IF(OR(AA65="-",AA65="",AB65="-",AB65=""),"-",CONCATENATE('Seguimiento OIT'!AB65-'Seguimiento OIT'!AA65+1," dias")),"-") -> 365 dias | AD65: =IFERROR(IF(Z65="Vencido",(TODAY()-AB65)+1,"-"),"-") -> - | AE65: - | AF65: HR Conformidad 249900-2025 | AG65: https://mefgobpe1.sharepoint.com/:f:/t/DireccindelaOficinadeInfraestructuraTecnolgica/IgATPnWtIVx9TYyaUbZxoGNrAShB4oFjXi_wDLFKkfM7rvk?e=8wdEbS | AH65: NO | AI65: =IFERROR(IF(AH65="SI",VLOOKUP(A65,$C$4:$AL$151,15,FALSE),"-"),"Sin tramite") -> - | AJ65: =IFERROR(IF(AH65="SI",VLOOKUP(A65,$C$4:$AL$151,7,FALSE),"-"),"Sin HR") -> - | AK65: =IF(AH65="SI",IFERROR(IF(VLOOKUP(A65,$C$4:$AL$151,25,FALSE)="","Sin registro",VLOOKUP(A65,$C$4:$AL$151,25,FALSE)),"Sin registro"),"-") -> - | AL65: =IF(AH65="SI",IFERROR(IF(VLOOKUP(A65,$C$4:$AL$151,26,FALSE)="","Sin registro",VLOOKUP(A65,$C$4:$AL$151,26,FALSE)),"Sin registro"),"-") -> -
A66: REQ-2026-0063 | B66: =IF(OR(Q66="Desistido",Q66="No corresponde Atención OGTI",Q66="Para reformulación",Q66="Paralizado",Q66="-",Z66="Renovado",AND(AH66="NO",Z66="Culminado")),"NO","SI") -> SI | C66: - | D66: NO | E66: Contratación Directa | F66: Renovación | G66: Servicios | H66: Servicio de Call Center Cloud para el Tribunal Fiscal | I66: 035208-2026 | J66: Call Center Cloud | K66: Telefonía | L66: Isaias Bolivar Reaño | M66: Isaias Bolivar Reaño | N66: Tribunal Fiscal | O66: 40356 | P66: 46105 | Q66: Ejecutado | R66: - | S66: - | T66: =IFERROR(IF(OR(Q66="Ejecutado",Q66="No corresponde atención OGTI",Q66="Desistido",Q66="-",Q66="Para reformulación"),"-",IF(OR(S66="-",S66=""),"Falta fecha_estado",NETWORKDAYS(S66,TODAY(),{"02/04/2026";"03/04/2026";"30/06/2026"}))),"-") -> - | U66: Contrato | V66: 009-2026-EF/43.03/CM | W66: 46193 | X66: CONVERGIA PERÚ S.A. | Y66: Isaias Bolivar Reaño | Z66: =IFERROR(IF(Q66="-","-",IF(Q66="Proceso de implementación/Activación/Entrega","Proceso de implementación/Activación/Entrega",IF(OR(Q66="Desistido",Q66="No corresponde atención OGTI",Q66="Para reformulación"),Q66,IF(AND(Q66="Ejecutado",AA66="No aplica",AB66="No Aplica"),"Culminado",IF(Q66="Ejecutado",IF(AND(AC66="-",G66="Bienes"),"Culminado",IF(AC66="-","Falta informacion",IF(AND(AB66-TODAY()>=0,AB66-TODAY()<=90),"Vigente_por vencer",IF(AND(AH66<>"SI",AB66<TODAY()),"Culminado",IF(AND(AH66="SI",AB66<TODAY(),OR(AK66="Sin Registro",AL66="Sin Registro")),"Vencido",IF(AND(AH66="SI",AB66<TODAY(),AK66>AA66,AL66>AB66),"Renovado","Vigente")))))),"En tramite"))))),"-") -> Vigente | AA66: 46213 | AB66: 46577 | AC66: =IFERROR(IF(OR(AA66="-",AA66="",AB66="-",AB66=""),"-",CONCATENATE('Seguimiento OIT'!AB66-'Seguimiento OIT'!AA66+1," dias")),"-") -> 365 dias | AD66: =IFERROR(IF(Z66="Vencido",(TODAY()-AB66)+1,"-"),"-") -> - | AE66: - | AF66: *Conformidad de implementación (HR 125846-2026) *Primer entregable 154417-2026 | AG66: https://mefgobpe1.sharepoint.com/:f:/t/DireccindelaOficinadeInfraestructuraTecnolgica/IgDqFzf3p96_TpqhIzJb69WFAcVnyOdZVks59rBK1UIX7ck?e=TVt1xq | AH66: NO | AI66: =IFERROR(IF(AH66="SI",VLOOKUP(A66,$C$4:$AL$151,15,FALSE),"-"),"Sin tramite") -> - | AJ66: =IFERROR(IF(AH66="SI",VLOOKUP(A66,$C$4:$AL$151,7,FALSE),"-"),"Sin HR") -> - | AK66: =IF(AH66="SI",IFERROR(IF(VLOOKUP(A66,$C$4:$AL$151,25,FALSE)="","Sin registro",VLOOKUP(A66,$C$4:$AL$151,25,FALSE)),"Sin registro"),"-") -> - | AL66: =IF(AH66="SI",IFERROR(IF(VLOOKUP(A66,$C$4:$AL$151,26,FALSE)="","Sin registro",VLOOKUP(A66,$C$4:$AL$151,26,FALSE)),"Sin registro"),"-") -> -
A67: REQ-2026-0064 | B67: =IF(OR(Q67="Desistido",Q67="No corresponde Atención OGTI",Q67="Para reformulación",Q67="Paralizado",Q67="-",Z67="Renovado",AND(AH67="NO",Z67="Culminado")),"NO","SI") -> SI | C67: - | D67: NO | E67: Procesos de Contratación | F67: Nuevo requerimiento | G67: Servicios | H67: Servicio de Telefonía Fija para el Ministerio de Economía y Finanzas | I67: 042873-2025 | J67: Telefonia Fija | K67: Telefonía | L67: Isaias Bolivar Reaño | M67: Isaias Bolivar Reaño | N67: Ministerio de Economía y Finanzas | O67: 137924.06 | P67: 45715 | Q67: Ejecutado | R67: - | S67: - | T67: =IFERROR(IF(OR(Q67="Ejecutado",Q67="No corresponde atención OGTI",Q67="Desistido",Q67="-",Q67="Para reformulación"),"-",IF(OR(S67="-",S67=""),"Falta fecha_estado",NETWORKDAYS(S67,TODAY(),{"02/04/2026";"03/04/2026";"30/06/2026"}))),"-") -> - | U67: Contrato | V67: 025-2025-EF/43.03 | W67: 46263 | X67: AMERICA MOVIL PERU S.A.C. | Y67: Isaias Bolivar Reaño | Z67: =IFERROR(IF(Q67="-","-",IF(Q67="Proceso de implementación/Activación/Entrega","Proceso de implementación/Activación/Entrega",IF(OR(Q67="Desistido",Q67="No corresponde atención OGTI",Q67="Para reformulación"),Q67,IF(AND(Q67="Ejecutado",AA67="No aplica",AB67="No Aplica"),"Culminado",IF(Q67="Ejecutado",IF(AND(AC67="-",G67="Bienes"),"Culminado",IF(AC67="-","Falta informacion",IF(AND(AB67-TODAY()>=0,AB67-TODAY()<=90),"Vigente_por vencer",IF(AND(AH67<>"SI",AB67<TODAY()),"Culminado",IF(AND(AH67="SI",AB67<TODAY(),OR(AK67="Sin Registro",AL67="Sin Registro")),"Vencido",IF(AND(AH67="SI",AB67<TODAY(),AK67>AA67,AL67>AB67),"Renovado","Vigente")))))),"En tramite"))))),"-") -> Vigente | AA67: 46001 | AB67: 46730 | AC67: =IFERROR(IF(OR(AA67="-",AA67="",AB67="-",AB67=""),"-",CONCATENATE('Seguimiento OIT'!AB67-'Seguimiento OIT'!AA67+1," dias")),"-") -> 730 dias | AD67: =IFERROR(IF(Z67="Vencido",(TODAY()-AB67)+1,"-"),"-") -> - | AE67: - | AF67: Conformidad 6to periodo (HR 135000-2026) | AG67: https://mefgobpe1.sharepoint.com/:f:/t/DireccindelaOficinadeInfraestructuraTecnolgica/IgA06S8IqzsVTrMJUXIyaH6VAYxFim3b8i0XgEClJ2DmMpo?e=yQUdoq | AH67: NO | AI67: =IFERROR(IF(AH67="SI",VLOOKUP(A67,$C$4:$AL$151,15,FALSE),"-"),"Sin tramite") -> - | AJ67: =IFERROR(IF(AH67="SI",VLOOKUP(A67,$C$4:$AL$151,7,FALSE),"-"),"Sin HR") -> - | AK67: =IF(AH67="SI",IFERROR(IF(VLOOKUP(A67,$C$4:$AL$151,25,FALSE)="","Sin registro",VLOOKUP(A67,$C$4:$AL$151,25,FALSE)),"Sin registro"),"-") -> - | AL67: =IF(AH67="SI",IFERROR(IF(VLOOKUP(A67,$C$4:$AL$151,26,FALSE)="","Sin registro",VLOOKUP(A67,$C$4:$AL$151,26,FALSE)),"Sin registro"),"-") -> -
A68: REQ-2026-0065 | B68: =IF(OR(Q68="Desistido",Q68="No corresponde Atención OGTI",Q68="Para reformulación",Q68="Paralizado",Q68="-",Z68="Renovado",AND(AH68="NO",Z68="Culminado")),"NO","SI") -> SI | C68: - | D68: NO | E68: Procesos de Contratación | F68: Nuevo requerimiento | G68: Bienes | H68: Adquisicion de equipos telefonicos IP MEF | I68: 099268-2026 (Recopilacion de Información) | J68: Telefonos IP | K68: Telefonía | L68: Isaias Bolivar Reaño | M68: Isaias Bolivar Reaño | N68: Ministerio de Economía y Finanzas | O68: 800000 | P68: 46147 | Q68: Sin tramitar | R68: OIT-Jefatura | S68: 46198 | T68: =IFERROR(IF(OR(Q68="Ejecutado",Q68="No corresponde atención OGTI",Q68="Desistido",Q68="-",Q68="Para reformulación"),"-",IF(OR(S68="-",S68=""),"Falta fecha_estado",NETWORKDAYS(S68,TODAY(),{"02/04/2026";"03/04/2026";"30/06/2026"}))),"-") -> 26 | U68: - | V68: - | W68: - | X68: - | Y68: - | Z68: =IFERROR(IF(Q68="-","-",IF(Q68="Proceso de implementación/Activación/Entrega","Proceso de implementación/Activación/Entrega",IF(OR(Q68="Desistido",Q68="No corresponde atención OGTI",Q68="Para reformulación"),Q68,IF(AND(Q68="Ejecutado",AA68="No aplica",AB68="No Aplica"),"Culminado",IF(Q68="Ejecutado",IF(AND(AC68="-",G68="Bienes"),"Culminado",IF(AC68="-","Falta informacion",IF(AND(AB68-TODAY()>=0,AB68-TODAY()<=90),"Vigente_por vencer",IF(AND(AH68<>"SI",AB68<TODAY()),"Culminado",IF(AND(AH68="SI",AB68<TODAY(),OR(AK68="Sin Registro",AL68="Sin Registro")),"Vencido",IF(AND(AH68="SI",AB68<TODAY(),AK68>AA68,AL68>AB68),"Renovado","Vigente")))))),"En tramite"))))),"-") -> En tramite | AA68: - | AB68: - | AC68: =IFERROR(IF(OR(AA68="-",AA68="",AB68="-",AB68=""),"-",CONCATENATE('Seguimiento OIT'!AB68-'Seguimiento OIT'!AA68+1," dias")),"-") -> - | AD68: =IFERROR(IF(Z68="Vencido",(TODAY()-AB68)+1,"-"),"-") -> - | AE68: *Con HR 099268-2026 se recopiló necesidad de area usuarias | AF68: - | AG68: https://mefgobpe1.sharepoint.com/:f:/t/DireccindelaOficinadeInfraestructuraTecnolgica/IgCryDhwWlIWRL82n3CyOgHoAay5kz3yABm4oo8TpwKpU6s?e=549TPk | AH68: NO | AI68: =IFERROR(IF(AH68="SI",VLOOKUP(A68,$C$4:$AL$151,15,FALSE),"-"),"Sin tramite") -> - | AJ68: =IFERROR(IF(AH68="SI",VLOOKUP(A68,$C$4:$AL$151,7,FALSE),"-"),"Sin HR") -> - | AK68: =IF(AH68="SI",IFERROR(IF(VLOOKUP(A68,$C$4:$AL$151,25,FALSE)="","Sin registro",VLOOKUP(A68,$C$4:$AL$151,25,FALSE)),"Sin registro"),"-") -> - | AL68: =IF(AH68="SI",IFERROR(IF(VLOOKUP(A68,$C$4:$AL$151,26,FALSE)="","Sin registro",VLOOKUP(A68,$C$4:$AL$151,26,FALSE)),"Sin registro"),"-") -> -
A69: REQ-2026-0066 | B69: =IF(OR(Q69="Desistido",Q69="No corresponde Atención OGTI",Q69="Para reformulación",Q69="Paralizado",Q69="-",Z69="Renovado",AND(AH69="NO",Z69="Culminado")),"NO","SI") -> SI | C69: - | D69: NO | E69: Contratación Directa | F69: Nuevo requerimiento (Apoyo técnico AUS) | G69: Bienes | H69: Adquisición de amplificadores de voz portátiles con micrófono inalámbrico | I69: Correo electrónico 25-06-26 | J69: Partelante portatil con Microfono | K69: Soporte Tecnico | L69: Cesar Augusto Muñoz Escalante | M69: Ronald Yrupailla Diaz | N69: Oficina General de Servicios al Usuario | O69: Pendiente | P69: 46198 | Q69: Revisión área usuaria | R69: Área Usuaria | S69: 46211 | T69: =IFERROR(IF(OR(Q69="Ejecutado",Q69="No corresponde atención OGTI",Q69="Desistido",Q69="-",Q69="Para reformulación"),"-",IF(OR(S69="-",S69=""),"Falta fecha_estado",NETWORKDAYS(S69,TODAY(),{"02/04/2026";"03/04/2026";"30/06/2026"}))),"-") -> 18 | U69: - | V69: - | W69: - | X69: - | Y69: - | Z69: =IFERROR(IF(Q69="-","-",IF(Q69="Proceso de implementación/Activación/Entrega","Proceso de implementación/Activación/Entrega",IF(OR(Q69="Desistido",Q69="No corresponde atención OGTI",Q69="Para reformulación"),Q69,IF(AND(Q69="Ejecutado",AA69="No aplica",AB69="No Aplica"),"Culminado",IF(Q69="Ejecutado",IF(AND(AC69="-",G69="Bienes"),"Culminado",IF(AC69="-","Falta informacion",IF(AND(AB69-TODAY()>=0,AB69-TODAY()<=90),"Vigente_por vencer",IF(AND(AH69<>"SI",AB69<TODAY()),"Culminado",IF(AND(AH69="SI",AB69<TODAY(),OR(AK69="Sin Registro",AL69="Sin Registro")),"Vencido",IF(AND(AH69="SI",AB69<TODAY(),AK69>AA69,AL69>AB69),"Renovado","Vigente")))))),"En tramite"))))),"-") -> En tramite | AA69: - | AB69: - | AC69: =IFERROR(IF(OR(AA69="-",AA69="",AB69="-",AB69=""),"-",CONCATENATE('Seguimiento OIT'!AB69-'Seguimiento OIT'!AA69+1," dias")),"-") -> - | AD69: =IFERROR(IF(Z69="Vencido",(TODAY()-AB69)+1,"-"),"-") -> - | AE69: *Con fecha 08-07-26 OIT remitió EETT visadas a OGSU mediante correo | AF69: - | AG69: https://mefgobpe1.sharepoint.com/:f:/t/DireccindelaOficinadeInfraestructuraTecnolgica/IgCISC5P3434QL2cRUmiD_NWAenWseAb4gJ_7QE8s7hDNeo?e=1bwG3P | AH69: NO | AI69: =IFERROR(IF(AH69="SI",VLOOKUP(A69,$C$4:$AL$151,15,FALSE),"-"),"Sin tramite") -> - | AJ69: =IFERROR(IF(AH69="SI",VLOOKUP(A69,$C$4:$AL$151,7,FALSE),"-"),"Sin HR") -> - | AK69: =IF(AH69="SI",IFERROR(IF(VLOOKUP(A69,$C$4:$AL$151,25,FALSE)="","Sin registro",VLOOKUP(A69,$C$4:$AL$151,25,FALSE)),"Sin registro"),"-") -> - | AL69: =IF(AH69="SI",IFERROR(IF(VLOOKUP(A69,$C$4:$AL$151,26,FALSE)="","Sin registro",VLOOKUP(A69,$C$4:$AL$151,26,FALSE)),"Sin registro"),"-") -> -
A70: REQ-2026-0067 | B70: =IF(OR(Q70="Desistido",Q70="No corresponde Atención OGTI",Q70="Para reformulación",Q70="Paralizado",Q70="-",Z70="Renovado",AND(AH70="NO",Z70="Culminado")),"NO","SI") -> SI | C70: - | D70: 2026 | E70: Procesos de Contratación | F70: Nuevo requerimiento | G70: Servicios | H70: Servicio de suscripción de licencias de Software de virtualización y soporte técnico de la marca VMWARE by Broadcom | I70: 009604-2026 (Requerimiento inicial) | J70: Suscripcion VMWare (1144 cores) | K70: Computo | L70: Rolly Villegas Delgado | M70: Anthony Céspedes Molina | N70: Oficina de Infraestructura Tecnológica | P70: 46038 | Q70: Sin tramitar | R70: OIT-Jefatura | S70: 46146 | T70: =IFERROR(IF(OR(Q70="Ejecutado",Q70="No corresponde atención OGTI",Q70="Desistido",Q70="-",Q70="Para reformulación"),"-",IF(OR(S70="-",S70=""),"Falta fecha_estado",NETWORKDAYS(S70,TODAY(),{"02/04/2026";"03/04/2026";"30/06/2026"}))),"-") -> 64 | U70: - | V70: - | W70: - | X70: - | Y70: - | Z70: =IFERROR(IF(Q70="-","-",IF(Q70="Proceso de implementación/Activación/Entrega","Proceso de implementación/Activación/Entrega",IF(OR(Q70="Desistido",Q70="No corresponde atención OGTI",Q70="Para reformulación"),Q70,IF(AND(Q70="Ejecutado",AA70="No aplica",AB70="No Aplica"),"Culminado",IF(Q70="Ejecutado",IF(AND(AC70="-",G70="Bienes"),"Culminado",IF(AC70="-","Falta informacion",IF(AND(AB70-TODAY()>=0,AB70-TODAY()<=90),"Vigente_por vencer",IF(AND(AH70<>"SI",AB70<TODAY()),"Culminado",IF(AND(AH70="SI",AB70<TODAY(),OR(AK70="Sin Registro",AL70="Sin Registro")),"Vencido",IF(AND(AH70="SI",AB70<TODAY(),AK70>AA70,AL70>AB70),"Renovado","Vigente")))))),"En tramite"))))),"-") -> En tramite | AA70: - | AB70: - | AC70: =IFERROR(IF(OR(AA70="-",AA70="",AB70="-",AB70=""),"-",CONCATENATE('Seguimiento OIT'!AB70-'Seguimiento OIT'!AA70+1," dias")),"-") -> - | AD70: =IFERROR(IF(Z70="Vencido",(TODAY()-AB70)+1,"-"),"-") -> - | AE70: No se continuó con contratación por falta de presupuesto | AF70: - | AG70: https://mefgobpe1.sharepoint.com/:f:/t/DireccindelaOficinadeInfraestructuraTecnolgica/IgARXzrnIH60T50VMCHG14aIAcThDyGkT2wZE686IqHqDAk?e=vGr0AS | AH70: NO | AI70: =IFERROR(IF(AH70="SI",VLOOKUP(A70,$C$4:$AL$151,15,FALSE),"-"),"Sin tramite") -> - | AJ70: =IFERROR(IF(AH70="SI",VLOOKUP(A70,$C$4:$AL$151,7,FALSE),"-"),"Sin HR") -> - | AK70: =IF(AH70="SI",IFERROR(IF(VLOOKUP(A70,$C$4:$AL$151,25,FALSE)="","Sin registro",VLOOKUP(A70,$C$4:$AL$151,25,FALSE)),"Sin registro"),"-") -> - | AL70: =IF(AH70="SI",IFERROR(IF(VLOOKUP(A70,$C$4:$AL$151,26,FALSE)="","Sin registro",VLOOKUP(A70,$C$4:$AL$151,26,FALSE)),"Sin registro"),"-") -> -
A71: REQ-2026-0068 | B71: =IF(OR(Q71="Desistido",Q71="No corresponde Atención OGTI",Q71="Para reformulación",Q71="Paralizado",Q71="-",Z71="Renovado",AND(AH71="NO",Z71="Culminado")),"NO","SI") -> SI | C71: - | D71: NO | E71: Procesos de Contratación | F71: Nuevo requerimiento | G71: Servicios | H71: Servicio de respaldo en nube para entornos Office 365 | I71: *009518-2026 (Requerimiento Inicial v2) *158566-2025 (Requerimiento Inicial v1) | J71: Acronis / VeamBackup 365 | K71: Computo | L71: Rolly Villegas Delgado | M71: Willinhton Walter De la Cruz Pinedo | N71: Oficina de Infraestructura Tecnológica | O71: Pendiente | P71: 46037 | Q71: Sin tramitar | R71: OIT-Jefatura | S71: 46091 | T71: =IFERROR(IF(OR(Q71="Ejecutado",Q71="No corresponde atención OGTI",Q71="Desistido",Q71="-",Q71="Para reformulación"),"-",IF(OR(S71="-",S71=""),"Falta fecha_estado",NETWORKDAYS(S71,TODAY(),{"02/04/2026";"03/04/2026";"30/06/2026"}))),"-") -> 101 | U71: - | V71: - | W71: - | X71: - | Y71: - | Z71: =IFERROR(IF(Q71="-","-",IF(Q71="Proceso de implementación/Activación/Entrega","Proceso de implementación/Activación/Entrega",IF(OR(Q71="Desistido",Q71="No corresponde atención OGTI",Q71="Para reformulación"),Q71,IF(AND(Q71="Ejecutado",AA71="No aplica",AB71="No Aplica"),"Culminado",IF(Q71="Ejecutado",IF(AND(AC71="-",G71="Bienes"),"Culminado",IF(AC71="-","Falta informacion",IF(AND(AB71-TODAY()>=0,AB71-TODAY()<=90),"Vigente_por vencer",IF(AND(AH71<>"SI",AB71<TODAY()),"Culminado",IF(AND(AH71="SI",AB71<TODAY(),OR(AK71="Sin Registro",AL71="Sin Registro")),"Vencido",IF(AND(AH71="SI",AB71<TODAY(),AK71>AA71,AL71>AB71),"Renovado","Vigente")))))),"En tramite"))))),"-") -> En tramite | AA71: - | AB71: - | AC71: =IFERROR(IF(OR(AA71="-",AA71="",AB71="-",AB71=""),"-",CONCATENATE('Seguimiento OIT'!AB71-'Seguimiento OIT'!AA71+1," dias")),"-") -> - | AD71: =IFERROR(IF(Z71="Vencido",(TODAY()-AB71)+1,"-"),"-") -> - | AE71: No se continuó con contratación por falta de presupuesto | AF71: - | AG71: https://mefgobpe1.sharepoint.com/:f:/t/DireccindelaOficinadeInfraestructuraTecnolgica/IgCgcRC8W-wMTq6ekZb_lSpLAeDJFqC-bcRW_kCo81Z8vlQ?e=JwNwPp | AH71: NO | AI71: =IFERROR(IF(AH71="SI",VLOOKUP(A71,$C$4:$AL$151,15,FALSE),"-"),"Sin tramite") -> - | AJ71: =IFERROR(IF(AH71="SI",VLOOKUP(A71,$C$4:$AL$151,7,FALSE),"-"),"Sin HR") -> - | AK71: =IF(AH71="SI",IFERROR(IF(VLOOKUP(A71,$C$4:$AL$151,25,FALSE)="","Sin registro",VLOOKUP(A71,$C$4:$AL$151,25,FALSE)),"Sin registro"),"-") -> - | AL71: =IF(AH71="SI",IFERROR(IF(VLOOKUP(A71,$C$4:$AL$151,26,FALSE)="","Sin registro",VLOOKUP(A71,$C$4:$AL$151,26,FALSE)),"Sin registro"),"-") -> -
A72: REQ-2026-0069 | B72: =IF(OR(Q72="Desistido",Q72="No corresponde Atención OGTI",Q72="Para reformulación",Q72="Paralizado",Q72="-",Z72="Renovado",AND(AH72="NO",Z72="Culminado")),"NO","SI") -> SI | C72: - | D72: 2026 | E72: Procesos de Contratación | F72: Nuevo requerimiento | G72: Servicios | H72: Servicio de garantía extendida y soporte técnico para el equipamiento y software de la marca IBM de los Centros de Procesamiento de Datos del Ministerio de Economía y Finanzas | I72: 009025-2026 (Requerimiento inicial) | J72: Garantia Extendida y soporte técnico IBM | K72: Computo | L72: Rolly Villegas Delgado | M72: Anthony Céspedes Molina | N72: Oficina de Infraestructura Tecnológica | O72: Pendiente | P72: 46037 | Q72: Revisión área usuaria | R72: OIT-Computo | S72: 46223 | T72: =IFERROR(IF(OR(Q72="Ejecutado",Q72="No corresponde atención OGTI",Q72="Desistido",Q72="-",Q72="Para reformulación"),"-",IF(OR(S72="-",S72=""),"Falta fecha_estado",NETWORKDAYS(S72,TODAY(),{"02/04/2026";"03/04/2026";"30/06/2026"}))),"-") -> 10 | U72: - | V72: - | W72: - | X72: - | Y72: - | Z72: =IFERROR(IF(Q72="-","-",IF(Q72="Proceso de implementación/Activación/Entrega","Proceso de implementación/Activación/Entrega",IF(OR(Q72="Desistido",Q72="No corresponde atención OGTI",Q72="Para reformulación"),Q72,IF(AND(Q72="Ejecutado",AA72="No aplica",AB72="No Aplica"),"Culminado",IF(Q72="Ejecutado",IF(AND(AC72="-",G72="Bienes"),"Culminado",IF(AC72="-","Falta informacion",IF(AND(AB72-TODAY()>=0,AB72-TODAY()<=90),"Vigente_por vencer",IF(AND(AH72<>"SI",AB72<TODAY()),"Culminado",IF(AND(AH72="SI",AB72<TODAY(),OR(AK72="Sin Registro",AL72="Sin Registro")),"Vencido",IF(AND(AH72="SI",AB72<TODAY(),AK72>AA72,AL72>AB72),"Renovado","Vigente")))))),"En tramite"))))),"-") -> En tramite | AA72: - | AB72: - | AC72: =IFERROR(IF(OR(AA72="-",AA72="",AB72="-",AB72=""),"-",CONCATENATE('Seguimiento OIT'!AB72-'Seguimiento OIT'!AA72+1," dias")),"-") -> - | AD72: =IFERROR(IF(Z72="Vencido",(TODAY()-AB72)+1,"-"),"-") -> - | AE72: Se realizará una nueva convocatoria según Memo Circular N° 0043-2026 | AF72: - | AG72: https://mefgobpe1.sharepoint.com/:f:/t/DireccindelaOficinadeInfraestructuraTecnolgica/IgDtya5wjZvOQrpwSRq7ahDIAaLQooeG3qKCmqho78GFs2o?e=qsBxDo | AH72: NO | AI72: =IFERROR(IF(AH72="SI",VLOOKUP(A72,$C$4:$AL$151,15,FALSE),"-"),"Sin tramite") -> - | AJ72: =IFERROR(IF(AH72="SI",VLOOKUP(A72,$C$4:$AL$151,7,FALSE),"-"),"Sin HR") -> - | AK72: =IF(AH72="SI",IFERROR(IF(VLOOKUP(A72,$C$4:$AL$151,25,FALSE)="","Sin registro",VLOOKUP(A72,$C$4:$AL$151,25,FALSE)),"Sin registro"),"-") -> - | AL72: =IF(AH72="SI",IFERROR(IF(VLOOKUP(A72,$C$4:$AL$151,26,FALSE)="","Sin registro",VLOOKUP(A72,$C$4:$AL$151,26,FALSE)),"Sin registro"),"-") -> -
A73: REQ-2026-0070 | B73: =IF(OR(Q73="Desistido",Q73="No corresponde Atención OGTI",Q73="Para reformulación",Q73="Paralizado",Q73="-",Z73="Renovado",AND(AH73="NO",Z73="Culminado")),"NO","SI") -> SI | C73: - | D73: 2026 | E73: Procesos de Contratación | F73: Nuevo requerimiento | G73: Servicios | H73: Servicio de garantía extendida y soporte técnico para el equipamiento y software de la marca LENOVO de los Centros de Procesamiento de Datos del Ministerio de Economía y Finanzas | I73: *009138-2026 (Requerimiento) *135916-2026 (Revision Contrato) | J73: Garantia Extendida y soporte técnico Lenovo | K73: Computo | L73: Rolly Villegas Delgado | M73: Anthony Céspedes Molina | N73: Oficina de Infraestructura Tecnológica | O73: 259738 | P73: 46038 | Q73: Ejecutado | R73: - | S73: - | T73: =IFERROR(IF(OR(Q73="Ejecutado",Q73="No corresponde atención OGTI",Q73="Desistido",Q73="-",Q73="Para reformulación"),"-",IF(OR(S73="-",S73=""),"Falta fecha_estado",NETWORKDAYS(S73,TODAY(),{"02/04/2026";"03/04/2026";"30/06/2026"}))),"-") -> - | U73: Contrato | V73: 037-2026-EF/43.03 | W73: 46197 | X73: GRUPO SYPSA S.A.C. | Y73: Anthony Céspedes Molina | Z73: =IFERROR(IF(Q73="-","-",IF(Q73="Proceso de implementación/Activación/Entrega","Proceso de implementación/Activación/Entrega",IF(OR(Q73="Desistido",Q73="No corresponde atención OGTI",Q73="Para reformulación"),Q73,IF(AND(Q73="Ejecutado",AA73="No aplica",AB73="No Aplica"),"Culminado",IF(Q73="Ejecutado",IF(AND(AC73="-",G73="Bienes"),"Culminado",IF(AC73="-","Falta informacion",IF(AND(AB73-TODAY()>=0,AB73-TODAY()<=90),"Vigente_por vencer",IF(AND(AH73<>"SI",AB73<TODAY()),"Culminado",IF(AND(AH73="SI",AB73<TODAY(),OR(AK73="Sin Registro",AL73="Sin Registro")),"Vencido",IF(AND(AH73="SI",AB73<TODAY(),AK73>AA73,AL73>AB73),"Renovado","Vigente")))))),"En tramite"))))),"-") -> Vigente | AA73: 46204 | AB73: 46568 | AC73: =IFERROR(IF(OR(AA73="-",AA73="",AB73="-",AB73=""),"-",CONCATENATE('Seguimiento OIT'!AB73-'Seguimiento OIT'!AA73+1," dias")),"-") -> 365 dias | AD73: =IFERROR(IF(Z73="Vencido",(TODAY()-AB73)+1,"-"),"-") -> - | AE73: *HR 135916-2026 (Remision de contrato) *Fecha maxima de activación de servicio 14-07-26 | AF73: - | AG73: https://mefgobpe1.sharepoint.com/:f:/t/DireccindelaOficinadeInfraestructuraTecnolgica/IgCJvVR_i2E3TqrTRjmHWYTAAU3UGXcMVcMOZXjAFDZVMQQ?e=aGZlCY | AH73: NO | AI73: =IFERROR(IF(AH73="SI",VLOOKUP(A73,$C$4:$AL$151,15,FALSE),"-"),"Sin tramite") -> - | AJ73: =IFERROR(IF(AH73="SI",VLOOKUP(A73,$C$4:$AL$151,7,FALSE),"-"),"Sin HR") -> - | AK73: =IF(AH73="SI",IFERROR(IF(VLOOKUP(A73,$C$4:$AL$151,25,FALSE)="","Sin registro",VLOOKUP(A73,$C$4:$AL$151,25,FALSE)),"Sin registro"),"-") -> - | AL73: =IF(AH73="SI",IFERROR(IF(VLOOKUP(A73,$C$4:$AL$151,26,FALSE)="","Sin registro",VLOOKUP(A73,$C$4:$AL$151,26,FALSE)),"Sin registro"),"-") -> -
A74: REQ-2026-0071 | B74: =IF(OR(Q74="Desistido",Q74="No corresponde Atención OGTI",Q74="Para reformulación",Q74="Paralizado",Q74="-",Z74="Renovado",AND(AH74="NO",Z74="Culminado")),"NO","SI") -> SI | C74: - | D74: 2026 | E74: Procesos de Contratación | F74: Nuevo requerimiento | G74: Servicios | H74: Servicio de notificaciones masivas a través de la plataforma de comunicaciones en nube de la marca INFOBIP | I74: 009170-2026 (Requerimiento) | J74: INFOBIP (Email, SMS, Ips, numero corto y soporte) | K74: Computo | L74: Rolly Villegas Delgado | M74: Edgar Hernández Sandoval | N74: Oficina de Infraestructura Tecnológica | O74: 300000 | P74: 46037 | Q74: Ejecutado | R74: - | S74: - | T74: =IFERROR(IF(OR(Q74="Ejecutado",Q74="No corresponde atención OGTI",Q74="Desistido",Q74="-",Q74="Para reformulación"),"-",IF(OR(S74="-",S74=""),"Falta fecha_estado",NETWORKDAYS(S74,TODAY(),{"02/04/2026";"03/04/2026";"30/06/2026"}))),"-") -> - | U74: Contrato | V74: 029-2026-EF/43.03 | W74: 46171 | X74: ENTEL PERU S.A. | Y74: Rolly Villegas Delgado | Z74: =IFERROR(IF(Q74="-","-",IF(Q74="Proceso de implementación/Activación/Entrega","Proceso de implementación/Activación/Entrega",IF(OR(Q74="Desistido",Q74="No corresponde atención OGTI",Q74="Para reformulación"),Q74,IF(AND(Q74="Ejecutado",AA74="No aplica",AB74="No Aplica"),"Culminado",IF(Q74="Ejecutado",IF(AND(AC74="-",G74="Bienes"),"Culminado",IF(AC74="-","Falta informacion",IF(AND(AB74-TODAY()>=0,AB74-TODAY()<=90),"Vigente_por vencer",IF(AND(AH74<>"SI",AB74<TODAY()),"Culminado",IF(AND(AH74="SI",AB74<TODAY(),OR(AK74="Sin Registro",AL74="Sin Registro")),"Vencido",IF(AND(AH74="SI",AB74<TODAY(),AK74>AA74,AL74>AB74),"Renovado","Vigente")))))),"En tramite"))))),"-") -> Vigente | AA74: 46220 | AB74: 46939 | AC74: =IFERROR(IF(OR(AA74="-",AA74="",AB74="-",AB74=""),"-",CONCATENATE('Seguimiento OIT'!AB74-'Seguimiento OIT'!AA74+1," dias")),"-") -> 720 dias | AD74: =IFERROR(IF(Z74="Vencido",(TODAY()-AB74)+1,"-"),"-") -> - | AE74: - | AF74: - | AG74: https://mefgobpe1.sharepoint.com/:f:/t/DireccindelaOficinadeInfraestructuraTecnolgica/IgBcfKaQe5wET66chWXXDkXQAfpJxinlTvEBOEqBY1P8uhs?e=mddoCs | AH74: NO | AI74: =IFERROR(IF(AH74="SI",VLOOKUP(A74,$C$4:$AL$151,15,FALSE),"-"),"Sin tramite") -> - | AJ74: =IFERROR(IF(AH74="SI",VLOOKUP(A74,$C$4:$AL$151,7,FALSE),"-"),"Sin HR") -> - | AK74: =IF(AH74="SI",IFERROR(IF(VLOOKUP(A74,$C$4:$AL$151,25,FALSE)="","Sin registro",VLOOKUP(A74,$C$4:$AL$151,25,FALSE)),"Sin registro"),"-") -> - | AL74: =IF(AH74="SI",IFERROR(IF(VLOOKUP(A74,$C$4:$AL$151,26,FALSE)="","Sin registro",VLOOKUP(A74,$C$4:$AL$151,26,FALSE)),"Sin registro"),"-") -> -
A75: REQ-2026-0072 | B75: =IF(OR(Q75="Desistido",Q75="No corresponde Atención OGTI",Q75="Para reformulación",Q75="Paralizado",Q75="-",Z75="Renovado",AND(AH75="NO",Z75="Culminado")),"NO","SI") -> SI | C75: - | D75: NO | E75: Procesos de Contratación | F75: Nuevo requerimiento | G75: Servicios | H75: Servicio de soporte especializado para la solución de protección de base de datos Oracle | I75: 015123-2026 (Requerimiento) | J75: Soporte Zero Data Loss Recovery Appliance (ZDLRA) (100 horas) | K75: Computo | L75: Rolly Villegas Delgado | M75: Lidia Tinco Rojas | N75: Oficina de Infraestructura Tecnológica | O75: 43950.25 | P75: 46057 | Q75: Ejecutado | R75: - | S75: - | T75: =IFERROR(IF(OR(Q75="Ejecutado",Q75="No corresponde atención OGTI",Q75="Desistido",Q75="-",Q75="Para reformulación"),"-",IF(OR(S75="-",S75=""),"Falta fecha_estado",NETWORKDAYS(S75,TODAY(),{"02/04/2026";"03/04/2026";"30/06/2026"}))),"-") -> - | U75: Orden de Servicio | V75: 0001421-2026 | W75: 46099 | X75: VALMER SYSTEMS S.A.C. | Y75: Lidia Tinco Rojas | Z75: =IFERROR(IF(Q75="-","-",IF(Q75="Proceso de implementación/Activación/Entrega","Proceso de implementación/Activación/Entrega",IF(OR(Q75="Desistido",Q75="No corresponde atención OGTI",Q75="Para reformulación"),Q75,IF(AND(Q75="Ejecutado",AA75="No aplica",AB75="No Aplica"),"Culminado",IF(Q75="Ejecutado",IF(AND(AC75="-",G75="Bienes"),"Culminado",IF(AC75="-","Falta informacion",IF(AND(AB75-TODAY()>=0,AB75-TODAY()<=90),"Vigente_por vencer",IF(AND(AH75<>"SI",AB75<TODAY()),"Culminado",IF(AND(AH75="SI",AB75<TODAY(),OR(AK75="Sin Registro",AL75="Sin Registro")),"Vencido",IF(AND(AH75="SI",AB75<TODAY(),AK75>AA75,AL75>AB75),"Renovado","Vigente")))))),"En tramite"))))),"-") -> Vigente | AA75: 46107 | AB75: 46376 | AC75: =IFERROR(IF(OR(AA75="-",AA75="",AB75="-",AB75=""),"-",CONCATENATE('Seguimiento OIT'!AB75-'Seguimiento OIT'!AA75+1," dias")),"-") -> 270 dias | AD75: =IFERROR(IF(Z75="Vencido",(TODAY()-AB75)+1,"-"),"-") -> - | AE75: - | AF75: - | AG75: https://mefgobpe1.sharepoint.com/:f:/t/DireccindelaOficinadeInfraestructuraTecnolgica/IgBR4lvj-uB6S7Y0W925_VQ1AaYFbVA7f4ZgU2Iu9i5IpjM?e=2X5gHQ | AH75: NO | AI75: =IFERROR(IF(AH75="SI",VLOOKUP(A75,$C$4:$AL$151,15,FALSE),"-"),"Sin tramite") -> - | AJ75: =IFERROR(IF(AH75="SI",VLOOKUP(A75,$C$4:$AL$151,7,FALSE),"-"),"Sin HR") -> - | AK75: =IF(AH75="SI",IFERROR(IF(VLOOKUP(A75,$C$4:$AL$151,25,FALSE)="","Sin registro",VLOOKUP(A75,$C$4:$AL$151,25,FALSE)),"Sin registro"),"-") -> - | AL75: =IF(AH75="SI",IFERROR(IF(VLOOKUP(A75,$C$4:$AL$151,26,FALSE)="","Sin registro",VLOOKUP(A75,$C$4:$AL$151,26,FALSE)),"Sin registro"),"-") -> -
A76: REQ-2026-0073 | B76: =IF(OR(Q76="Desistido",Q76="No corresponde Atención OGTI",Q76="Para reformulación",Q76="Paralizado",Q76="-",Z76="Renovado",AND(AH76="NO",Z76="Culminado")),"NO","SI") -> SI | C76: - | D76: 2026 | E76: Procesos de Contratación | F76: Nuevo requerimiento | G76: Servicios | H76: Servicio de garantía extendida y soporte técnico para el equipamiento de la marca CISCO de los Centros de Procesamiento de Datos del Ministerio de Economía y Finanzas | I76: 009305-2026 (Requerimiento) | J76: Garantia Extendida y soporte técnico CISCO | K76: Computo | L76: Rolly Villegas Delgado | M76: Anthony Céspedes Molina | N76: Oficina de Infraestructura Tecnológica | O76: 287400 | P76: 46038 | Q76: Ejecutado | R76: - | S76: - | T76: =IFERROR(IF(OR(Q76="Ejecutado",Q76="No corresponde atención OGTI",Q76="Desistido",Q76="-",Q76="Para reformulación"),"-",IF(OR(S76="-",S76=""),"Falta fecha_estado",NETWORKDAYS(S76,TODAY(),{"02/04/2026";"03/04/2026";"30/06/2026"}))),"-") -> - | U76: Contrato | V76: 026-2026-EF/43.03 | W76: 46169 | X76: TAYLOR NETWORKS E.I.R.L | Y76: Anthony Céspedes Molina | Z76: =IFERROR(IF(Q76="-","-",IF(Q76="Proceso de implementación/Activación/Entrega","Proceso de implementación/Activación/Entrega",IF(OR(Q76="Desistido",Q76="No corresponde atención OGTI",Q76="Para reformulación"),Q76,IF(AND(Q76="Ejecutado",AA76="No aplica",AB76="No Aplica"),"Culminado",IF(Q76="Ejecutado",IF(AND(AC76="-",G76="Bienes"),"Culminado",IF(AC76="-","Falta informacion",IF(AND(AB76-TODAY()>=0,AB76-TODAY()<=90),"Vigente_por vencer",IF(AND(AH76<>"SI",AB76<TODAY()),"Culminado",IF(AND(AH76="SI",AB76<TODAY(),OR(AK76="Sin Registro",AL76="Sin Registro")),"Vencido",IF(AND(AH76="SI",AB76<TODAY(),AK76>AA76,AL76>AB76),"Renovado","Vigente")))))),"En tramite"))))),"-") -> Vigente | AA76: 46170 | AB76: 46534 | AC76: =IFERROR(IF(OR(AA76="-",AA76="",AB76="-",AB76=""),"-",CONCATENATE('Seguimiento OIT'!AB76-'Seguimiento OIT'!AA76+1," dias")),"-") -> 365 dias | AD76: =IFERROR(IF(Z76="Vencido",(TODAY()-AB76)+1,"-"),"-") -> - | AE76: - | AF76: - | AG76: https://mefgobpe1.sharepoint.com/:f:/t/DireccindelaOficinadeInfraestructuraTecnolgica/IgBNFoeESGWkSpYPorps2a4YAWBoil3bcT0gNKU7-Whv00A?e=zKkBeZ | AH76: NO | AI76: =IFERROR(IF(AH76="SI",VLOOKUP(A76,$C$4:$AL$151,15,FALSE),"-"),"Sin tramite") -> - | AJ76: =IFERROR(IF(AH76="SI",VLOOKUP(A76,$C$4:$AL$151,7,FALSE),"-"),"Sin HR") -> - | AK76: =IF(AH76="SI",IFERROR(IF(VLOOKUP(A76,$C$4:$AL$151,25,FALSE)="","Sin registro",VLOOKUP(A76,$C$4:$AL$151,25,FALSE)),"Sin registro"),"-") -> - | AL76: =IF(AH76="SI",IFERROR(IF(VLOOKUP(A76,$C$4:$AL$151,26,FALSE)="","Sin registro",VLOOKUP(A76,$C$4:$AL$151,26,FALSE)),"Sin registro"),"-") -> -
A77: REQ-2026-0074 | B77: =IF(OR(Q77="Desistido",Q77="No corresponde Atención OGTI",Q77="Para reformulación",Q77="Paralizado",Q77="-",Z77="Renovado",AND(AH77="NO",Z77="Culminado")),"NO","SI") -> SI | C77: - | D77: NO | E77: Contratación Directa | F77: Nuevo requerimiento | G77: Servicios | H77: Servicio de renovación de soporte técnico y actualización de software de gestión de contenido empresarial - LASERFICHE | I77: 015148-2026 (Requerimiento) | J77: Soporte LaserFiche Rio (25 unidades) | K77: Computo | L77: Rolly Villegas Delgado | M77: Anthony Céspedes Molina | N77: Oficina General de Inversiones y Proyectos | O77: 43910 | P77: 46101 | Q77: Ejecutado | R77: - | S77: - | T77: =IFERROR(IF(OR(Q77="Ejecutado",Q77="No corresponde atención OGTI",Q77="Desistido",Q77="-",Q77="Para reformulación"),"-",IF(OR(S77="-",S77=""),"Falta fecha_estado",NETWORKDAYS(S77,TODAY(),{"02/04/2026";"03/04/2026";"30/06/2026"}))),"-") -> - | U77: Orden de Servicio | V77: 0001267-2026 | W77: 46087 | X77: LINK-SOFT SOLUTIONS S.A.C. | Y77: Anthony Céspedes Molina | Z77: =IFERROR(IF(Q77="-","-",IF(Q77="Proceso de implementación/Activación/Entrega","Proceso de implementación/Activación/Entrega",IF(OR(Q77="Desistido",Q77="No corresponde atención OGTI",Q77="Para reformulación"),Q77,IF(AND(Q77="Ejecutado",AA77="No aplica",AB77="No Aplica"),"Culminado",IF(Q77="Ejecutado",IF(AND(AC77="-",G77="Bienes"),"Culminado",IF(AC77="-","Falta informacion",IF(AND(AB77-TODAY()>=0,AB77-TODAY()<=90),"Vigente_por vencer",IF(AND(AH77<>"SI",AB77<TODAY()),"Culminado",IF(AND(AH77="SI",AB77<TODAY(),OR(AK77="Sin Registro",AL77="Sin Registro")),"Vencido",IF(AND(AH77="SI",AB77<TODAY(),AK77>AA77,AL77>AB77),"Renovado","Vigente")))))),"En tramite"))))),"-") -> Vigente | AA77: 46094 | AB77: 46458 | AC77: =IFERROR(IF(OR(AA77="-",AA77="",AB77="-",AB77=""),"-",CONCATENATE('Seguimiento OIT'!AB77-'Seguimiento OIT'!AA77+1," dias")),"-") -> 365 dias | AD77: =IFERROR(IF(Z77="Vencido",(TODAY()-AB77)+1,"-"),"-") -> - | AE77: - | AF77: Conformidad emitida con HR 063624-2026 | AG77: https://mefgobpe1.sharepoint.com/:f:/t/DireccindelaOficinadeInfraestructuraTecnolgica/IgCKUOh6eb7WT6u4yXs-FljeAUz_cQAYKops0YotIrBgd48?e=dw6Xxx | AH77: NO | AI77: =IFERROR(IF(AH77="SI",VLOOKUP(A77,$C$4:$AL$151,15,FALSE),"-"),"Sin tramite") -> - | AJ77: =IFERROR(IF(AH77="SI",VLOOKUP(A77,$C$4:$AL$151,7,FALSE),"-"),"Sin HR") -> - | AK77: =IF(AH77="SI",IFERROR(IF(VLOOKUP(A77,$C$4:$AL$151,25,FALSE)="","Sin registro",VLOOKUP(A77,$C$4:$AL$151,25,FALSE)),"Sin registro"),"-") -> - | AL77: =IF(AH77="SI",IFERROR(IF(VLOOKUP(A77,$C$4:$AL$151,26,FALSE)="","Sin registro",VLOOKUP(A77,$C$4:$AL$151,26,FALSE)),"Sin registro"),"-") -> -
A78: REQ-2026-0075 | B78: =IF(OR(Q78="Desistido",Q78="No corresponde Atención OGTI",Q78="Para reformulación",Q78="Paralizado",Q78="-",Z78="Renovado",AND(AH78="NO",Z78="Culminado")),"NO","SI") -> SI | D78: NO | E78: Contratación Directa | F78: Nuevo requerimiento | G78: Servicios | H78: Servicio de suscripción de una herramienta de seguridad para la inspección de protocolo HTTP y HTTPS en servicios Web. | I78: 159952-2025 (Requerimiento) | J78: (3) Suscripciones para una herramienta de seguridad para HTTP Y HPTTPS | K78: CSIRT | L78: Samuel Segismundo Ascona Fabian | M78: Samuel Segismundo Ascona Fabian | N78: Oficina de Infraestructura Tecnológica | O78: 28300 | P78: 45882 | Q78: Ejecutado | R78: - | S78: - | T78: =IFERROR(IF(OR(Q78="Ejecutado",Q78="No corresponde atención OGTI",Q78="Desistido",Q78="-",Q78="Para reformulación"),"-",IF(OR(S78="-",S78=""),"Falta fecha_estado",NETWORKDAYS(S78,TODAY(),{"02/04/2026";"03/04/2026";"30/06/2026"}))),"-") -> - | U78: Orden de Servicio | V78: 0003606-2025 | W78: 45901 | X78: IMPERIA SOLUCIONES TECNOLOGICAS S.A.C | Y78: Samuel Segismundo Ascona Fabian | Z78: =IFERROR(IF(Q78="-","-",IF(Q78="Proceso de implementación/Activación/Entrega","Proceso de implementación/Activación/Entrega",IF(OR(Q78="Desistido",Q78="No corresponde atención OGTI",Q78="Para reformulación"),Q78,IF(AND(Q78="Ejecutado",AA78="No aplica",AB78="No Aplica"),"Culminado",IF(Q78="Ejecutado",IF(AND(AC78="-",G78="Bienes"),"Culminado",IF(AC78="-","Falta informacion",IF(AND(AB78-TODAY()>=0,AB78-TODAY()<=90),"Vigente_por vencer",IF(AND(AH78<>"SI",AB78<TODAY()),"Culminado",IF(AND(AH78="SI",AB78<TODAY(),OR(AK78="Sin Registro",AL78="Sin Registro")),"Vencido",IF(AND(AH78="SI",AB78<TODAY(),AK78>AA78,AL78>AB78),"Renovado","Vigente")))))),"En tramite"))))),"-") -> Vigente_por vencer | AA78: 45905 | AB78: 46270 | AC78: =IFERROR(IF(OR(AA78="-",AA78="",AB78="-",AB78=""),"-",CONCATENATE('Seguimiento OIT'!AB78-'Seguimiento OIT'!AA78+1," dias")),"-") -> 366 dias | AD78: =IFERROR(IF(Z78="Vencido",(TODAY()-AB78)+1,"-"),"-") -> - | AE78: Se debe renovar el servicio | AF78: Conformidad emitida con HR 179920-2025 (Constancia de vigencia, acta de activación) | AG78: https://mefgobpe1.sharepoint.com/:f:/t/DireccindelaOficinadeInfraestructuraTecnolgica/IgB3mKwdSVA2T5wKzIHJsWfUAdgF98kQq88aamvh6DryXbs?e=BIBuXh | AH78: NO | AI78: =IFERROR(IF(AH78="SI",VLOOKUP(A78,$C$4:$AL$151,15,FALSE),"-"),"Sin tramite") -> - | AJ78: =IFERROR(IF(AH78="SI",VLOOKUP(A78,$C$4:$AL$151,7,FALSE),"-"),"Sin HR") -> - | AK78: =IF(AH78="SI",IFERROR(IF(VLOOKUP(A78,$C$4:$AL$151,25,FALSE)="","Sin registro",VLOOKUP(A78,$C$4:$AL$151,25,FALSE)),"Sin registro"),"-") -> - | AL78: =IF(AH78="SI",IFERROR(IF(VLOOKUP(A78,$C$4:$AL$151,26,FALSE)="","Sin registro",VLOOKUP(A78,$C$4:$AL$151,26,FALSE)),"Sin registro"),"-") -> -
